Workbook
Name AdministrasiS: GL!$G$2864:$G$2865
Name Aktkeu: GL!$G$2214:$G$2267
Name ASF: GL!$G$2436:$G$2485
Name Audio: GL!$G$1406:$G$1460
Name Bakademik1: GL!$K$842:$K$1089
Name Bakademik2: GL!$G$842:$G$1089
Name BBantuan1: GL!$K$2856:$K$2865
Name BBantuan2: GL!$G$2856:$G$2865
Name BDaksos1: GL!$K$1090:$K$1355
Name BDaksos2: GL!$G$1090:$G$1355
Name BDepresiasi1: GL!$K$2808:$K$2855
Name BDepresiasi2: GL!$G$2808:$G$2855
Name BDukunganAka1: GL!$K$1356:$K$1460
Name BDukunganAka2: GL!$G$1356:$G$1460
Name BeasiswaSa: GL!$G$2862:$G$2863
Name Bimbangankonseling: GL!$G$1703:$G$1752
Name BKegiatanSantri1: GL!$K$1461:$K$2090
Name BKegiatanSantri2: GL!$G$1461:$G$2090
Name BLayananAsrama1: GL!$K$2874:$K$3039
Name BlayananAsrama2: GL!$G$2874:$G$3039
Name BPemeliharaan1: GL!$K$2436:$K$2807
Name BPemeliharaan2: GL!$G$2436:$G$2807
Name BPenjualan1: GL!$K$2866:$K$2873
Name BPenjualan2: GL!$G$2866:$G$2873
Name Buku: GL!$G$2868:$G$2870
Name CDAK1: CD!$I$12:$I$1989
Name CDAK2: CD!$F$12:$F$1989
Name COA: [1]NASo!$A$8:$F$282
Name CRAK1: CR!$I$12:$I$1000
Name CRAK2: CR!$G$12:$G$1000
Name Daksan: GL!$G$2036:$G$2042
Name Dakwah: GL!$G$1090:$G$1149
Name DepB: GL!$G$2808:$G$2816
Name DepEq: GL!$G$2827:$G$2835
Name DepFu: GL!$G$2836:$G$2845
Name DepInf: GL!$G$2817:$G$2826
Name DepLi: GL!$G$2850:$G$2853
Name Depoth: GL!$G$2854:$G$2855
Name Depv: GL!$G$2846:$G$2849
Name DukunganInstitusi1: GL!$K$2091:$K$2435
Name DukunganInstitusi2: GL!$G$2091:$G$2435
Name Executive: GL!$G$2091:$G$2148
Name Humas: GL!$G$1283:$G$1355
Name InformasiTeknologi: GL!$G$2384:$G$2435
Name JMAK1: JM!$I$12:$I$1005
Name JMAK2: JM!$G$12:$G$1005
Name JMAK3: JM!$F$12:$F$1005
Name Jummiyah: GL!$G$1812:$G$2035
Name Keamanan: GL!$G$2700:$G$2753
Name KepengasuhanMA: GL!$G$1621:$G$1702
Name Kepengasuhanmts: GL!$G$1541:$G$1620
Name KepengasuhanSDITQ: GL!$G$1461:$G$1540
Name Kesehatansantri: GL!$G$1753:$G$1811
Name KK: GL!$G$2486:$G$2545
Name KODEAK: CD!$I$12:$I$989
Name Layanankamar: GL!$G$2989:$G$3039
Name layananlaundry: GL!$G$2933:$G$2988
Name Layananmakanan: GL!$G$2874:$G$2932
Name Ledger: '[1]Buku Besar'!$A$7:$J$134
Name Litbang: GL!$G$2149:$G$2213

Sheet IN
A1: PESANTREN ISLAM AL IRSYAD TENGARAN 6 BONDOWOSO
A2: INPUT LAPORAN KEUANGAN
A3: TAHUN PELAJARAN 2025 - 2026 | C3: EDUCATION YEAR 2025 - 2026
C4: =IF($B$5="","","Laporan Keuangan "&TEXT($B$5,"MMMM YYYY")) -> Laporan Keuangan June 2026 | D4: =IF($B$5="","","Financial Statement "&TEXT($B$5,"MMM YYYY")) -> Financial Statement Jun 2026
A5: TANGGAL NERACA | B5: 46203 | C5: =TEXT(_xlnm.Criteria,"dd mmmm yyyy") -> 30 June 2026 | D5: =_xlnm.Criteria -> 46203
A6: AWAL TAHUN PELAJARAN | B6: 45839
A7: AKHIR TAHUN PELAJARAN | B7: 46203
C8: =TEXT(B9,"dd mmmm yyyy") -> 31 May 2026 | D8: =B9 -> 46173
A9: PERBANDINGAN DENGAN | B9: =IF(_xlnm.Criteria=0,"",EOMONTH($B$5,-1)) -> 46173 | C9: =IF(C8="","","(Dengan perbandingan informasi keuangan untuk bulan yang berakhir "&TEXT(C8,"DD MMMM YYYY")&" /") -> (Dengan perbandingan informasi keuangan untuk bulan yang berakhir 31 May 2026 /
C10: =IF(D8="","","With Comparative financial information for the month ended "&TEXT(D8,"MMM DD, YYYY")&" )") -> With Comparative financial information for the month ended May 31, 2026 )

Sheet Cover Dp
L1: 1
A24: PESANTREN ISLAM AL-IRSYAD
A25: TENGARAN 6 - BONDOWOSO
A29: LAPORAN KEUANGAN / FINANCIAL STATEMENTS
A30: =IN!A3 -> TAHUN PELAJARAN 2025 - 2026 | F30: / | G30: =IN!C3 -> EDUCATION YEAR 2025 - 2026
A31: Untuk Bulan yang Berakhir / For the Month Ended
A32: =IN!C5 -> 30 June 2026 | F32: / | G32: =IN!D5 -> 46203
A33: =IN!C9 -> (Dengan perbandingan informasi keuangan untuk bulan yang berakhir 31 May 2026 /
A34: =IN!C10 -> With Comparative financial information for the month ended May 31, 2026 )

Sheet Cover Blkg
K1: 1
A41: PESANTREN ISLAM AL-IRSYAD
A42: TENGARAN 6 - BONDOWOSO
A46: =IN!C4 -> Laporan Keuangan June 2026 | F46: =IN!D4 -> Financial Statement Jun 2026

Sheet TC
B12: PESANTREN ISLAM AL-IRSYAD, TENGARAN
B14: Laporan Keuangan / Financial Statements
B15: Untuk Bulan yang Berakhir / For the Month Ended
F16: =IN!C5 -> 30 June 2026 | O16: / | P16: =IN!D5 -> 46203
B17: =IN!C9 -> (Dengan perbandingan informasi keuangan untuk bulan yang berakhir 31 May 2026 /
B18: =IN!C10 -> With Comparative financial information for the month ended May 31, 2026 )
B21: Daftar isi | M21: Halaman / Page | V21: Table contents
B23: Kata pengantar dari manajemen | M23: …………………………………………………. | Q23: …………………………………………………. | AF23: Message from the management | AI23: =IF(AH23="ok",1,"")
B24: Grafik perubahan aset bersih tidak terikat | M24: ……………………………………… | O24: 1 | Q24: …………………………………. | AF24: Graphic of changes in unrestricted net assets | AI24: =IF(AH24="ok",1,"")
B25: Laporan posisi keuangan | M25: ………………………………………………………. | O25: 2 | Q25: …………………………………………………. | AF25: Statements of financial position | AI25: =IF(AH25="ok",1,"")
B26: Laporan pendapatan, beban dan perubahan aset bersih tidak terikat | M26: …… | O26: 3 | AF26: ...Statements of revenues, expenses and changes in unrestricted net assets | AI26: =IF(AH26="ok",1,"")
B27: Laporan perubahan aset bersih | M27: ………………………………………………. | O27: 4 | Q27: ……………………………………………. | AF27: Statements of changes in net assets | AI27: =IF(AH27="ok",1,"")
B28: Laporan arus kas | M28: ………………………………………………………………….. | O28: 5 | Q28: ………………………………………………………………… | AF28: Statements of cash flow | AI28: =IF(AH28="ok",1,"")
B29: Catatan atas laporan keuangan | M29: …………………………………………………. | N29: 6 - 16 | Q29: ……………………………………………………. | AF29: Notes to financial statements | AI29: =IF(AH29="ok",1,"")
B30: Informasi tambahan | AF30: Supplementary information | AI30: =IF(AH30="ok",1,"")
B31: Lampiran 1 | E31: Rincian piutang uang pendidikan | M31: ………………………………….. | N31: 17 - 26 | Q31: ………………………………. | AC31: Details of tuition and fee receivable | AF31: Appendix 1 | AI31: =IF(AH31="ok",1,"")
B32: Lampiran 2 | E32: Rincian piutang lain lain | M32: ………………………………………….. | N32: 27 - 26 | Q32: …………………………………….. | AC32: Details of others receivables | AF32: Appendix 2 | AI32: =IF(AH32="ok",1,"")
B33: Lampiran 3 | E33: Rincian persediaan | M33: ……………………………………………… | N33: 27 - 29 | Q33: ………………………………………………. | AC33: Details of inventories | AF33: Appendix 3 | AI33: =IF(AH33="ok",1,"")
B34: Lampiran 4 | E34: Rincian aset tetap | M34: …………………………………………… | N34: 30 - 40 | Q34: ………………………………………………. | AC34: Details of fixed assets | AF34: Appendix 4 | AI34: =IF(AH34="ok",1,"")
B35: Lampiran 5 | E35: Rincian titipan uang pendidikan | M35: ……………………………………. | N35: 41 - 43 | Q35: …………………………………. | AC35: Details of tuition and fee deposits | AF35: Appendix 5 | AI35: =IF(AH35="ok",1,"")
B36: Lampiran 6 | E36: Rincian titipan lain lain | M36: …………………………………………… | N36: 44 - 49 | Q36: …………………………………………. | AC36: Details of other deposits | AF36: Appendix 6 | AI36: =IF(AH36="ok",1,"")
B37: Lampiran 7 | E37: Rincian hutang lain lain | M37: …………………………………………… | O37: 50 | Q37: …………………………………………. | AC37: Details of other paybles | AF37: Appendix 7 | AI37: =IF(AH37="ok",1,"")
E38: Rincian biaya masih harus dibayar | M38: …………………………………………… | O38: 51 | Q38: …………………………………………. | AC38: Details of accrued expenses | AI38: =IF(AH38="ok",1,"")
B39: Lampiran 8 | E39: Rincian aset bersih terikat | M39: ………………………………………….. | O39: 52 | Q39: ……………………………………. | AC39: Details of restricted net assets | AF39: Appendix 8 | AI39: =IF(AH39="ok",1,"")
B40: Lampiran 9 | E40: Rincian pendapatan dan keuntungan tidak terikat | M40: ………………………………………….. | O40: 53 | Q40: ………………….. | AC40: Details of unrestricted revenues and gains | AF40: Appendix 9 | AI40: =IF(AH40="ok",1,"")
B41: Lampiran 10 | E41: Rincian beban dan kerugian | M41: ………………………………………….. | O41: 54 | Q41: …………………………………….. | AC41: Details of expenses and loss | AF41: Appendix 10 | AI41: =IF(AH41="ok",1,"")
B42: Lampiran 11 | E42: Rincian beban dan kerugian menurut klasifikasi sifat | AC42: Details of expenses and loss by natural classification | AF42: Appendix 11 | AI42: =IF(AH42="ok",1,"")
E43: dengan fungsional | M43: ……………………………………………….. | N43: 55 - 56 | Q43: ……………………………………… | AC43: with fuctional classification | AI43: =IF(AH43="ok",1,"")
B44: Informasi tambahan untuk usaha pelengkap | AF44: Supplementary information for auxiliary enterprises | AI44: =IF(AH44="ok",1,"")
B45: Lampiran 12 | E45: Laporan posisi keuangan usaha pelengkap | M45: ……………………….. | O45: 57 | Q45: ……….. | AC45: Statements of auxiliary enterprises financial position | AF45: Appendix 12 | AI45: =IF(AH45="ok",1,"")
B46: Lampiran 13 | E46: Rincian pendapatan dan beban usaha pelengkap | M46: …………….. | O46: 58 | Q46: ……. | AC46: Details of auxiliary enterprises revenues and expenses | AF46: Appendix 13 | AI46: =IF(AH46="ok",1,"")
B47: Lampiran 14 | E47: Rincian posisi keuangan - usaha pelengkap | M47: ……………………….. | N47: 59 - 63 | AC47: ….Details of statement financial position - auxiliary enterprises | AF47: Appendix 14 | AI47: =IF(AH47="ok",1,"")
B48: Lampiran 15 | E48: Rincian piutang pembiayaan 1 - usaha pelengkap | M48: …………….. | O48: 64 | AC48: Details of financing 1 account receivable - auxiliary enterprises | AF48: Appendix 15 | AI48: =IF(AH48="ok",1,"")
B49: Lampiran 16 | E49: Rincian piutang pembiayaan 2 - usaha pelengkap | M49: …………….. | O49: 65 | AC49: Details of financing 2 account receivable - auxiliary enterprises | AF49: Appendix 16 | AI49: =IF(AH49="ok",1,"")
B50: Lampiran 17 | E50: Rincian aset tetap - usaha pelengkap | M50: ……………………….. | N50: 66 - 67 | Q50: ………………….. | AC50: Details of fixed assets - auxiliary enterprises | AF50: Appendix 17 | AI50: =IF(AH50="ok",1,"")
B51: Lampiran 18 | E51: Rincian titipan simpanan anggota - usaha pelengkap | M51: …………….. | O51: 68 | AC51: ....Details of member's saving deposit - auxiliary enterprises | AF51: Appendix 18 | AI51: =IF(AH51="ok",1,"")
B52: Lampiran 19 | E52: Rincian hutang usaha Amin Mart - usaha pelengkap | M52: …………….. | O52: 70 | AC52: ...Details of Amin Mart account payables auxiliary enterprises | AF52: Appendix 19 | AI52: =IF(AH52="ok",1,"")
B53: Halaman kosong | M53: …………………………………………………………………. | O53: 71 | Q53: ………………………………………………………………………………. | AF53: Blank page | AI53: =IF(AH53="ok",1,"")
AI54: =SUM(AI23:AI53) -> 0
B55: Kata pengantar dari manajemen | M55: …………………………………………………. | Q55: …………………………………………………. | AF55: Message from the management
B56: Grafik perubahan aset bersih tidak terikat | M56: ……………………………………… | O56: 1 | Q56: …………………………………. | AF56: Graphic of changes in unrestricted net assets
B57: Laporan posisi keuangan | M57: ………………………………………………………. | O57: 2 | Q57: …………………………………………………. | AF57: Statements of financial position
B58: Laporan pendapatan, beban dan perubahan aset bersih tidak terikat | M58: …… | O58: 3 | AF58: ...Statements of revenues, expenses and changes in unrestricted net assets
B59: Laporan perubahan aset bersih | M59: ………………………………………………. | O59: 4 | Q59: ……………………………………………. | AF59: Statements of changes in net assets
B60: Laporan arus kas | M60: ………………………………………………………………….. | O60: 5 | Q60: ………………………………………………………………… | AF60: Statements of cash flow
B61: Catatan atas laporan keuangan | M61: …………………………………………………. | N61: 6 - 17 | Q61: ……………………………………………………. | AF61: Notes to financial statements
B62: Informasi tambahan untuk usaha pelengkap | AF62: Supplementary information for auxiliary enterprises
B63: Laporan posisi keuangan usaha pelengkap | M63: ………………………................. | O63: 18 | Q63: …………………........ | AF63: Statements of auxiliary enterprises financial position
B64: Rincian pendapatan dan beban usaha pelengkap | M64: ……………....................... | O64: 19 | Q64: ……………............ | AF64: Details of auxiliary enterprises revenues and expenses
B65: Halaman kosong | M65: …………………………………………………………………. | O65: 20 | Q65: ………………………………………………………………………………. | AF65: Blank page

Sheet Grafik
A1: =IN!A1 -> PESANTREN ISLAM AL IRSYAD TENGARAN 6 BONDOWOSO
A3: II. GRAFIK PERUBAHAN ASET BERSIH TIDAK TERIKAT / GRAPHIC OF CHANGES IN UNRESTRICTED NET ASSETS
A45: Tahun pendidikan 2025 - 2026 (Juli 2025 - Juni 2026) / Education Year 2025- 2026 (July 2025 - June 2026)
A46: Uraian / | C46: Juli 2025 / | D46: Agustus 2025 / | E46: September 2025 / | F46: Oktober 2025/ | G46: Nopember 2025 / | H46: Desember 2025 / | I46: Januari 2026 / | J46: Februari 2026 / | K46: Maret 2026 / | L46: April 2026 / | M46: Mei 2026 / | N46: Juni 2026 / | O46: Jumlah /
A47: Description | C47: July 2025 | D47: August 2025 | E47: September 2025 | F47: October 2025 | G47: November 2025 | H47: December 2025 | I47: January 2026 | J47: February 2026 | K47: March 2026 | L47: April 2026 | M47: May 2026 | N47: June 2026 | O47: Total
A48: Pendapatan, keuntungan & dukungan lain / | B48: 0
A49: Revenues, gains & others support | B49: 0 | C49: 2944636096 | D49: 1010692073 | E49: 943787100 | F49: 1083368899 | G49: 1097743827 | H49: 812104650 | I49: 1445806630 | J49: 7.4180451e+08 | K49: 630681247 | L49: 707461450 | M49: 801827018 | N49: =LR!E58 -> 641150550 | O49: =SUM(C49:N49) -> 1.2861064e+10
A50: Beban & kerugian / | B50: 0
A51: Expenses & losses | B51: 0 | C51: 6.3391583e+08 | D51: 9.7570735e+08 | E51: 1.0586135e+09 | F51: 1.104388e+09 | G51: 7.6123705e+08 | H51: 7.1287737e+08 | I51: 7.4123915e+08 | J51: 8.0452115e+08 | K51: 9.5874558e+08 | L51: 7.4904215e+08 | M51: 9.5371266e+08 | N51: =LR!E75 -> 6.6987422e+08 | O51: =SUM(C51:N51) -> 1.0123874e+10
A52: Kenaikan ( penurunan ) /
A53: Increase ( decrease ) | B53: 0 | C53: =C49-C51 -> 2.3107203e+09 | D53: =D49-D51 -> 34984718 | E53: =E49-E51 -> -1.1482641e+08 | F53: =F49-F51 -> -21019071 | G53: =G49-G51 -> 3.3650677e+08 | H53: =H49-H51 -> 99227278 | I53: =I49-I51 -> 7.0456748e+08 | J53: =J49-J51 -> -62716636 | ... O53: =O49-O51 -> 2.7371901e+09
O54: ='[2]LR '!J82-O53 -> 2.0558689e+09
A64: =IN!C4 -> Laporan Keuangan June 2026 | H64: 1 | O64: =IN!D4 -> Financial Statement Jun 2026

Sheet NRC
B2: PESANTREN ISLAM AL-IRSYAD TENGARAN 6 BONDOWOSO
B4: LAPORAN POSISI KEUANGAN | K4: STATEMENTS OF FINANCIAL POSITION
B5: =IN!C5 -> 30 June 2026 | I5: =IN!D5 -> 46203
C6: =IN!C9 -> (Dengan perbandingan informasi keuangan untuk bulan yang berakhir 31 May 2026 / | K6: =IN!C10 -> With Comparative financial information for the month ended May 31, 2026 )
B7: (Disajikan dalam rupiah) | K7: (Expressed in rupiah)
B9: Pos - pos | E9: =IN!C5&"/" -> 30 June 2026/ | F9: Catatan / | G9: =IN!C8&"/" -> 31 May 2026/ | H9: Kenaikan/Penurunan | I9: Accounts
E10: =IN!D5 -> 46203 | F10: Notes | G10: =IN!D8 -> 46173
C11: Aset | J11: Assets
C12: Aset Lancar | J12: Current Assets
C13: Kas dan setara kas | E13: =CLK!Q152 -> 3.1284258e+09 | F13: 2 | G13: =CLK!X152 -> 3.0051166e+09 | H13: =E13-G13 -> 123309192 | J13: Cash and Cash Equivalents
C14: Piutang aktivitas - bersih | F14: 3 | J14: Account receivable - net
C15: אּ | D15: Piutang uang pendidikan - bersih | E15: =CLK!Q170 -> 847774000 | G15: =CLK!X170 -> 830206000 | H15: =E15-G15 -> 17568000 | I15: Tuition & fee receivable - net | J15: אּ
C16: אּ | D16: Piutang sumbangan - bersih | E16: =CLK!Q184 -> 0 | G16: =CLK!X184 -> 0 | H16: =E16-G16 -> 0 | I16: Contributions receivable - net | J16: אּ
C17: אּ | D17: Piutang usaha pelengkap - bersih | E17: =CLK!Q202 -> 140077350 | G17: =CLK!X202 -> 73712800 | H17: =E17-G17 -> 66364550 | I17: Auxiliary enterprises receiable net | J17: אּ
E18: =SUM(E15:E17) -> 987851350 | G18: =SUM(G15:G17) -> 903918800 | H18: =E18-G18 -> 83932550 | L18: =[3]NRC!$E$18 -> 1014166450 | M18: =L18-G18 -> 110247650
C19: Piutang lain lain - bersih | E19: =CLK!Q222 -> 78023804 | F19: 4 | G19: =CLK!X222 -> 71027505 | H19: =E19-G19 -> 6996298.2 | J19: Others receivables - net
C20: Persediaan | E20: =CLK!Q249 -> 206952262 | F20: 5 | G20: =CLK!X249 -> 224288070 | H20: =E20-G20 -> -17335808 | J20: Inventories
C21: Pajak dibayar dimuka | E21: =CLK!Q264 -> 0 | G21: =CLK!X264 -> 0 | H21: 0 | J21: Prepaid tax
C22: Uang muka | E22: =CLK!Q308 -> 32400000 | G22: =CLK!X308 -> 32400000 | H22: =E22-G22 -> 0 | J22: Advance payments
C23: Beban dibayar dimuka | E23: =CLK!Q322 -> 9166665.7 | G23: =CLK!X322 -> 10833332 | H23: =E23-G23 -> -1666666.7 | J23: Prepaid expenses
C25: Jumlah Aset Lancar | E25: =E13+E18+E19+E20+E21+E22+E23 -> 4.4428198e+09 | G25: =G13+G18+G19+G20+G21+G22+G23 -> 4.2475843e+09 | H25: =E25-G25 -> 1.9523557e+08 | J25: Total Current Assets | L25: =[3]NRC!$E$25 -> 3.0301104e+09 | M25: =L25-G25 -> -1.2174739e+09 | N25: ='20'!H25 -> 4.4428198e+09 | O25: =E25-N25 -> 0
C26: Aset Tidak Lancar | J26: Non Current Assets
C27: Investasi pada unit usaha pesantren | J27: Investment in Auxiliary Enterprises
C28: Aset tetap - bersih | J28: Fixed assets - net
C29: אּ | D29: Harga Perolehan | E29: =CLK!AF347 -> 2.2996453e+10 | F29: 8 | G29: =CLK!AF382 -> 2.2988954e+10 | H29: =E29-G29 -> 7499000 | I29: Acquisition cost | J29: אּ
C30: אּ | D30: Akumulasi Penyusutan | E30: =-CLK!AF358 -> -3.7406288e+09 | F30: 8 | G30: =-CLK!AF394 -> -3.64738e+09 | H30: =E30-G30 -> -93248822 | I30: Accumulated depreciation | J30: אּ
E31: =SUM(E29:E30) -> 1.9255825e+10 | G31: =SUM(G29:G30) -> 1.9341574e+10 | H31: =E31-G31 -> -85749822 | L31: =[3]NRC!$E$34 -> 1.8772845e+10 | M31: =L31-G31 -> -5.687297e+08
C32: Aset lain lain | E32: =CLK!Q434 -> 10130900 | G32: =CLK!X434 -> 9899400 | H32: =E32-G32 -> 231500 | J32: Other assets
C34: Jumlah Aset Tidak Lancar | E34: =E32+E31+E27 -> 1.9265955e+10 | G34: =G32+G31+G27 -> 1.9351474e+10 | H34: =E34-G34 -> -85518322 | J34: Total Non Current Assets | N34: ='20'!H34 -> 1.9265955e+10 | O34: =E34-N34 -> 0.4600029
B36: Jumlah Aset | E36: =E34+E25 -> 2.3708775e+10 | G36: =G34+G25 -> 2.3599058e+10 | H36: =E36-G36 -> 1.0971724e+08 | I36: Total Assets | L36: =[3]NRC!$E$36 -> 2.1802955e+10 | M36: =L36-G36 -> -1.796103e+09
C37: Liabilitas dan Aset Bersih | J37: Liabilities and Net Assets
C38: Liabilitas Lancar | J38: Current Liabilities
C39: Hutang aktivitas | J39: Account payble
C40: אּ | D40: Hutang pendidikan | E40: =CLK!Q456 -> 127867575 | G40: =CLK!X448 -> 23819342 | H40: =E40-G40 -> 104048233 | I40: Education payble | J40: אּ
C41: אּ | D41: Hutang usaha pelengkap | E41: =CLK!Q464 -> 0 | G41: =CLK!X464 -> 0 | H41: =E41-G41 -> 0 | I41: Auxiliary enterprises payble | J41: אּ
C42: אּ | D42: Hutang perolehan aset tetap | E42: =CLK!Q472 -> 0 | G42: =CLK!X472 -> 0 | H42: 0 | I42: Fixed assets acquisition payble | J42: אּ
E43: =SUM(E40:E42) -> 127867575 | G43: =SUM(G40:G42) -> 23819342 | H43: 0
C44: Hutang titipan | J44: Deposit paybles
C45: אּ | D45: Titipan uang pendidikan | E45: =CLK!Q488 -> 178972000 | F45: 11 | G45: =CLK!X488 -> 121652000 | H45: =E45-G45 -> 57320000 | I45: Tuition & fee deposits | J45: אּ
C46: אּ | D46: Tabungan santri | E46: =CLK!Q491 -> 85600 | F46: 11 | G46: =CLK!X491 -> 101107200 | H46: =E46-G46 -> -101021600 | I46: Student saving | J46: אּ
C47: אּ | D47: Titipan usaha pelengkap | E47: 0 | G47: 0 | I47: Auxiliary enterprises deposit | J47: אּ
C48: אּ | D48: Titipan - lain lain | E48: =CLK!Q506 -> 255093228 | G48: =CLK!X506 -> 176057228 | H48: =E48-G48 -> 79036000 | I48: Others deposits | J48: אּ | N48: Likuiditas
E49: =SUM(E45:E48) -> 434150828 | G49: =SUM(G45:G48) -> 398816428 | H49: =E49-G49 -> 35334400 | L49: =[3]NRC!$E$49 -> 462655588 | M49: =L49-G49 -> 63839160 | N49: Rasio Lancar | O49: =SUM(E13:E15)/E61 -> 2.0266787 | Q49: Min | R49: 1
C50: Hutang lain lain | E50: =CLK!Q527 -> 370022227 | G50: =CLK!X527 -> 370022227 | J50: Other paybles | N50: Rasio Kas | O50: =E13/E61 -> 1.5945662 | Q50: Min | R50: 1
C51: Hutang pajak | E51: =CLK!Q540 -> 0 | G51: =CLK!X540 -> 0 | J51: Tax payble
C52: Pendapatan diterima dimuka | E52: =CLK!Q555 -> 783200000 | G52: =CLK!X555 -> 780600000 | H52: =E52-G52 -> 2600000 | J52: Unearned Revenue
C53: Biaya masih harus dibayar | E53: =CLK!Q572 -> 2.4668843e+08 | G53: =CLK!X572 -> 2.3665195e+08 | H53: =E53-G53 -> 10036480 | J53: Accrued expenses
C55: Jumlah Liabilitas Lancar | E55: =E43+E49+E50+E51+E52+E53 -> 1.9619291e+09 | G55: =G53+G50+G49+G43+G51+G52 -> 1.8099099e+09 | H55: =E55-G55 -> 1.5201911e+08 | J55: Total Current Liabilities | L55: =[3]NRC!$E$55 -> 6.9561293e+08 | M55: =L55-G55 -> -1.114297e+09 | N55: ='20'!H46 -> 1.9619291e+09 | O55: =E55-N55 -> 0
C56: Liabilitas Tidak Lancar | J56: Non Current Liabilities
C57: אּ | D57: Pinjaman jangka panjang | E57: =CLK!Q581 -> 0 | G57: =CLK!X581 -> 0 | I57: Long term loan | J57: אּ
C58: אּ | D58: LIABILITAS imbalan paska kerja | E58: 0 | G58: 0 | H58: 0 | I58: Retirement benenfit obligation | J58: אּ
C59: Jumlah Liabilitas Tidak Lancar | E59: =SUM(E57:E58) -> 0 | G59: =SUM(G57:G58) -> 0 | H59: 0 | J59: Total Non Current Liabilities
C61: Jumlah Liabilitas | E61: =E59+E55 -> 1.9619291e+09 | G61: =G59+G55 -> 1.8099099e+09 | H61: =E61-G61 -> 1.5201911e+08 | J61: Total Liabilities
C62: Aset Bersih | J62: Net Assets | N62: Solvabilitas
C63: Aset bersih tidak terikat | J63: Unrestricted net assets | N63: Rasio Utang terhadap Aset | O63: =E61/E36 -> 0.082751177 | Q63: Mak | R63: 0.5
C64: אּ | D64: Tidak ditentukan penggunaanya | E64: =CLK!AA607 -> 1.0076428e+09 | G64: =CLK!AA702 -> 9.5549653e+08 | H64: =E64-G64 -> 52146265 | I64: Unappropriated | J64: אּ | N64: Rasio Utang terhadap Ekuitas | O64: =E61/E74 -> 0.090216716 | Q64: Mak | R64: 0.5
C65: אּ | D65: Usaha pelengkap | E65: =CLK!AA626 -> 5.0914978e+08 | G65: =CLK!O626 -> 5.0426989e+08 | H65: =E65-G65 -> 4879888.3 | I65: Auxiliary enterprises | J65: אּ | L65: =[3]NRC!$E$65 -> 4.2156034e+08 | M65: =L65-G65 -> -82709548
C66: אּ | D66: Dana gedung | E66: =CLK!AA642 -> -1.5612114e+09 | G66: =CLK!AA736 -> -1.5612114e+09 | H66: =E66-G66 -> 0 | I66: Building fund | J66: אּ
C67: אּ | D67: Diinvestasikan dalam aset tetap - bersih | E67: =CLK!AA651 -> 1.5015558e+10 | G67: =CLK!O651 -> 1.5101307e+10 | H67: =E67-G67 -> -85749822 | I67: Net - investment in fixed assets | J67: אּ
E68: =SUM(E63:E67) -> 1.4971139e+10 | G68: =SUM(G63:G67) -> 1.4999862e+10 | H68: =E68-G68 -> -28723668 | L68: =[3]NRC!$E$68 -> 1.4579642e+10 | M68: =L68-G68 -> -4.2022025e+08 | N68: ='20'!F69 -> 1.4461989e+10 | O68: =E68-N68 -> 5.0914978e+08
C69: Aset bersih terikat | H69: =E69-G69 -> 0 | J69: Restricted net assets
C70: אּ | D70: Terikat temporer | E70: =CLK!X785 -> 337644500 | G70: =CLK!I785 -> 351222700 | H70: =E70-G70 -> -13578200 | I70: Temporarily restricted | J70: אּ | N70: ='20'!F70 -> 337644500 | O70: =E70-N70 -> 0
C71: אּ | D71: Terikat permanen | E71: =CLK!X792 -> 6438063087 | G71: =CLK!I792 -> 6438063087 | H71: =E71-G71 -> 0 | I71: Permanently restricted | J71: אּ | N71: ='20'!F71 -> 6438063087 | O71: =E71-N71 -> 0
E72: =SUM(E70:E71) -> 6775707587 | G72: =SUM(G70:G71) -> 6789285787 | H72: =E72-G72 -> -13578200 | L72: =[3]NRC!$E$72 -> 6527700087 | M72: =L72-G72 -> -261585700
H73: =E73-G73 -> 0
C74: Jumlah Aset Bersih | E74: =E72+E68 -> 2.1746846e+10 | G74: =G72+G68 -> 2.1789148e+10 | H74: =E74-G74 -> -42301868 | J74: Total Net Assets | N74: ='20'!H74 -> 2.1746846e+10 | O74: =E74-N74 -> 0.4600029
C76: Jumlah Liabilitas dan Aset Bersih | E76: =E74+E61 -> 2.3708775e+10 | G76: =G74+G61 -> 2.3599058e+10 | H76: =E76-G76 -> 1.0971724e+08 | J76: Total Liabilities and Net Assets | N76: ='20'!H76 -> 2.3708775e+10 | O76: =E76-N76 -> 0.46000671
E77: =E36-E76+0.4-0.7-0.81+0.35 -> 0.00052856445 | G77: =G76-G36+0.4+0.72 -> 0.0031863403
B79: =IN!C4 -> Laporan Keuangan June 2026 | F79: 2 | K79: =IN!D4 -> Financial Statement Jun 2026
E81: =+E77 -> 0.00052856445 | G81: =+G77 -> 0.0031863403
G84: =G68+H68 -> 1.4971139e+10
G85: =G72+H72 -> 6775707587

Sheet LR
B2: PESANTREN ISLAM AL IRSYAD TENGARAN 6 BONDOWOSO
B4: LAPORAN PENDAPATAN, BEBAN DAN | O4: STATEMENTS OF REVENUES, EXPENSES AND
B5: PERUBAHAN ASET BERSIH TIDAK TERIKAT | O5: CHANGES IN UNRESTRICTED NET ASSETS
C6: ="Untuk Bulan yang Berakhir "&NRC!B5 -> Untuk Bulan yang Berakhir 30 June 2026 | I6: ="For The Month Ended "&TEXT(IN!D5,"MMM YYYY") -> For The Month Ended Jun 2026
C7: =NRC!C6 -> (Dengan perbandingan informasi keuangan untuk bulan yang berakhir 31 May 2026 / | O7: =IN!C10 -> With Comparative financial information for the month ended May 31, 2026 )
O8: =[4]IN!K31 -> #N/A
B9: (Disajikan dalam rupiah) | O9: (Expressed in rupiah)
C11: Pos - pos | E11: =NRC!E9 -> 30 June 2026/ | F11: % | G11: Catatan / | H11: =NRC!G9 -> 31 May 2026/ | I11: % | J11: Selisih | K11: ="sd "&(E11) -> sd 30 June 2026/ | L11: % | M11: Accounts | P11: Catatan / | Q11: Catatan / | R11: ="sd "&(H11) -> sd 31 May 2026/
E12: =NRC!E10 -> 46203 | G12: Notes | H12: =NRC!G10 -> 46173 | K12: =NRC!E10 -> 46203 | P12: Notes | Q12: Notes | R12: =H12 -> 46173
C13: Pendapatan dan keuntungan tidak terikat | N13: Unrestricted revenues & gains
C14: Pendapatan uang pendidikan | N14: Tuition and fees
C15: אּ | D15: SPP | E15: ='9'!D15 -> 547400000 | H15: ='9'!G15 -> 552500000 | J15: =E15-H15 -> -5100000 | K15: =E15+R15 -> 6692650000 | M15: Tuition | N15: אּ | R15: 6145250000
C16: אּ | D16: Ekstrakurikuler | E16: ='9'!D16 -> 0 | H16: ='9'!G16 -> 0 | K16: =E16+R16 -> 0 | M16: Extra curriculer | N16: אּ | R16: 0
C17: אּ | D17: Ujian akhir semester | E17: ='9'!D17 -> 0 | H17: ='9'!G17 -> 0 | K17: =E17+R17 -> 0 | M17: Examination fee | N17: אּ | R17: 0
C18: אּ | D18: Daftar ulang | E18: ='9'!D18 -> 0 | H18: ='9'!G18 -> 0 | K18: =E18+R18 -> 578289000 | M18: Enrollment fee | N18: אּ | R18: 578289000
C19: אּ | D19: Dana pengembangan | E19: ='9'!D19 -> 0 | H19: ='9'!G19 -> 0 | J19: =E19-H19 -> 0 | K19: =E19+R19 -> 1207500000 | M19: Deveopment fund | N19: אּ | R19: 1207500000
C20: אּ | D20: Kegiatan santri | E20: ='9'!D20 -> 0 | H20: ='9'!G20 -> 0 | J20: =E20-H20 -> 0 | K20: =E20+R20 -> 74100000 | M20: Student activity | N20: אּ | R20: 74100000
C21: אּ | D21: Pendaftaran santri baru | E21: ='9'!D21 -> 0 | H21: ='9'!G21 -> 0 | J21: =E21-H21 -> 0 | K21: =E21+R21 -> 22500000 | M21: Admission fee | N21: אּ | R21: 22500000
E22: =SUM(E15:E21) -> 547400000 | H22: =SUM(H15:H21) -> 552500000 | J22: =E22-H22 -> -5100000 | K22: =SUM(K15:K21) -> 8575039000 | R22: 8027639000
C23: אּ | D23: Dikurangi : Potongan Pendidikan | E23: =-'9'!D24 -> -3950000 | H23: =-'9'!G24 -> -4200000 | J23: =E23-H23 -> 250000 | K23: =E23+R23 -> -70768000 | M23: Less : scholarship | N23: אּ | R23: -66818000
E24: =SUM(E22:E23) -> 543450000 | H24: =SUM(H22:H23) -> 548300000 | J24: =E24-H24 -> -4850000 | K24: =SUM(K22:K23) -> 8504271000 | R24: 7960821000
C25: Bantuan | E25: ='9'!D36 -> 1000100 | H25: ='9'!G36 -> 168 | J25: =E25-H25 -> 999932 | K25: =E25+R25 -> 1031304.3 | L25: =K25/$K$58*100 -> 0.0080188103 | N25: Contributions | R25: 31204.33
C26: Sumbangan | J26: =E26-H26 -> 0 | K26: =E26+R26 -> 0 | L26: =K26/$K$58*100 -> 0 | N26: Grants | R26: 0
C27: Penjualan & layanan | E27: ='9'!D44 -> 50000 | H27: ='9'!G44 -> 414950 | J27: =E27-H27 -> -364950 | K27: =E27+R27 -> 10914450 | L27: =K27/$K$58*100 -> 0.084864285 | N27: Sales & services | R27: 10864450
C28: Penghasilan investasi | E28: 0 | H28: 0 | J28: =E28-H28 -> 0 | K28: =E28+R28 -> 0 | L28: =K28/$K$58*100 -> 0 | N28: Investment income | R28: 0
C29: Usaha pelengkap | J29: =E29-H29 -> 0 | K29: =E29+R29 -> 0 | L29: =K29/$K$58*100 -> 0 | N29: Auxiliary enterprises | R29: 0
C30: אּ | D30: Kantin 6 Mart | E30: ='9'!D47 -> 82572250 | H30: ='9'!G47 -> 129992100 | J30: =E30-H30 -> -47419850 | K30: =E30+R30 -> 1332016556 | L30: =K30/$K$58*100 -> 10.35697 | M30: Financing | N30: אּ | R30: 1249444306
C31: אּ | D31: Wartel | E31: 0 | H31: 0 | J31: =E31-H31 -> 0 | K31: =E31+R31 -> 0 | L31: =K31/$K$58*100 -> 0 | M31: Telphone cabin | N31: אּ | R31: 0
C32: אּ | D32: Kanten | E32: 0 | H32: 0 | J32: =E32-H32 -> 0 | K32: =E32+R32 -> 0 | L32: =K32/$K$58*100 -> 0 | M32: Canteen | N32: אּ | R32: 0
C33: אּ | D33: Foto copy | E33: 0 | H33: 0 | J33: =E33-H33 -> 0 | K33: =E33+R33 -> 0 | L33: =K33/$K$58*100 -> 0 | M33: Foto copy | R33: 0
C34: אּ | D34: Toko | E34: 0 | H34: 0 | J34: =E34-H34 -> 0 | K34: =E34+R34 -> 0 | L34: =K34/$K$58*100 -> 0 | M34: Barber shop | N34: אּ | R34: 0
C35: אּ | D35: Kantor | E35: ='[4]9'!E41+'[4]9'!E42 -> 0 | H35: 0 | J35: =E35-H35 -> 0 | K35: =E35+R35 -> 0 | L35: =K35/$K$58*100 -> 0 | M35: Office | N35: אּ | R35: 0
E36: =SUM(E30:E35) -> 82572250 | H36: =SUM(H30:H35) -> 129992100 | J36: =E36-H36 -> -47419850 | K36: =SUM(K30:K35) -> 1332016556 | R36: 1249444306
C37: Penghasilan lain lain & keuntungan | J37: =E37-H37 -> 0 | N37: Others income & gains
C38: אּ | D38: Keuntungan pelepasan Aset tetap | E38: 0 | H38: 0 | J38: =E38-H38 -> 0 | K38: =E38+R38 -> 0 | M38: Gains on disposal of fixed assets | N38: אּ | R38: 0
C39: אּ | D39: Keuntungan penjualan investasi | E39: 0 | H39: 0 | J39: =E39-H39 -> 0 | K39: =E39+R39 -> 0 | M39: Loss on sale invesment | N39: אּ | R39: 0
C40: אּ | D40: Keuntungan selisih kurs & lain-lain | E40: 0 | H40: 0 | J40: =E40-H40 -> 0 | K40: =E40+R40 -> 0 | M40: Gains on foreign exchange | N40: אּ | R40: 0
C41: אּ | D41: Penerimaan dan pembulatan lebih | E41: 0 | H41: 0 | J41: =E41-H41 -> 0 | K41: =E41+R41 -> 0 | M41: Excess payment and rounded | N41: אּ | R41: 0
C42: אּ | D42: Penerimaan piutang yang dihapus | E42: 0 | H42: 0 | J42: =E42-H42 -> 0 | K42: =E42+R42 -> 0 | M42: Recovery of write off of receivable | N42: אּ | R42: 0
C43: אּ | D43: Bagi hasil dari UP | E43: 0 | H43: 0 | J43: =E43-H43 -> 0 | K43: =E43+R43 -> 0 | M43: Profit sharinf from AE | R43: 0
C44: אּ | D44: Lain lain | E44: ='9'!D64 -> 0 | H44: 0 | J44: =E44-H44 -> 0 | K44: =E44+R44 -> 0 | M44: Others | N44: אּ | R44: 0
E45: =SUM(E38:E44) -> 0 | H45: 0 | J45: =E45-H45 -> 0 | K45: =SUM(K38:K44) -> 0 | R45: 0
J46: =E46-H46 -> 0
C47: Jumlah pendapatan dan | J47: =E47-H47 -> 0 | N47: Total unrestricted revenues and
C48: keuntungan tidak terikat | E48: =E45+E36+E25+E24+E27+E28+E26 -> 627072350 | H48: =H45+H36+H25+H24+H27+H28+H26 -> 678707218 | J48: =E48-H48 -> -51634868 | K48: =K45+K36+K26+K24+K27+K28+K25 -> 9.8482333e+09 | N48: gains | R48: 9.221161e+09 | S48: =K48-R48 -> 627072350
J49: =E49-H49 -> 0
C50: Aset bersih yang dibebaskan | J50: =E50-H50 -> 0 | N50: Net assets released
C51: dari pembatasan | J51: =E51-H51 -> 0 | N51: from restrictions
C52: Pembatasan program | E52: =CLK!S779 -> 14078200 | H52: 123119800 | J52: =E52-H52 -> -109041600 | K52: =E52+R52 -> 372744200 | M52: Program restriction | N52: אּ | R52: 358666000
C53: Pembatasan perolehan Aset tetap | E53: ='8'!P59 -> 0 | H53: 0 | J53: =E53-H53 -> 0 | K53: =E53+R53 -> 2640086544 | M53: Fixed assets acquisition restriction | N53: אּ | R53: 2640086544
C54: Pembatasan waktu | J54: =E54-H54 -> 0 | K54: =E54+H54 -> 0 | M54: Time restriction | N54: אּ | R54: 0
E55: =SUM(E52:E54) -> 14078200 | H55: =SUM(H52:H54) -> 123119800 | J55: =E55-H55 -> -109041600 | K55: =SUM(K52:K54) -> 3012830744 | R55: 2998752544
J56: =E56-H56 -> 0
C57: Jumlah pendapatan, keuntungan | J57: =E57-H57 -> 0 | N57: Total unrestricted revenues, gains
C58: dan dukungan lain tidak terikat | E58: =E55+E48 -> 641150550 | F58: 100 | H58: =H55+H48 -> 801827018 | I58: 100 | J58: =E58-H58 -> -160676468 | K58: =K55+K48 -> 1.2861064e+10 | L58: 100 | N58: and other support | R58: 1.2219914e+10 | U58: 931835924
C59: Beban dan kerugian | J59: =E59-H59 -> 0 | N59: Expenses and losses
C60: Pendidikan & umum | J60: =E60-H60 -> 0 | N60: Education and general
C61: אּ | D61: Akademik | E61: ='10'!D18 -> 13578200 | F61: =E61/$E$75*100 -> 2.0269775 | H61: ='10'!F18 -> 53619800 | I61: =H61/$H$75*100 -> 5.6222175 | J61: =E61-H61 -> -40041600 | K61: =E61+R61 -> 286569100 | L61: =K61/$K$75*100 -> 2.8306301 | M61: Academic | N61: אּ | R61: 272990900
C62: אּ | D62: Dakwah & sosial | E62: ='10'!D24 -> 1390000 | F62: =E62/$E$75*100 -> 0.20750164 | H62: ='10'!F24 -> 87571100 | I62: =H62/$H$75*100 -> 9.1821262 | J62: =E62-H62 -> -86181100 | K62: =E62+R62 -> 448380900 | L62: =K62/$K$75*100 -> 4.4289509 | M62: Propaganda and social | N62: אּ | R62: 446990900
C63: אּ | D63: Dukungan akademik | E63: ='10'!D28 -> 0 | F63: =E63/$E$75*100 -> 0 | H63: ='10'!F28 -> 0 | I63: =H63/$H$75*100 -> 0 | J63: =E63-H63 -> 0 | K63: =E63+R63 -> 4165000 | L63: =K63/$K$75*100 -> 0.041140424 | M63: Academic support | N63: אּ | R63: 4165000
C64: אּ | D64: Kegiatan dan layanan santri | E64: ='10'!D42 -> 10808800 | F64: =E64/$E$75*100 -> 1.6135567 | H64: ='10'!F42 -> 7899800 | I64: =H64/$H$75*100 -> 0.82832077 | J64: =E64-H64 -> 2909000 | K64: =E64+R64 -> 264820247 | L64: =K64/$K$75*100 -> 2.6158025 | M64: Student activities and services | N64: אּ | R64: 254011447
C65: אּ | D65: Dukungan institusi | E65: ='10'!D50 -> 2.9831743e+08 | F65: =E65/$E$75*100 -> 44.53335 | H65: ='10'!F50 -> 2.9393349e+08 | I65: =H65/$H$75*100 -> 30.819922 | J65: =E65-H65 -> 4383938.2 | K65: =E65+R65 -> 4.1451121e+09 | L65: =K65/$K$75*100 -> 40.943978 | M65: Institutional support | N65: אּ | R65: 3.8467946e+09
C66: אּ | D66: Pemeliharan & operasional plant | E66: ='10'!D60 -> 70631600 | F66: =E66/$E$75*100 -> 10.544009 | H66: ='10'!F60 -> 66706700 | I66: =H66/$H$75*100 -> 6.9944233 | J66: =E66-H66 -> 3924900 | K66: =E66+R66 -> 450286093 | L66: =K66/$K$75*100 -> 4.4477697 | M66: Maintenance and operation of plant | N66: אּ | R66: 379654493
C67: אּ | D67: Bantuan keuangan santri | E67: ='10'!D65 -> 61850 | F67: =E67/$E$75*100 -> 0.0092330766 | H67: ='10'!F65 -> 53300 | I67: =H67/$H$75*100 -> 0.0055886854 | J67: =E67-H67 -> 8550 | K67: =E67+R67 -> 2996487 | L67: =K67/$K$75*100 -> 0.029598259 | M67: Student financial aid | N67: אּ | R67: 2934637
C68: אּ | D68: Penjualan dan jasa | E68: ='10'!D70 -> 0 | F68: =E68/$E$75*100 -> 0 | H68: ='10'!F70 -> 0 | I68: =H68/$H$75*100 -> 0 | J68: =E68-H68 -> 0 | K68: =E68+R68 -> 432850231 | L68: =K68/$K$75*100 -> 4.2755444 | M68: Sales and service | N68: אּ | R68: 432850231
C69: אּ | D69: Layanan asrama | E69: ='10'!D75 -> 105573243 | F69: =E69/$E$75*100 -> 15.760159 | H69: ='10'!F75 -> 226657778 | I69: =H69/$H$75*100 -> 23.765835 | J69: =E69-H69 -> -121084535 | K69: =E69+R69 -> 1762366822 | L69: =K69/$K$75*100 -> 17.408048 | M69: Boarding services | N69: אּ | R69: 1656793579
E70: =SUM(E61:E69) -> 5.0036112e+08 | H70: =SUM(H61:H69) -> 7.3644197e+08 | J70: =E70-H70 -> -2.3608085e+08 | K70: =SUM(K61:K69) -> 7.7975469e+09 | R70: 7.2971858e+09
C71: Penyusutan | E71: ='10'!D86 -> 91820733 | F71: =E71/$E$75*100 -> 13.70716 | H71: ='10'!F86 -> 93437189 | I71: =H71/$H$75*100 -> 9.7972055 | J71: =E71-H71 -> -1616455.9 | K71: =E71+R71 -> 1.1111933e+09 | L71: =K71/$K$75*100 -> 10.975982 | N71: Depreciation | R71: 1.0193726e+09
C72: Usaha pelengkap | E72: ='10'!D88 -> 77692362 | F72: =E72/$E$75*100 -> 11.598052 | H72: ='10'!F88 -> 1.238335e+08 | I72: =H72/$H$75*100 -> 12.984361 | J72: =E72-H72 -> -46141134 | K72: =E72+R72 -> 1.2151222e+09 | L72: =K72/$K$75*100 -> 12.002556 | N72: Auxiliary enterprises | R72: 1.1374299e+09
C73: Beban lain lain & kerugian | E73: ='10'!D101 -> 0 | F73: =E73/$E$75*100 -> 0 | H73: ='10'!F101 -> 0 | I73: =H73/$H$75*100 -> 0 | J73: =E73-H73 -> 0 | K73: =E73+R73 -> 0 | L73: =K73/$K$75*100 -> 0 | N73: Other expenses & losses | R73: 0
J74: =E74-H74 -> 0
C75: Jumlah beban dan kerugian | E75: =SUM(E70:E73) -> 6.6987422e+08 | F75: 100 | H75: =SUM(H70:H73) -> 9.5371266e+08 | I75: 100 | J75: =E75-H75 -> -2.8383844e+08 | K75: =SUM(K70:K73) -> 1.0123862e+10 | L75: 100 | N75: Total expenses and losses | R75: 9.4539883e+09
J76: =E76-H76 -> 0 | S76: Profitabilitas
C77: Kenaikan ( penurunan ) | J77: =E77-H77 -> 0 | N77: Increase ( decrease ) | S77: Roa (Efesiensi Menghasilkan Laba | T77: =K78/NRC!E36*100% -> 0.11545099 | U77: Min | V77: 0.0598
C78: Aset bersih tidak terikat | E78: =E58-E75 -> -28723668 | H78: =H58-H75 -> -1.5188564e+08 | I78: =H78/H81*100 -> -1.0024298 | J78: =E78-H78 -> 1.2316197e+08 | K78: =K58-K75 -> 2.7372016e+09 | L78: =K78/K81*100 -> 22.37384 | N78: in unrestricted net assets | R78: 2.7659252e+09 | S78: Roe (Laba Dari Modal) | T78: =K78/NRC!E74*100% -> 0.1258666
J79: =E79-H79 -> 0 | S79: NPM (Laba Bersih Dari total Pendapatan) | T79: =K78/K58 -> 0.21282855 | U79: min. | V79: 5%-20%
C80: Aset bersih tidak terikat | J80: =E80-H80 -> 0 | N80: Unrestricted net assets
C81: pada awal bulan | E81: =H85 -> 1.4999862e+10 | H81: 1.5151748e+10 | J81: =E81-H81 -> -1.5188564e+08 | K81: =[5]LR!$E$85 -> 1.2233937e+10 | N81: at beginning of month | R81: 1.2233937e+10
D82: Reklasifikasi | E82: 0 | H82: 0 | J82: =E82-H82 -> 0 | K82: =E82+R82 -> 0 | M82: Reclassification | R82: 0
J83: =E83-H83 -> 0
C84: Aset bersih tidak terikat | J84: =E84-H84 -> 0 | M84: Unrestricted net assets
C85: pada akhir bulan | E85: =E78+E81+E82 -> 1.4971139e+10 | H85: =H78+H81+H82 -> 1.4999862e+10 | J85: =E85-H85 -> -28723668 | K85: =K78+K81+K82 -> 1.4971139e+10 | M85: at end of month | R85: 1.4999862e+10
E86: =E85-NRC!E68 -> 0.13999939 | H86: =H85-NRC!G68 -> 0.14999771 | K86: =K85-E85 -> 0.080001831
R87: =R85-[6]LR!$K$85 -> 0
C88: =IN!C4 -> Laporan Keuangan June 2026 | N88: =IN!D4 -> Financial Statement Jun 2026
E92: =E78-H78 -> 1.2316197e+08
E94: =E92/H78*100% -> -0.81088621
B128: Catatan atas laporan keuangan merupakan bagian yang tidak terpisahkan dari laporan keuangan | O128: The accompanying notes form an integral part of these financial statements
C130: =[4]IN!C19 -> Laporan keuangan August 2023 | H130: 3 | O130: =[4]IN!M19 -> #N/A
Q133: Pendapatan | R133: pendidikan | S133: =K24 -> 8504271000 | T133: Biaya
E134: =[7]LR!$E$78 -> 2.3107203e+09 | R134: Sumbangan Dll | S134: =K25+K26+K27+K28 -> 11945754
E135: =E78-E134 -> -2.3394439e+09 | R135: Usaha Pelengkap | S135: =K30+K31+K32+K33+K34+K35 -> 1332016556
R136: Pembebasan Program | S136: =K55 -> 3012830744
D139: DIAGRAM PENDAPATAN & BIAYA

Sheet PAB
B2: PESANTREN ISLAM AL IRSYAD TENGARAN 6 BONDOWOSO
B4: LAPORAN PERUBAHAN ASET BERSIH | L4: STATEMENTS OF CHANGES IN NET ASSETS
B5: =LR!C6 -> Untuk Bulan yang Berakhir 30 June 2026 | K5: =LR!I6 -> For The Month Ended Jun 2026 | L5: =[8]RL!O6 -> #N/A
B6: =LR!C7 -> (Dengan perbandingan informasi keuangan untuk bulan yang berakhir 31 May 2026 / | L6: =LR!O7 -> With Comparative financial information for the month ended May 31, 2026 )
L7: =[8]RL!O8 -> #N/A
B8: (Disajikan dalam rupiah) | L8: (Expressed in rupiah)
B10: =B5 -> Untuk Bulan yang Berakhir 30 June 2026 | K10: ="For The Month Ended "&TEXT(IN!D5,"MMM YYYY") -> For The Month Ended Jun 2026 | L10: =[8]IN!M23 -> #N/A
C11: Pos - pos | E11: Catatan / | F11: Tidak terikat / | G11: Terikat temporer / | H11: Terikat permanen / | I11: Jumlah / | J11: Accounts
E12: Notes | F12: Unrestricted | G12: Temporarily | H12: Permanently | I12: Total
G13: restricted | H13: restricted
C14: Pendapatan dan keuntungan | K14: Revenues & gains
C15: Pendapatan pendidikan | F15: =LR!E22 -> 547400000 | G15: 0 | H15: 0 | I15: =SUM(F15:H15) -> 547400000 | K15: Tuition and fees
C16: אּ | D16: Dikurangi : beasiswa | F16: =LR!E23 -> -3950000 | I16: =SUM(F16:H16) -> -3950000 | J16: Less : scholarship | K16: אּ
F17: =F15+F16 -> 543450000 | G17: =SUM(G15:G16) -> 0 | H17: =SUM(H15:H16) -> 0 | I17: =I15+I16 -> 543450000
C18: Sumbangan | F18: =LR!E25 -> 1000100 | H18: 0 | I18: =SUM(F18:H18) -> 1000100 | K18: Contributions
C19: Bantuan | F19: =LR!E26 -> 0 | G19: =CLK!N785 -> 500000 | I19: =SUM(F19:H19) -> 500000 | K19: Grants
C20: Penjualan & layanan | F20: =LR!E27 -> 50000 | I20: =SUM(F20:H20) -> 50000 | K20: Sales & services
C21: Penghasilan investasi | F21: =LR!E28 -> 0 | I21: =SUM(F21:H21) -> 0 | K21: Investment income
C22: Usaha pelengkap | F22: =LR!E36 -> 82572250 | I22: =SUM(F22:H22) -> 82572250 | K22: Auxiliary enterprises
C23: Penghasilan lain lain & keuntungan | F23: =LR!E45 -> 0 | I23: =SUM(F23:H23) -> 0 | K23: Others income & gains
C24: Jumlah pendapatan dan keuntungan | F24: =SUM(F17:F23) -> 627072350 | G24: =SUM(G17:G23) -> 500000 | H24: =SUM(H17:H23) -> 0 | I24: =SUM(I17:I23) -> 627572350 | K24: Total Revenues and gains
C26: Aset bersih yang dibebaskan | K26: Net assets released
C27: dari pembatasan | F27: =LR!E55 -> 14078200 | G27: =-CLK!S794 -> -14078200 | H27: 0 | I27: =SUM(F27:H27) -> 0 | K27: from restrictions
C29: Jumlah pendapatan, keuntungan | K29: Total revenues, gains
C30: dan dukungan lain | F30: =F27+F24 -> 641150550 | G30: =G27+G24 -> -13578200 | H30: =H27+H24 -> 0 | I30: =SUM(F30:H30) -> 627572350 | K30: and other support
C32: Beban dan kerugian | F32: =LR!E75 -> 6.6987422e+08 | G32: 0 | H32: 0 | I32: =SUM(F32:H32) -> 6.6987422e+08 | K32: Expenses and losses
C34: Kenaikan ( penurunan ) | K34: Increase ( decrease )
C35: Aset bersih | F35: =F30-F32 -> -28723668 | G35: =G30-G32 -> -13578200 | H35: =H30-H32 -> 0 | I35: =SUM(F35:H35) -> -42301868 | K35: net assets
C37: Aset bersih awal bulan | F37: =F73 -> 1.4999862e+10 | G37: =G73 -> 351222700 | H37: =H73 -> 6438063087 | I37: =SUM(F37:H37) -> 2.1789148e+10 | K37: Net assets at beginning of month
D38: Reklasifikasi | F38: 0 | I38: =SUM(F38:H38) -> 0 | J38: Reclassification
C40: Aset bersih akhir bulan | F40: =F35+F37 -> 1.4971139e+10 | G40: =G35+G37 -> 337644500 | H40: =H35+H37 -> 6438063087 | I40: =I35+I37 -> 2.1746846e+10 | J40: Net assets at end of month
F41: =NRC!E68-F40 -> 0.0099868774 | G41: =G40-NRC!E70 -> 0 | H41: =H40-NRC!E71 -> 0 | I41: =I40-NRC!E74 -> -0.0099830627
B43: ="Untuk Bulan yang Berakhir "&TEXT(IN!C8,"MMMm YYYY") -> Untuk Bulan yang Berakhir May 2026 | K43: ="For The Month Ended "&TEXT(IN!D8,"MMM YYYY") -> For The Month Ended May 2026 | L43: =[8]IN!M26 -> #N/A
C44: Pos - pos | E44: Catatan / | F44: Tidak terikat / | G44: Terikat temporer / | H44: Terikat permanen / | I44: Jumlah / | J44: Accounts
E45: Notes | F45: Unrestricted | G45: Temporarily | H45: Permanently | I45: Total
G46: restricted | H46: restricted
C47: Pendapatan dan keuntungan | K47: Revenues & gains
C48: Pendapatan pendidikan | F48: 552500000 | G48: 0 | H48: 0 | I48: =SUM(F48:H48) -> 552500000 | K48: Tuition and fees
C49: אּ | D49: Dikurangi : beasiswa | F49: -4200000 | I49: =SUM(F49:H49) -> -4200000 | J49: Less : scholarship | K49: אּ
F50: =F48+F49 -> 548300000 | G50: =SUM(G48:G49) -> 0 | H50: =SUM(H48:H49) -> 0 | I50: =I48+I49 -> 548300000
C51: Sumbangan | F51: 168 | H51: 0 | I51: =SUM(F51:H51) -> 168 | K51: Contributions
C52: Bantuan | F52: 0 | G52: 160735000 | I52: =SUM(F52:H52) -> 160735000 | K52: Grants
C53: Penjualan & layanan | F53: 414950 | I53: =SUM(F53:H53) -> 414950 | K53: Sales & services
C54: Penghasilan investasi | F54: 0 | I54: =SUM(F54:H54) -> 0 | K54: Investment income
C55: Usaha pelengkap | F55: 129992100 | I55: =SUM(F55:H55) -> 129992100 | K55: Auxiliary enterprises
C56: Penghasilan lain lain & keuntungan | F56: 0 | I56: =SUM(F56:H56) -> 0 | K56: Others income & gains
C57: Jumlah pendapatan dan keuntungan | F57: =SUM(F50:F56) -> 678707218 | G57: =SUM(G51:G56)+G50 -> 160735000 | H57: =SUM(H51:H56)+H50 -> 0 | I57: =SUM(I50:I56) -> 839442218 | K57: Total Revenues and gains
C59: Aset bersih yang dibebaskan | K59: Net assets released
C60: dari pembatasan | F60: 123119800 | G60: =-F60 -> -123119800 | H60: 0 | I60: =SUM(F60:H60) -> 0 | K60: from restrictions
C62: Jumlah pendapatan, keuntungan | K62: Total revenues, gains
C63: dan dukungan lain | F63: =F60+F57 -> 801827018 | G63: =G57+G60 -> 37615200 | H63: =H60+H57 -> 0 | I63: =SUM(F63:H63) -> 839442218 | K63: and other support
C65: Beban dan kerugian | F65: 9.5371266e+08 | G65: 0 | H65: 0 | I65: =SUM(F65:H65) -> 9.5371266e+08 | K65: Expenses and losses
C67: Kenaikan ( penurunan ) | K67: Increase ( decrease )
C68: Aset bersih | F68: =F63-F65 -> -1.5188564e+08 | G68: =G63-G65 -> 37615200 | H68: =H63-H65 -> 0 | I68: =SUM(F68:H68) -> -1.1427044e+08 | K68: net assets
I69: =SUM(F69:H69) -> 0
C70: Aset bersih awal bulan | F70: 1.5151748e+10 | G70: 313607500 | H70: 6438063087 | I70: =SUM(F70:H70) -> 2.1903419e+10 | K70: Net assets at beginning of month
D71: Reklasifikasi | F71: 0 | I71: =SUM(F71:H71) -> 0 | J71: Reclassification
C73: Aset bersih akhir bulan | F73: =F68+F70 -> 1.4999862e+10 | G73: =G68+G70 -> 351222700 | H73: =H68+H70 -> 6438063087 | I73: =SUM(I68:I71) -> 2.1789148e+10 | J73: Net assets at end of month
F74: =F73-NRC!G68 -> 0 | G74: =G73-NRC!G70 -> 0 | H74: =H73-NRC!G71 -> 0 | I74: =I73-NRC!G74 -> 0
B75: =IN!C4 -> Laporan Keuangan June 2026 | K75: =IN!D4 -> Financial Statement Jun 2026
B115: Catatan atas laporan keuangan merupakan bagian yang tidak terpisahkan dari laporan keuangan | L115: The accompanying notes form an integral part of these financial statements
B117: =[8]IN!C19 -> Laporan keuangan July 2023 | G117: 4 | K117: =[8]IN!M19 -> #N/A | L117: FINANCIAL STATEMENT JULY TO AUGUST 2015

Sheet AK
L1: =E58 -> 0
B3: PESANTREN ISLAM AL-IRSYAD TENGARAN 6 BONDOWOSO
B5: LAPORAN ARUS KAS | J5: STATEMENTS OF CASH FLOWS
C6: =PAB!B5 -> Untuk Bulan yang Berakhir 30 June 2026 | J6: =LR!I6 -> For The Month Ended Jun 2026
B7: =[8]Nrc!B6 -> (Dengan perbandingan informasi keuangan 30 June 2023 ) | C7: =LR!C7 -> (Dengan perbandingan informasi keuangan untuk bulan yang berakhir 31 May 2026 / | J7: =LR!O7 -> With Comparative financial information for the month ended May 31, 2026 )
B9: ='[9]LR '!B9 -> (Disajikan dalam rupiah) | J9: ='[9]LR '!N9 -> (Expressed in rupiah)
C11: Uraian | E11: =NRC!E9 -> 30 June 2026/ | F11: =NRC!G9 -> 31 May 2026/ | G11: ="sd "&(E11) -> sd 30 June 2026/ | H11: Description | L11: ="sd "&(F11) -> sd 31 May 2026/
E12: =NRC!E10 -> 46203 | F12: =NRC!G10 -> 46173 | G12: =E12 -> 46203 | L12: =F12 -> 46173
C13: Arus kas dari aktivitas operasi | I13: Cash flows from operating activities
C14: Penerimaan kas dari : | I14: Cash receipt from :
C15: אּ | D15: Pendidikan santri | E15: =IF(K15<>"",SUMIF(CRAK1,K15,CRAK2),0)+IF(K15<>"",SUMIF(JMAK1,K15,JMAK2),0) -> 590502000 | F15: 662186000 | G15: =E15+L15 -> 7949850000 | H15: Tuition and fees | I15: אּ | K15: M41 | L15: 7359348000 | N15: =[8]CR!N1 -> 57351290 | O15: =E15-N15 -> 533150710
C16: אּ | D16: Sumbangan dan bantuan | E16: =IF(K16<>"",SUMIF(CRAK1,K16,CRAK2),0)+IF(K16<>"",SUMIF(JMAK1,K16,JMAK2),0) -> 0 | F16: 126385000 | G16: =E16+L16 -> 2580657300 | H16: Contributions and grants | I16: אּ | K16: M42 | L16: 2580657300
C17: אּ | D17: Kas masuk usaha pelengkap (U. Usaha) | E17: ='[10]Buku Besar'!$K$15 -> 50007700 | F17: 177492100 | G17: =E17+L17 -> 1518668400 | H17: Auxiliary enterprises cash in | I17: אּ | K17: M43 | L17: 1468660700
C18: אּ | D18: Tabungan santri | E18: =IF(K18<>"",SUMIF(CRAK1,K18,CRAK2),0)+IF(K18<>"",SUMIF(JMAK1,K18,JMAK2),0) -> 101337100 | F18: 153240700 | G18: =E18+L18 -> 1651932750 | H18: Student saving | I18: אּ | K18: M44 | L18: 1550595650 | N18: =[8]Jm!H53 -> 166740500 | O18: =E18-N18 -> -65403400
C19: אּ | D19: Pelunasan piutang lain lain | E19: =IF(K19<>"",SUMIF(CRAK1,K19,CRAK2),0)+IF(K19<>"",SUMIF(JMAK1,K19,JMAK2),0) -> 2000000 | F19: 7831615 | G19: =E19+L19 -> 21263282 | H19: Other receivable collected | I19: אּ | K19: M45 | L19: 19263282
C20: אּ | D20: Penerimaan lain lain | E20: =IF(K20<>"",SUMIF(CRAK1,K20,CRAK2),0)+IF(K20<>"",SUMIF(JMAK1,K20,JMAK2),0) -> 250100 | F20: 415118 | G20: =E20+L20 -> 4.6585912e+08 | H20: Others receipts | I20: אּ | K20: M46 | L20: 4.6560902e+08 | N20: =[8]CR!N2 -> 215130000 | O20: =E20-N20 -> -214879900
E21: =SUM(E15:E20) -> 744096900 | F21: 1127550533 | G21: =SUM(G15:G20) -> 14188230856 | L21: 13444133956
C22: Pembayaran kas kepada : | I22: Cash payment to :
C23: אּ | D23: Pemasok | E23: =IF(K23<>"",SUMIF(CDAK1,K23,CDAK2),0)+IF(K23<>"",SUMIF(JMAK1,K23,JMAK3),0) -> 133355190 | F23: 393937728 | G23: =E23+L23 -> 3955722741 | H23: Suppliers | I23: אּ | K23: K51 | L23: 3822367551 | N23: =[8]CD!N1 -> 124052605 | O23: =E23-N23 -> 9302585
C24: אּ | D24: Karyawan | E24: =IF(K24<>"",SUMIF(CDAK1,K24,CDAK2),0)+IF(K24<>"",SUMIF(JMAK1,K24,JMAK3),0) -> 266681354 | F24: 261680735 | G24: =E24+L24 -> 3402269724 | H24: Employee | I24: אּ | K24: K52 | L24: 3135588370 | N24: =[8]CD!N2 -> 25931842 | O24: =E24-N24 -> 240749512
C25: אּ | D25: Santri | E25: =IF(K25<>"",SUMIF(CDAK1,K25,CDAK2),0)+IF(K25<>"",SUMIF(JMAK1,K25,JMAK3),0) -> 122322700 | F25: 160638350 | G25: =E25+L25 -> 1398061300 | H25: Student | I25: אּ | K25: K53 | L25: 1275738600 | N25: =[8]CD!N3+[8]Jm!G52 -> 164455790 | O25: =E25-N25 -> -42133090
C26: אּ | D26: Kas keluar usaha pelengkap (U. Usaha) | E26: ='[10]Buku Besar'!$L$15 -> 92728464 | F26: 139591402 | G26: =E26+L26 -> 1490314752 | H26: Auxiliary enterprises cash out | I26: אּ | L26: 1397586288
C27: אּ | D27: Pembayaran lain lain | E27: =IF(K27<>"",SUMIF(CDAK1,K27,CDAK2),0)+IF(K27<>"",SUMIF(JMAK1,K27,JMAK3),0) -> 4200000 | F27: 74027100 | G27: =E27+L27 -> 175457128 | H27: Others payment | I27: אּ | K27: K54 | L27: 171257128
E28: =SUM(E23:E27) -> 619287708 | F28: 1029875315 | G28: =SUM(G23:G27) -> 10421825645 | L28: 9802537937
C30: Kas bersih yang diperoleh dari | I30: Net cash provided by
C31: ( digunakan untuk ) aktivitas operasi | E31: =E21-E28 -> 124809192 | F31: =F21-F28 -> 97675218 | G31: =G21-G28 -> 3766405211 | I31: ( used in ) operating activities | L31: 3641596019
C32: Arus kas dari aktivitas investasi | I32: Cash flows from investing activities
C33: Perolehan Aset tetap | E33: =IF(K33<>"",SUMIF(CDAK1,K33,CDAK2),0)+IF(K33<>"",SUMIF(JMAK1,K33,JMAK3),0) -> 1500000 | F33: 30940000 | G33: =E33+L33 -> 1775248773 | I33: Acquisition o fixed assets | K33: K50 | L33: 1773748773
C34: Hasil penjualan Aset tetap | E34: =IF(K34<>"",SUMIF(CDAK1,K34,CDAK2),0)+IF(K34<>"",SUMIF(JMAK1,K34,JMAK3),0) -> 0 | F34: 0 | G34: =SUM(E34:F34) -> 0 | I34: Proceeds from sale of fixed assets | K34: M40 | L34: 0
C35: Pembelian investasi | G35: =SUM(E35:F35) -> 0 | I35: Purchase of invesment | L35: 0
C36: Hasil penjualan investasi | E36: 0 | F36: 0 | G36: =SUM(E36:F36) -> 0 | I36: Proceeds from sale of invesment | L36: 0
C37: Kas bersih yang diperoleh dari | I37: Net cash provided by
C38: ( digunakan untuk ) aktivitas investasi | E38: =E34-E33 -> -1500000 | F38: =F34-F33 -> -30940000 | G38: =G34-G33 -> -1775248773 | I38: ( used in ) investing activities | L38: -1773748773
C39: Arus kas dari aktivitas pendanaan | I39: Cash flows from financing activities
C40: Penerimaan kas dari sumbangan terikat untuk : | I40: Cash receipt from restricted contributions for :
C41: אּ | D41: Investasi Aset tetap | E41: 0 | F41: 0 | G41: =E41+L41 -> 0 | H41: Invesment in fixed assets | I41: אּ | K41: 31 | L41: 0
C42: אּ | D42: Program jangka panjang | E42: 0 | F42: 0 | G42: =SUM(E42:F42) -> 0 | H42: Long term purpose | I42: אּ | J42: Biaya Penyusutan | K42: 32 | L42: 0
E43: =SUM(E41:E42) -> 0 | F43: 0 | G43: =SUM(G41:G42) -> 0 | L43: 0
C44: Pendapatan investasi terikat untuk | I44: Invesment income restricted for
D45: program jangka panjang | H45: Long term purpose
C46: Penerimaan pinjaman jangka panjang | I46: Cash receipts from long term loan | K46: 21
C47: Pembayaran bagi hasil | E47: 0 | F47: 0 | I47: Payment for profit sharing | K47: 22
C48: Kas bersih yang diperoleh dari | I48: Net cash provided by
C49: ( digunakan untuk ) aktivitas pendanaan | E49: =E43+E46-E47 -> 0 | F49: 0 | G49: =G43+G46-G47 -> 0 | I49: ( used in ) financing activities | L49: 0
C51: Kenaikan ( penurunan ) bersih | I51: Net increase ( decrease ) in
C52: kas dan setara kas | E52: =E49+E38+E31 -> 123309192 | F52: =F49+F38+F31 -> 66735218 | G52: =G49+G38+G31 -> 1991156438 | I52: cash and cash equivalent | L52: 1867847246
C54: Kas dan setara kas | G54: 0 | I54: Cash and cash equivalent | L54: 0
C55: pada awal bulan | E55: =F57 -> 3.0051166e+09 | F55: 2.9383814e+09 | G55: 1.1372693e+09 | H55: at beginning ot month | L55: 1.1372693e+09
C57: Kas dan setara kas pada akhir bulan | E57: =E52+E55 -> 3.1284258e+09 | F57: =F52+F55 -> 3.0051166e+09 | G57: =G52+G55 -> 3.1284258e+09 | H57: Cash and cash equivalent at end of month | L57: 3.0051166e+09
E58: =E57-NRC!E13 -> 0 | F58: =F57-NRC!G13 -> 0 | G58: =G57-NRC!E13 -> 0 | L58: =L57-[6]AK!$G$57 -> 0
B61: Catatan atas laporan keuangan merupakan bagian yang tidak terpisahkan dari laporan keuangan | J61: The accompanying notes form an integral part of these financial statements
B63: =[9]NRC!B81 -> Laporan keuangan August 2015 | C63: =IN!C4 -> Laporan Keuangan June 2026 | F63: 5 | J63: =IN!D4 -> Financial Statement Jun 2026
D66: Penerimaan Pendidikan + Donasi + Lain2 | E66: =E15+E19+E20+E16 -> 592752100 | F66: =E66-E67 -> 188515556 | G66: Dirinci
D67: Biaya Operasional | E67: =E23+E24+E27 -> 404236544
D70: Penerimaan Donasi Pembangunan | E70: 0 | F70: =E70-E71 -> -1500000
D71: Investasi Aset Tetap | E71: =E33 -> 1500000
D73: Penerimaan Tabungan | E73: =E18 -> 101337100 | F73: =E73-E74 -> -20985600
D74: Kas Keluar Tabungan | E74: =E25 -> 122322700
D76: Penerimaan Usaha Pelengkap | E76: =E17 -> 50007700 | F76: =E76-E77 -> -42720764
D77: Kas Keluar Usaha Pelengkap | E77: =E26 -> 92728464
D78: Kenaikan ( penurunan ) bersih | F78: =SUM(F66:F76) -> 123309192

Sheet CLK
B3: PESANTREN ISLAM AL-IRSYAD TENGARAN 6 BONDOWOSO
B5: CATATAN ATAS LAPORAN KEUANGAN | AQ5: NOTES TO FINANCIAL STATEMENTS
B6: =NRC!B5 -> 30 June 2026 | AJ6: =NRC!I5 -> 46203
B7: =NRC!C6&")" -> (Dengan perbandingan informasi keuangan untuk bulan yang berakhir 31 May 2026 /) | AP7: ="("&NRC!K6 -> (With Comparative financial information for the month ended May 31, 2026 )
B8: (Disajikan dalam rupiah) | AQ8: =[9]NRC!J7 -> (Expressed in rupiah)
B9: (lanjutan) | AQ9: (continued)
B12: 1. | C12: IKHTISAR KEBIJAKAN AKUNTANSI YANG PENTING | X12: =B12 -> 1. | Y12: SUMMARY OF SIGNIFICANT ACCOUNTING POLICIES
C15: Laporan keuangan lembaga telah disusun dan diselesaikan pada 9 Agustus 2023 | Y15: ="The Istitution's financial statements were prepared and completed on"&" August" -> The Istitution's financial statements were prepared and completed on August
C16: Berikut ini adalah ikhtisar kebijakan akuntansi penting yang diterapkan dalam | Y16: ="09, 2023. Presented below are the significant accounting policies adopted in" -> 09, 2023. Presented below are the significant accounting policies adopted in
C17: penyusunan dan penyajian laporan keuangan lembaga , yang sesuai dengan prinsip | Y17: preparing and presenting the financial statements of the institution, which are
C18: dan praktek akuntansi yang berlaku umum di Indonesia. | Y18: in conformity with accounting principles and practices generally accepted
Y19: in Indonesia.
C21: a. | D21: Dasar pengukuran dan penyusunan laporan keuangan | Y21: a. | Z21: Basis of measurement and preparation of the financial statements
C34: b. | D34: Kas dan setara kas | Y34: b. | Z34: Cash and cash equivalents
C40: c. | D40: Piutang aktivitas dan lain lain | Y40: c. | Z40: Accounts and other receivables
C47: d. | D47: Persediaan | Y47: d. | Z47: Inventories
C58: e. | D58: Aset tetap | Y58: e. | Z58: Fixed assets
T67: Masa manfaat / Useful life
T68: Tahun / Years
D70: Gedung | T70: 20 | AO70: Building
D71: Infrastruktur | T71: 5 - 20 | AO71: Infrastructure
D72: Mesin dan peralatan | T72: 5 | AO72: Mechine & equipment
D73: Mebel dan perlengkapan | T73: 5 | AO73: Furniture & fixture
D74: Kendaraan | T74: 8 | AO74: Vehicles
D75: Buku & material perpustakaan | T75: 5 | AO75: Library books & material
D76: Lain lain Aset tetap | T76: 5 | AO76: Other fixed assets
C97: f. | D97: Pengakuan pendapatan dan beban | Y97: f. | Z97: Revenue and Expense Recognition
B118: Catatan atas laporan keuangan merupakan bagian yang tidak terpisahkan dari laporan keuangan | AQ118: The accompanying notes form an integral part of these financial statements
B120: =IN!C4 -> Laporan Keuangan June 2026 | W120: 6 | AQ120: =IN!D4 -> Financial Statement Jun 2026
B121: 2. | C121: KAS DAN SETARA KAS | X121: =B121 -> 2. | Y121: CASH AND CASH EQUIVALENTS
C123: Akun ini terdiri dari : | AQ123: This account consists of :
Q124: =NRC!E9 -> 30 June 2026/ | R124: =[8]IN!$G$23 -> 31 July 2023 / | S124: =[8]IN!$G$23 -> 31 July 2023 / | T124: =[8]IN!$G$23 -> 31 July 2023 / | U124: =[8]IN!$G$23 -> 31 July 2023 / | V124: =[8]IN!$G$23 -> 31 July 2023 / | X124: =NRC!G9 -> 31 May 2026/ | Y124: =[8]IN!$G$26 -> 30 June 2023 / | Z124: =[8]IN!$G$26 -> 30 June 2023 / | AA124: =[8]IN!$G$26 -> 30 June 2023 / | AB124: =[8]IN!$G$26 -> 30 June 2023 / | AC124: =[8]IN!$G$26 -> 30 June 2023 /
Q125: =NRC!E10 -> 46203 | R125: =[8]IN!$I$23 -> #N/A | S125: =[8]IN!$I$23 -> #N/A | T125: =[8]IN!$I$23 -> #N/A | U125: =[8]IN!$I$23 -> #N/A | V125: =[8]IN!$I$23 -> #N/A | X125: =NRC!G10 -> 46173 | Y125: =[8]IN!$I$26 -> #N/A | Z125: =[8]IN!$I$26 -> #N/A | AA125: =[8]IN!$I$26 -> #N/A | AB125: =[8]IN!$I$26 -> #N/A | AC125: =[8]IN!$I$26 -> #N/A
C126: Kas | AQ126: Cash on hand
C127: אּ | D127: Kas ditangan | Q127: =BS!C17 -> 919800 | X127: 1885900 | AP127: Cash - central | AQ127: אּ | AS127: 1-1111 | AT127: Education Cash
C128: אּ | D128: Kas Kantin 6 Mart | Q128: ='12'!E14+'12'!E15 -> 2.2306116e+08 | X128: 2.6578192e+08 | AP128: Cash - auxiliary enterprise | AQ128: אּ
C129: אּ | D129: Kas tabungan | Q129: =BS!C18 -> 85600 | X129: 101107200 | AP129: Cash - saving student | AQ129: אּ | AS129: 1-1112 | AT129: Student Saving Cash
C130: אּ | D130: Kas BOS SD Diknas | Q130: 0 | X130: 0 | AP130: Cash - BOS SDITQ | AQ130: אּ
C131: אּ | D131: Kas BOS MTS Depag | Q131: =BS!C20 -> 175654800 | X131: 183016600 | AP131: Cash - BOS MTS Depag | AQ131: אּ
C132: אּ | D132: Kas BOS IM Depag | Q132: =BS!C21 -> 161988900 | X132: 168205300 | AP132: Cash - BOS MA Depag | AQ132: אּ | AS132: =X128-Q128 -> 42720764
C133: אּ | Q133: =BS!C24 -> 0 | X133: 0 | AQ133: אּ
C134: אּ | X134: 0 | AQ134: אּ
C135: אּ | X135: 0 | AQ135: אּ
C136: אּ | X136: 0 | AQ136: אּ
C137: אּ | Q137: =IF($AS137="",0,VLOOKUP($AS137,[9]GL!$B$11:$J$3054,9,FALSE)) -> 0 | X137: 0 | AQ137: אּ | AV137: .
Q138: =SUM(Q127:V137) -> 5.6171026e+08 | X138: =SUM(X127:AC137) -> 7.1999692e+08
C139: Bank | AQ139: Cash in bank
C140: אּ | D140: Giro Bank Muamalat Indonesia | Q140: =BS!C27 -> 2368365264 | X140: 1998607680 | AP140: Bank Muamalat Indonesia 7350016529 | AQ140: אּ
C141: אּ | D141: Bank Muamalat Indonesia (BMI) | Q141: =BS!C28 -> 136214910 | X141: 94823535 | AP141: Bank Muamalat Indonesia 7350013979 | AQ141: אּ
C142: אּ | D142: BMI Yayasan | Q142: =BS!C29 -> 61760328 | X142: 61760328 | AP142: Bank Muamalat Indonesia 7350014923 | AQ142: אּ
C143: אּ | D143: Bank Syariah Indonesia (BSI) | Q143: =BS!C30 -> 375000 | X143: 129928103 | AP143: Bank Syariah Indonesia | AQ143: אּ
C144: אּ | D144: BMI 6 Mart | Q144: ='12'!E16 -> 0.08 | X144: 0.08 | AP144: Bank Muamalat Indonesia | AQ144: אּ
C145: אּ | Q145: =BS!C32 -> 0 | X145: 0 | AQ145: אּ
C146: אּ | Q146: =BS!C33 -> 0 | X146: 0 | AQ146: אּ
C147: אּ | Q147: =BS!C25 -> 0 | X147: 0 | AQ147: אּ
C148: אּ | Q148: =BS!C26 -> 0 | X148: 0 | AQ148: אּ
C149: אּ | Q149: 0 | X149: 0 | AQ149: אּ | AS149: 1-1122 | AT149: Bank Central Asia (BCA) - | AV149: 427020500
Q150: =SUM(Q140:V149) -> 2.5667155e+09 | X150: =SUM(X140:AC149) -> 2.2851196e+09
C152: Jumlah kas dan setara kas | Q152: =Q138+Q150 -> 3.1284258e+09 | X152: =X138+X150 -> 3.0051166e+09 | AQ152: Total cash and cash equivalents
AT155: =Q152-#REF!-Q149-Q128-#REF! -> #REF!
B156: 3. | C156: PIUTANG AKTIFITAS - BERSIH | X156: =B156 -> 3. | Y156: ACCOUNT RECEIVABLE - NET
C158: Akun ini terdiri dari : | AQ158: This account consists of :
Q159: =Q124 -> 30 June 2026/ | R159: =[8]IN!$G$23 -> 31 July 2023 / | S159: =[8]IN!$G$23 -> 31 July 2023 / | T159: =[8]IN!$G$23 -> 31 July 2023 / | U159: =[8]IN!$G$23 -> 31 July 2023 / | V159: =[8]IN!$G$23 -> 31 July 2023 / | X159: =X124 -> 31 May 2026/ | Y159: =[8]IN!$G$26 -> 30 June 2023 / | Z159: =[8]IN!$G$26 -> 30 June 2023 / | AA159: =[8]IN!$G$26 -> 30 June 2023 / | AB159: =[8]IN!$G$26 -> 30 June 2023 / | AC159: =[8]IN!$G$26 -> 30 June 2023 /
Q160: =Q125 -> 46203 | X160: =X125 -> 46173 | Y160: =[8]IN!$I$26 -> #N/A | Z160: =[8]IN!$I$26 -> #N/A | AA160: =[8]IN!$I$26 -> #N/A | AB160: =[8]IN!$I$26 -> #N/A | AC160: =[8]IN!$I$26 -> #N/A
C162: Piutang biaya pendidikan | AQ162: Tuition and fee receivable
C163: אּ | D163: Piutang santri | Q163: ='1'!K173 -> 664823000 | X163: 647255000 | AP163: Student receivable | AQ163: אּ | AT163: =X163-AS163 -> 647255000 | AV163: 252781830
C164: אּ | D164: Piutang kafil | Q164: ='1'!K192 -> 0 | X164: 0 | AP164: Sponsor receivable | AQ164: אּ | AT164: =X164-AS164 -> 0 | AV164: 85575000
C165: אּ | D165: Piutang santri keluar | Q165: ='1'!K216 -> 182951000 | X165: 182951000 | AP165: Exit student receivable | AQ165: אּ | AT165: =X165-AS165 -> 182951000 | AV165: 228833330
C166: אּ | D166: Piutang tak tertagih - biaya pendidikan | Q166: 0 | X166: 0 | AP166: Uncollectible tuition and fee | AQ166: אּ | AT166: =X166-AS166 -> 0
Q167: =SUM(Q163:V166) -> 847774000 | X167: =SUM(X163:AC166) -> 830206000
C168: אּ | D168: Penyisihan cadangan piutang tak tertagih | Q168: 0 | X168: 0 | AP168: Provision of uncollectable account | AQ168: אּ
C170: Jumlah piutang biaya pendidikan - bersih | Q170: =Q167+Q168 -> 847774000 | X170: =X167+X168 -> 830206000 | AQ170: Total tuition and fee receivable - net
A172: @ | C172: Rincian piutang biaya pendidikan tersedia di lampiran 1 | AQ172: The details of tuition and fee receivable available on appendix 1
B176: 3. | C176: PIUTANG AKTIFITAS - BERSIH (lanjutan) | X176: =B176 -> 3. | Y176: ACCOUNT RECEIVABLE - NET (continued)
C178: Piutang sumbangan dan bantuan | AQ178: Contribution receivable
C179: אּ | D179: Piutang sumbangan dan bantuan | AP179: Contributions and grants | AQ179: אּ
D180: Piutang tak tertagih - sumbangan dan janji | Q180: 0 | X180: 0 | AP180: Uncollectibe contribution and pladges
Q181: =SUM(Q180:V180) -> 0 | X181: =SUM(X180:AC180) -> 0
C182: אּ | D182: Penyisihan cadangan piutang tak tertagih | Q182: 0 | X182: 0 | AP182: Provision of uncollectable account | AQ182: אּ
C184: Jumlah sumbangan - bersih | Q184: =Q182+Q181 -> 0 | X184: =X181+X182 -> 0 | AQ184: Total contribution receivable - net
Q187: =$Q$124 -> 30 June 2026/ | X187: =$X$124 -> 31 May 2026/
Q188: =$Q$125 -> 46203 | X188: =$X$125 -> 46173
C189: Piutang usaha pelengkap | AQ189: Auxiliary enterprises receivable
C190: אּ | D190: Piutang Dagang 6 Mart | Q190: ='12'!E17 -> 140077350 | X190: 73712800 | AP190: Financing receivable 2 | AQ190: אּ
C191: אּ | D191: Piutang Karyawan | Q191: ='14'!C18 -> 0 | X191: ='14'!D18 -> 0 | AP191: Financing receivable 1 | AQ191: אּ
C192: אּ | D192: Piutang lain-lain | Q192: ='14'!C19 -> 0 | X192: ='14'!D19 -> 0 | AP192: Mini market receivable | AQ192: אּ
C193: אּ | D193: Piutang tak tertagih - usaha pelengkap | AP193: Uncollectible auxiliary enterprises | AQ193: אּ
Q194: =SUM(Q190:V193) -> 140077350 | X194: =SUM(X190:AC193) -> 73712800
C195: אּ | D195: Pendapatan ditangguhkan | AP195: Deffered revenue | AQ195: אּ
D196: Pembiayaan 1 | Q196: 0 | X196: 0 | AP196: Financing 1
D197: Pembiayaan 2 | Q197: 0 | X197: 0 | AP197: Financing 2
Q198: =SUM(Q196:V197) -> 0 | X198: =SUM(X196:AC197) -> 0
C200: אּ | D200: Penyisihan cadangan piutang tak tertagih | Q200: 0 | X200: 0 | AP200: Provision of uncollectable account | AQ200: אּ
C202: Jumlah piutang usaha pelengkap - bersih | Q202: =Q194+Q198+Q200 -> 140077350 | X202: =X194+X198+X200 -> 73712800 | AQ202: Total auxiliary enterprises receivable - net
C204: Jumlah piutang aktivitas - bersih | Q204: =Q202+Q184+Q170 -> 987851350 | X204: =X202+X184+X170 -> 903918800 | AQ204: Total account receivable - net
B206: 4. | C206: PIUTANG LAIN - LAIN - BERSIH | X206: =B206 -> 4. | Y206: OTHER RECEIVABLES - NET
C208: Akun ini terdiri dari : | AQ208: This account consists of :
Q209: =Q187 -> 30 June 2026/ | R209: =[8]IN!$G$23 -> 31 July 2023 / | S209: =[8]IN!$G$23 -> 31 July 2023 / | T209: =[8]IN!$G$23 -> 31 July 2023 / | U209: =[8]IN!$G$23 -> 31 July 2023 / | V209: =[8]IN!$G$23 -> 31 July 2023 / | X209: =X187 -> 31 May 2026/ | Y209: =[8]IN!$G$26 -> 30 June 2023 / | Z209: =[8]IN!$G$26 -> 30 June 2023 / | AA209: =[8]IN!$G$26 -> 30 June 2023 / | AB209: =[8]IN!$G$26 -> 30 June 2023 / | AC209: =[8]IN!$G$26 -> 30 June 2023 /
Q210: =Q188 -> 46203 | R210: =[8]IN!$I$23 -> #N/A | S210: =[8]IN!$I$23 -> #N/A | T210: =[8]IN!$I$23 -> #N/A | U210: =[8]IN!$I$23 -> #N/A | V210: =[8]IN!$I$23 -> #N/A | X210: =X188 -> 46173 | Y210: =[8]IN!$I$26 -> #N/A | Z210: =[8]IN!$I$26 -> #N/A | AA210: =[8]IN!$I$26 -> #N/A | AB210: =[8]IN!$I$26 -> #N/A | AC210: =[8]IN!$I$26 -> #N/A
AW211: begin | AX211: add | AY211: end
...

Sheet 1
C1: 2 | D1: 3 | E1: 4 | F1: 5 | G1: 6 | H1: 7 | I1: 8 | J1: 9 | K1: 10 | L1: 11
A2: =CLK!B3 -> PESANTREN ISLAM AL-IRSYAD TENGARAN 6 BONDOWOSO
A4: LAMPIRAN 1 / APPENDIX 1
A5: RINCIAN PIUTANG UANG PENDIDIKAN | L5: DETAILS OF TUITION AND FEE RECEIVABLE
A6: =NRC!B5 -> 30 June 2026 | L6: =NRC!I5 -> 46203
A7: =NRC!C6 -> (Dengan perbandingan informasi keuangan untuk bulan yang berakhir 31 May 2026 / | L7: =NRC!K6 -> With Comparative financial information for the month ended May 31, 2026 )
A8: (Disajikan dalam Rupiah) | L8: (Expressed in rupiah)
A9: (lanjutan) | L9: (continued)
A11: No./ | B11: Uraian / | D11: Kelas / | E11: =NRC!E9 & (IN!D5) -> 30 June 2026/46203 | L11: =NRC!E9 -> 30 June 2026/ | S11: Tgl Invoice | T11: Nama sales | U11: Jumlah | V11: Pembayaran I | Y11: Pembayaran II | AB11: Pembayaran III | AG11: Jumlah
B12: Description | D12: Class | E12: SPP / | F12: Ektra k. / | G12: Dana gedung | H12: D.Perpustakaan | I12: Daftar ulang / | J12: B & Seragam | K12: Jumlah / | L12: =NRC!E10 -> 46203
E13: Tuition | F13: Extra c. | G13: Building fund / | H13: Library fund | I13: Enrollment | J13: B & Uniform | K13: Total
B14: PIUTANG SANTRI / STUDENT RECEIVABLE
C15: MTS / Islamic junior high school
C16: Kelas VII / Class VII
B17: 1 | C17: ABDUL GHOWI TAMIM IMRAN | D17: MTW VII | E17: 15900000 | F17: 0 | G17: 15300000 | H17: 0 | I17: 0 | J17: 0 | K17: =SUM(E17:J17) -> 31200000
B18: 2 | C18: AHNAF ISMAIL AL FAQIH | D18: MTW VII | E18: 0 | F18: 0 | G18: 10500000 | H18: 0 | I18: 0 | J18: 0 | K18: =SUM(E18:J18) -> 10500000
B19: 3 | C19: FAHRI | D19: MTW VII | E19: 500000 | F19: 0 | G19: 0 | H19: 0 | I19: 0 | J19: 0 | K19: =SUM(E19:J19) -> 500000
B20: 4 | C20: ZUBAIR RAJAB | D20: MTW VII | E20: 0 | F20: 0 | G20: 4600000 | H20: 0 | I20: 0 | J20: 0 | K20: =SUM(E20:J20) -> 4600000
B21: 5 | K21: =SUM(E21:J21) -> 0
B22: 6 | K22: =SUM(E22:J22) -> 0
B23: 7 | K23: =SUM(E23:J23) -> 0
B24: 8 | K24: =SUM(E24:J24) -> 0
B25: 9 | K25: =SUM(E25:J25) -> 0
B26: 10 | K26: =SUM(E26:J26) -> 0
B27: 11 | K27: =SUM(E27:J27) -> 0
B28: 12 | K28: =SUM(E28:J28) -> 0
B29: 13 | K29: =SUM(E29:J29) -> 0
B30: 14 | K30: =SUM(E30:J30) -> 0
B31: 15 | K31: =SUM(E31:J31) -> 0
B32: 16 | K32: =SUM(E32:J32) -> 0
... B36: 20 | K36: =SUM(E36:J36) -> 0
E37: =SUM(E17:E36) -> 16400000 | F37: =SUM(F17:F36) -> 0 | G37: =SUM(G17:G36) -> 30400000 | H37: =SUM(H17:H36) -> 0 | I37: =SUM(I17:I36) -> 0 | J37: =SUM(J17:J36) -> 0 | K37: =SUM(K17:K36) -> 46800000
C38: Kelas VIII / Class VIII
B39: 1 | C39: Ahmad Adnan Bayasyut | D39: MTW VIII | E39: 3400000 | F39: 0 | G39: 0 | H39: 0 | I39: 0 | J39: 0 | K39: =SUM(E39:J39) -> 3400000
B40: 2 | C40: Darrell Attharizt Zaidan Alvaro | D40: MTW VIII | E40: 4200000 | F40: 0 | G40: 0 | H40: 0 | I40: 0 | J40: 0 | K40: =SUM(E40:J40) -> 4200000
B41: 3 | C41: Fahri Balafif | D41: MTW VIII | E41: 0 | F41: 0 | G41: 0 | H41: 0 | I41: 2166000 | J41: 0 | K41: =SUM(E41:J41) -> 2166000
B42: 4 | C42: Fahri Muhamad Bakrak | D42: MTW VIII | E42: 600000 | F42: 0 | G42: 0 | H42: 0 | I42: 0 | J42: 0 | K42: =SUM(E42:J42) -> 600000
B43: 5 | C43: Fandi Azwana Ibrahim | D43: MTW VIII | E43: 14450000 | F43: 0 | G43: 11300000 | H43: 0 | I43: 1416000 | J43: 0 | K43: =SUM(E43:J43) -> 27166000
B44: 6 | C44: Fawwaz Tamim Imran | D44: MTW VIII | E44: 3700000 | F44: 0 | G44: 0 | H44: 0 | I44: 100000 | J44: 0 | K44: =SUM(E44:J44) -> 3800000
B45: 7 | C45: Fikri Akid | D45: MTW VIII | E45: 5100000 | F45: 0 | G45: 0 | H45: 0 | I45: 0 | J45: 0 | K45: =SUM(E45:J45) -> 5100000
B46: 8 | C46: Haidar Almairi Tsaqib | D46: MTW VIII | E46: 12347000 | F46: 0 | G46: 0 | H46: 0 | I46: 2166000 | J46: 0 | K46: =SUM(E46:J46) -> 14513000
B47: 9 | C47: Mochamad Lionel Chandra Diputro | D47: MTW VIII | E47: 17266000 | F47: 0 | G47: 0 | H47: 0 | I47: 0 | J47: 0 | K47: =SUM(E47:J47) -> 17266000
B48: 10 | C48: Muadz Faisal Habasy | D48: MTW VIII | E48: 25700000 | F48: 0 | G48: 8750000 | H48: 0 | I48: 2166000 | J48: 0 | K48: =SUM(E48:J48) -> 36616000
B49: 11 | C49: Muhammad Al-fatih | D49: MTW VIII | E49: 1700000 | F49: 0 | G49: 0 | H49: 0 | I49: 0 | J49: 0 | K49: =SUM(E49:J49) -> 1700000
B50: 12 | C50: Muhammad Alief Puji Septianto | D50: MTW VIII | E50: 7700000 | F50: 0 | G50: 5000000 | H50: 0 | I50: 2166000 | J50: 0 | K50: =SUM(E50:J50) -> 14866000
... B53: 15 | C53: Zabdan Zabir | D53: MTW VIII | E53: 1700000 | F53: 0 | G53: 0 | H53: 0 | I53: 0 | J53: 0 | K53: =SUM(E53:J53) -> 1700000
B54: 16 | K54: =SUM(E54:J54) -> 0
B55: 17 | K55: =SUM(E55:J55) -> 0
B56: 18 | K56: =SUM(E56:J56) -> 0
B57: 19 | K57: =SUM(E57:J57) -> 0
B58: 20 | K58: =SUM(E58:J58) -> 0
E59: =SUM(E39:E58) -> 111463000 | F59: =SUM(F39:F58) -> 0 | G59: =SUM(G39:G58) -> 36050000 | H59: =SUM(H39:H58) -> 0 | I59: =SUM(I39:I58) -> 10346000 | J59: =SUM(J39:J58) -> 0 | K59: =SUM(K39:K58) -> 157859000 | L59: 0
C60: Kelas IX / Class IX
B61: 1 | C61: Aulia Laisy Yusuf Cokrokusumo | D61: MTW IX | E61: 4300000 | F61: 0 | G61: 0 | H61: 0 | I61: 2490000 | J61: 0 | K61: =SUM(E61:J61) -> 6790000
B62: 2 | C62: Daffa Ibrahim Nurul Imam | D62: MTW IX | E62: 5100000 | F62: 0 | G62: 0 | H62: 0 | I62: 0 | J62: 0 | K62: =SUM(E62:J62) -> 5100000
B63: 3 | C63: Dhafin Riziq Prastyo | D63: MTW IX | E63: 3400000 | F63: 0 | G63: 0 | H63: 0 | I63: 0 | J63: 0 | K63: =SUM(E63:J63) -> 3400000
B64: 4 | C64: Kayana Alden Pradita Yudistira | D64: MTW IX | E64: 1700000 | F64: 0 | G64: 0 | H64: 0 | I64: 0 | J64: 0 | K64: =SUM(E64:J64) -> 1700000
B65: 5 | C65: Musa Ahmad Dziban | D65: MTW IX | E65: 1700000 | F65: 0 | G65: 0 | H65: 0 | I65: 0 | J65: 0 | K65: =SUM(E65:J65) -> 1700000
B66: 6 | C66: Nabil Banawir | D66: MTW IX | E66: 3000000 | F66: 0 | G66: 0 | H66: 0 | I66: 2129000 | J66: 0 | K66: =SUM(E66:J66) -> 5129000
B67: 7 | C67: Tsagif | D67: MTW IX | E67: 16950000 | F67: 0 | G67: 0 | H67: 0 | I67: 4629000 | J67: 0 | K67: =SUM(E67:J67) -> 21579000
B68: 8 | C68: Amir Ahmad | D68: MTW IX | E68: 1700000 | F68: 0 | G68: 0 | H68: 0 | I68: 0 | J68: 0 | K68: =SUM(E68:J68) -> 1700000
B69: 9 | K69: =SUM(E69:J69) -> 0
B70: 10 | K70: =SUM(E70:J70) -> 0
B71: 11 | K71: =SUM(E71:J71) -> 0
B72: 12 | K72: =SUM(E72:J72) -> 0
B73: 13 | K73: =SUM(E73:J73) -> 0
B74: 14 | K74: =SUM(E74:J74) -> 0
B75: 15 | K75: =SUM(E75:J75) -> 0
B76: 16 | K76: =SUM(E76:J76) -> 0
B77: 17 | K77: =SUM(E77:J77) -> 0
B78: 18 | K78: =SUM(E78:J78) -> 0
B79: 19 | K79: =SUM(E79:J79) -> 0
B80: 20 | K80: =SUM(E80:J80) -> 0
E81: =SUM(E61:E80) -> 37850000 | F81: =SUM(F61:F80) -> 0 | G81: =SUM(G61:G80) -> 0 | H81: =SUM(H61:H80) -> 0 | I81: =SUM(I61:I80) -> 9248000 | J81: =SUM(J61:J80) -> 0 | K81: =SUM(K61:K80) -> 47098000
A82: Jumlah MTW / Total JHS | E82: =E37+E59+E81 -> 165713000 | F82: =F37+F59+F81 -> 0 | G82: =G37+G59+G81 -> 66450000 | H82: =H37+H59+H81 -> 0 | I82: =I37+I59+I81 -> 19594000 | J82: =J37+J59+J81 -> 0 | K82: =K37+K59+K81 -> 251757000
G83: 19
C84: MA / Islamic senior high school
C85: Kelas X / Class X
B86: 1 | C86: AHMAD SAFARAZ | D86: IM X | E86: 1200000 | F86: 0 | G86: 9700000 | I86: 0 | J86: 0 | K86: =SUM(E86:J86) -> 10900000
B87: 2 | C87: FAHMI AYUBI | D87: IM X | E87: 1700000 | F87: 0 | G87: 0 | I87: 0 | J87: 0 | K87: =SUM(E87:J87) -> 1700000
B88: 3 | C88: MOH RAYHAN BAWAZIER | D88: IM X | E88: 1600000 | F88: 0 | G88: 0 | I88: 634000 | J88: 0 | K88: =SUM(E88:J88) -> 2234000
B89: 4 | C89: SALMAN MUADZ BANAWIR | D89: IM X | E89: 4800000 | F89: 0 | G89: 4000000 | I89: 134000 | J89: 0 | K89: =SUM(E89:J89) -> 8934000
B90: 5 | C90: UMAR AL MASHUR | D90: IM X | E90: 1400000 | F90: 0 | G90: 2108000 | I90: 0 | J90: 0 | K90: =SUM(E90:J90) -> 3508000
B91: 6 | C91: YUSUF AKMAL JANJWA | D91: IM X | E91: 3400000 | F91: 0 | G91: 0 | I91: 0 | J91: 0 | K91: =SUM(E91:J91) -> 3400000
B92: 7 | C92: Muhammad Rafi IL | D92: IM X | E92: 10300000 | F92: 0 | G92: 0 | I92: 1684000 | J92: 0 | K92: =SUM(E92:J92) -> 11984000
B93: 8 | C93: Muhammad Rakha Ghazali | D93: IM X | E93: 1700000 | F93: 0 | G93: 0 | I93: 0 | J93: 0 | K93: =SUM(E93:J93) -> 1700000
B94: 9 | C94: Muhammad Zaid Elhaq | D94: IM X | E94: 11900000 | F94: 0 | G94: 0 | I94: 2184000 | J94: 0 | K94: =SUM(E94:J94) -> 14084000
B95: 10 | J95: 0 | K95: =SUM(E95:J95) -> 0
B96: 11 | J96: 0 | K96: =SUM(E96:J96) -> 0
B97: 12 | J97: 0 | K97: =SUM(E97:J97) -> 0
B98: 13 | K98: =SUM(E98:J98) -> 0
B99: 14 | K99: =SUM(E99:J99) -> 0
B100: 15 | K100: =SUM(E100:J100) -> 0
B101: 16 | K101: =SUM(E101:J101) -> 0
B102: 17 | K102: =SUM(E102:J102) -> 0
B103: 18 | K103: =SUM(E103:J103) -> 0
B104: 19 | K104: =SUM(E104:J104) -> 0
B105: 20 | K105: =SUM(E105:J105) -> 0
E106: =SUM(E86:E105) -> 38000000 | F106: =SUM(F86:F105) -> 0 | G106: =SUM(G86:G105) -> 15808000 | H106: =SUM(H86:H105) -> 0 | I106: =SUM(I86:I105) -> 4636000 | J106: =SUM(J86:J105) -> 0 | K106: =SUM(K86:K105) -> 58444000
C107: Kelas XI / Class XI
...

Sheet 2
A2: =NRC!B2 -> PESANTREN ISLAM AL-IRSYAD TENGARAN 6 BONDOWOSO
A4: LAMPIRAN 2 / APPENDIX 2
A5: RINCIAN PIUTANG LAIN LAIN | F5: DETAILS OF OTHER ACCOUNT RECEIVABLES
A6: =NRC!B5 -> 30 June 2026 | F6: =NRC!I5 -> 46203
A7: =NRC!C6 -> (Dengan perbandingan informasi keuangan untuk bulan yang berakhir 31 May 2026 / | F7: =NRC!K6 -> With Comparative financial information for the month ended May 31, 2026 )
A8: =+[12]NRC!B7 -> (Disajikan dalam rupiah) | F8: =+[12]NRC!J7 -> (Expressed in rupiah)
A9: (lanjutan) | F9: (continued)
A11: No. | B11: Uraian / | D11: =NRC!E9 -> 30 June 2026/ | E11: =NRC!G9 -> 31 May 2026/ | F11: Keterangan / | J11: No | K11: Nama Customer | L11: No Invoice | M11: Tgl Invoice | N11: Nama sales | O11: Jumlah | P11: Pembayaran I | S11: Pembayaran II | V11: Pembayaran III | AA11: Jumlah
A12: No. | B12: Desrciption | D12: =NRC!E10 -> 46203 | E12: =NRC!G10 -> 46173 | F12: Remark
A13: 1. | B13: PIUTANG KARYAWAN / EMPLOYEE RECEIVABLE
B14: PIAT
B15: 1 | C15: AHMAD WARDIYANTO | D15: 0 | E15: 300000
B16: 2 | C16: BENI SETIAWAN | D16: 0 | E16: 2400000
B17: 3 | C17: Husein Bafadal | D17: 0 | E17: 1000000
B18: 4 | C18: HARIS MAULANA ISHAQ | D18: 241666.67 | E18: 483333.33
B19: 5 | C19: HANIF MUFTI AL ISLAM | D19: 750000 | E19: 1000000
B20: 6 | C20: NANANG SUGIANTO | D20: 250000 | E20: 1000000
B21: 7 | C21: YOGA NUGRAHA PERMANA (Potong Mulai 5 Des 25) | D21: 1250000 | E21: 1500000
B22: 8 | C22: JUALI EFENDI | D22: 1083333.3 | E22: 1300000
B23: 9 | C23: AJI MAULANA MAJID | D23: 1666666.7 | E23: 2000000
B24: 10 | C24: RIZAL HABIBULLOH (Potong mulai Jan 26) | D24: 1000000 | E24: 2000000
B25: 11 | C25: FARIS | D25: 4000000 | E25: 5000000
B26: 12 | C26: BABUN AGUS TIANTORO | D26: 3500000 | E26: 4000000
... B43: 29 | C43: UMAR | D43: 10768470 | E43: 11747422
B44: 30 | C44: MUHAMMAD ARIF ARIWAKRI | D44: 4000000
B45: 31 | C45: BENI SETIAWAN | D45: 4000000
B46: 32 | C46: FIRDAUS AL'ROSI | D46: 7000000
B47: 33 | C47: IRZADULIBAD | D47: 3600000
B48: 34 | C48: MARWA ROFIQUL ILHAM (Potong Mulai 1 Agustus) | D48: 3000000
D50: =SUM(D15:D49) -> 76049804 | E50: =SUM(E15:E49) -> 69053505
G51: 11429
B52: Lain-lain karyawan / Other employee
B53: 1
B54: 2
D55: =SUM(D53:D54) -> 0 | E55: =SUM(E53:E54) -> 0
A57: Jumlah piutang karyawan / Total employee receivable | D57: =D50+D55 -> 76049804 | E57: =+E48+E55 -> 0 | H57: Untuk eliminasi
A58: 2. | B58: PINJAMAN SANTRI / STUDENT LOAN | G58: =D66-E66 -> 0 | H58: ='[12]14'!I111 -> 1819992316 | I58: ='[12]6'!$F$715 -> 576584225
B59: 1 | C59: Pinjaman Santri | D59: 0 | E59: 0
B60: 2 | C60: Kelebihan pembayaran tabungan
B61: 3 | C61: Piutang tabungan yusran | G61: ='[12]30'!V20 -> 6.6889448e+09
B62: 4 | C62: Piutang kelebihan sewa lapangan badminton
H63: angka elimnisasi
A64: Jumlah pinjaman santri / Total student loan | D64: =SUM(D59:D63) -> 0 | E64: =SUM(E59:E63) -> 0
A65: 3. | B65: PIUTANG LAIN - USAHA PELENGKAP / AUXILIARY ENTERPISES OTHER RECEIVABLE | H65: =#REF!-#REF! -> #REF!
B66: 1 | C66: Kantor | H66: ='[12]6'!#REF! -> #REF!
B67: 2 | C67: Kantin 1 | G67: 1-3461
B68: 3 | C68: Kantin 2
B69: 4 | C69: Kantin 3 | H69: ='[12]6'!#REF! -> #REF!
B70: 5 | C70: Toko
B71: 6 | C71: Laundri
B72: 11 | C72: Lain lain
A73: Jumlah piutang lain - usaha pelengkap / Total other receivable - auxiliary enterprises | D73: =SUM(D66:D72) -> 0 | E73: =SUM(E66:E72) -> 0
B74: PIUTANG PIAT PUSAT / PIAT PUSAT RECEIVABLE
B75: 1
B76: 2
B77: 3
B78: 4
A80: Jumlah Piutang PIAT PUSAT / Total PIAT PUSAT Receivable | D80: =SUM(D77:D78) -> 0 | E80: =SUM(E77:E78) -> 0
B81: PIUTANG YAYASAN / INTITUTION RECEIVABLE
B82: 1 | C82: Cek Masuk BMI Yayasan | D82: 1974000 | E82: 1974000 | F82: Daftar Ulang Atas Nama Ali Albar
B83: 2
A85: Jumlah Piutang Pajak / Total Tax Receivable | D85: =SUM(D82:D84) -> 1974000 | E85: =SUM(E82:E84) -> 1974000 | K85: =E106-E101 -> 0
A86: 4. | B86: PIUTANG PIHAK 3 / THIRD PARTIES RECEIVABLE
B87: Piutang Unit Usaha & Proyek
B88: 1 | C88: Operasional Usaha Juli 2023
B89: 2
B90: 3 | K90: 203728785
B91: 4 | K91: 2.0396878e+08
B92: 5 | K92: =K90-K91 -> -239999.98
B93: 6
B94: 7
B95: 8 | K95: 6989759331
B96: 9 | K96: =H95-K95 -> -6989759331
B97: 10
B98: 11 | K98: 1389850001
B99: 12
B100: 13 | K100: =K96-K98 -> -8379609332
B101: 14
B102: 15
B103: 16
B104: 17
C105: Eliminasi piutang ke Usaha
D106: =SUM(D88:D105) -> 0 | E106: =SUM(E88:E105) -> 0
B107: Piutang Dana BOS
B108: 1 | C108: BOS SDITQ
B109: 2 | C109: BOS MTW
B110: 3 | C110: BOS IM | F110: =D110 -> 0
B111: 4
B112: 5 | K112: =D120-E120 -> 0
B113: 6 | K113: =D121-E121 -> 0
B114: 7
B115: 8
B116: 9 | F116: =SUM(D115:D116) -> 0 | K116: =D124-E124 -> 0
D117: =SUM(D108:D116) -> 0 | E117: =SUM(E108:E116) -> 0 | K117: =D125-E125 -> 0
K118: =D126-E126 -> 0
B119: Lain Lain pihak 3 | K119: =D127-E127 -> 0
B120: 1 | C120: Lain-lain | E120: 0 | K120: =D128-E128 -> 0
B121: 2 | C121: Dana Sosial Civitas | K121: =D129-E129 -> 0
B122: 3 | C122: Thrid part Project | K122: =D130-E130 -> 0
B123: 4 | C123: Others | K123: =D131-E131 -> 0
...

Sheet 3
A2: =NRC!B2 -> PESANTREN ISLAM AL-IRSYAD TENGARAN 6 BONDOWOSO | M2: 181
A4: LAMPIRAN 3 / APPENDIX 3
A5: RINCIAN PERSEDIAAN | I5: DETAIL OF INVENTORIES
A6: =NRC!B5 -> 30 June 2026 | I6: =NRC!I5 -> 46203 | L6: 123721327
A7: =NRC!C6 -> (Dengan perbandingan informasi keuangan untuk bulan yang berakhir 31 May 2026 / | I7: =NRC!K6 -> With Comparative financial information for the month ended May 31, 2026 ) | L7: 213250750
A8: =+[12]NRC!B7 -> (Disajikan dalam rupiah) | I8: =+[12]NRC!J7 -> (Expressed in rupiah)
A9: (lanjutan) | I9: (continued) | K9: 37929540
A11: No. / | B11: Uraian / | C11: Satuan / | D11: =NRC!E9 -> 30 June 2026/ | G11: =NRC!G9 -> 31 May 2026/
A12: No. | B12: Description | C12: Unit | D12: Harga / Price | E12: Qty. | F12: Jumlah / Total | G12: Harga / Price | H12: Qty. | I12: Jumlah / Total
A13: 1 | B13: Buku dan seragam / Books and uniform
A14: 1 | B14: Persediaan seragam Kain Batik & Kain Guru | K14: =SUM(#REF!)-6958000-750000 -> #REF! | L14: ada buku bantu
A15: 2 | B15: Persediaan seragam santri 22/23 | F15: 34870000 | I15: 34870000
A16: 3 | B16: Persediaan Buku santri 22/23 | F16: 38180496 | I16: 38180496
A17: 4 | B17: Persediaan seragam santri 26/27 | D17: 12110000 | E17: 1 | F17: =D17*E17 -> 12110000 | I17: =G17*H17 -> 0
A18: 5 | B18: Persediaan Buku santri 26/27 | D18: 35528685 | E18: 1 | F18: =D18*E18 -> 35528685 | I18: =G18*H18 -> 0
A19: 6 | B19: Sprei dan Sarung Bantal | D19: 75000 | E19: 100 | F19: =D19*E19 -> 7500000 | G19: 75000 | H19: 100 | I19: =G19*H19 -> 7500000
A20: 7 | B20: Bantal | D20: 32290 | E20: 100 | F20: =D20*E20 -> 3229000 | G20: 32290 | H20: 100 | I20: =G20*H20 -> 3229000 | K20: K291225
F21: =SUM(F14:F20) -> 131418181 | I21: =SUM(I14:I20) -> 83779496 | K21: =F21-I21 -> 47638685
A22: 2 | B22: Alat tulis kantor / Stationary
A23: 1 | B23: Ballpoint - 4 Warna | C23: Biji | F23: =D23*E23 -> 0 | I23: =G23*H23 -> 0
A24: 2 | B24: Ballpoint ( Biru ) | C24: Biji | F24: =D24*E24 -> 0 | I24: =G24*H24 -> 0
A25: 3 | B25: Ballpoint ( Hitam ) | C25: Dus | F25: =D25*E25 -> 0 | I25: =G25*H25 -> 0
A26: 4 | B26: Ballpoint ( Merah ) | C26: Biji | F26: =D26*E26 -> 0 | I26: =G26*H26 -> 0
A27: 5 | B27: Ballpoint Meja | C27: Biji | F27: =D27*E27 -> 0 | I27: =G27*H27 -> 0
A28: 6 | B28: Ballpoint R5/ ACTION ( Hitam ) | C28: Biji | F28: =D28*E28 -> 0 | I28: =G28*H28 -> 0
A29: 7 | B29: Boxi / TIZO ( Hitam ) | C29: Biji | F29: =D29*E29 -> 0 | I29: =G29*H29 -> 0
A30: 8 | B30: Pencil TIC | C30: Biji | F30: =D30*E30 -> 0 | I30: =G30*H30 -> 0
A31: 9 | B31: Drawing pen 0,5 mm | C31: Biji | F31: =D31*E31 -> 0 | I31: =G31*H31 -> 0
A32: 10 | B32: Ballpoint PILOT | C32: Biji | F32: =D32*E32 -> 0 | I32: =G32*H32 -> 0
D34: =SUM(D23:D33) -> 0 | E34: =SUM(E23:E33) -> 0 | F34: =SUM(F23:F33) -> 0 | G34: =SUM(G23:G32) -> 0 | H34: =SUM(H23:H32) -> 0 | I34: =SUM(I23:I32) -> 0 | K34: =F34-F35 -> -13778617
A35: 3 | B35: Obat - obatan / Medicines | E35: =[13]ATK!$V$343 -> 6112 | F35: =[14]ATK!$AL$344 -> 13778617 | L35: =E34-E35 -> -6112
A37: 1 | B37: BENANG JAHIT CROMIC | C37: tablet | F37: =D37*E37 -> 0 | I37: =G37*H37 -> 0 | J37: OG101
A38: 2 | B38: BENANG JAHIT CUTGUT | C38: tablet | F38: =D38*E38 -> 0 | I38: =G38*H38 -> 0 | J38: OG102
A39: 3 | B39: BENANG JAHIT SILK | C39: Tube | F39: =D39*E39 -> 0 | I39: =G39*H39 -> 0 | J39: OG301
A40: 4 | B40: DARYANTULE | C40: tablet | F40: =D40*E40 -> 0 | I40: =G40*H40 -> 0 | J40: OB101
A41: 5 | B41: ELASTIS PERBAN | C41: tablet | F41: =D41*E41 -> 0 | I41: =G41*H41 -> 0 | J41: OB102
A42: 6 | B42: HANDSCONE | C42: tablet | F42: =D42*E42 -> 0 | I42: =G42*H42 -> 0 | J42: OB103
A43: 7 | B43: HYGENIK 500 ML | C43: tablet | F43: =D43*E43 -> 0 | I43: =G43*H43 -> 0 | J43: OB104
A44: 8 | B44: JARUM JAHIT | C44: tablet | F44: =D44*E44 -> 0 | I44: =G44*H44 -> 0 | J44: OB105
A45: 9 | B45: KAPAS 1KG | C45: tablet | F45: =D45*E45 -> 0 | I45: =G45*H45 -> 0 | J45: OB106
A46: 10 | B46: KASSA DUS | C46: tablet | F46: =D46*E46 -> 0 | I46: =G46*H46 -> 0 | J46: OB107
A47: 11 | B47: KASSA GULUNG BESAR | C47: tablet | F47: =D47*E47 -> 0 | I47: =G47*H47 -> 0 | J47: OB108
A48: 12 | B48: KASSA GULUNG KECIL | C48: tablet | F48: =D48*E48 -> 0 | I48: =G48*H48 -> 0 | J48: OB109
A49: 13 | B49: KLIP PLASTIK 8X5 | C49: tablet | F49: =D49*E49 -> 0 | I49: =G49*H49 -> 0 | J49: OB110 | K49: laxamex
A50: 14 | B50: PLESTER ROL BESAR | C50: tablet | F50: =D50*E50 -> 0 | I50: =G50*H50 -> 0 | J50: OB111
A51: 15 | B51: SPUIT 3CC | C51: tablet | F51: =D51*E51 -> 0 | I51: =G51*H51 -> 0 | J51: OB112
A52: 16 | B52: SURGICAL BLADE | C52: tablet | F52: =D52*E52 -> 0 | I52: =G52*H52 -> 0 | J52: OB113
A53: 17 | B53: HANSAPLAST PLESTER KAIN | C53: tablet | F53: =D53*E53 -> 0 | I53: =G53*H53 -> 0 | J53: OB114
A54: 18 | B54: COTTON BUD | C54: tablet | F54: =D54*E54 -> 0 | I54: =G54*H54 -> 0 | J54: OB115
A55: 19 | B55: MASKER DISPOSIBLE | C55: tablet | F55: =D55*E55 -> 0 | I55: =G55*H55 -> 0 | J55: OB116
A56: 20 | B56: PLESTER ROL KECIL | C56: tablet | F56: =D56*E56 -> 0 | I56: =G56*H56 -> 0 | J56: OB117
A57: 21 | B57: JARUM BD | C57: tablet | F57: =D57*E57 -> 0 | I57: =G57*H57 -> 0 | J57: OB118
A58: 22 | B58: HYPAVIX 10X5 | C58: Botol | F58: =D58*E58 -> 0 | I58: =G58*H58 -> 0 | J58: OB201
A59: 23 | B59: STIK CHOLESTROL | C59: Botol | F59: =D59*E59 -> 0 | I59: =G59*H59 -> 0 | J59: OB202
A60: 24 | B60: STIK GULA DARAH | C60: Botol | F60: =D60*E60 -> 0 | I60: =G60*H60 -> 0 | J60: OB203
A61: 25 | B61: STIK ASAM URAT | C61: Botol | F61: =D61*E61 -> 0 | I61: =G61*H61 -> 0 | J61: OB204
... A104: 68 | B104: GOM | C104: tablet | F104: =D104*E104 -> 0 | I104: =G104*H104 -> 0 | J104: OK126
A105: 69 | B105: LASERIN 30 ML | C105: tablet | F105: =D105*E105 -> 0 | I105: =G105*H105 -> 0 | J105: OK127 | K105: zicafen
A106: 70 | B106: NEW GUANISTREP 60 ML | C106: tablet | F106: =D106*E106 -> 0 | I106: =G106*H106 -> 0 | J106: OK128
A107: 71 | B107: PARACETAMOL SYR 60 ML | C107: tablet | F107: =D107*E107 -> 0 | I107: =G107*H107 -> 0 | J107: OK129
A108: 72 | B108: PHAROLIT | C108: tablet | F108: =D108*E108 -> 0 | I108: =G108*H108 -> 0 | J108: OK130
A109: 73 | B109: ANTASIDA SYR 60 ML | C109: Botol | F109: =D109*E109 -> 0 | I109: =G109*H109 -> 0 | J109: OK201
A110: 74 | B110: SIRUP PILEK | C110: Botol | F110: =D110*E110 -> 0 | I110: =G110*H110 -> 0 | J110: OK202
A111: 75 | B111: ANTIMO ANAK | C111: Botol | F111: =D111*E111 -> 0 | I111: =G111*H111 -> 0 | J111: OK203
A112: 76 | B112: BODREXIN DEMAM | C112: Tube | F112: =D112*E112 -> 0 | I112: =G112*H112 -> 0 | J112: OK301
A113: 77 | B113: LACTO B | C113: Tube | F113: =D113*E113 -> 0 | I113: =G113*H113 -> 0 | J113: OK302
A114: 78 | B114: IBUPROFEN SYR | C114: Tube | F114: =D114*E114 -> 0 | I114: =G114*H114 -> 0 | J114: OK303
A115: 79 | B115: TIALYSIN | C115: Tube | F115: =D115*E115 -> 0 | I115: =G115*H115 -> 0 | J115: OK304
A116: 80 | B116: LASEIN 60 ML | C116: Tube | F116: =D116*E116 -> 0 | I116: =G116*H116 -> 0 | J116: OK305
A117: 81 | B117: BALSEM GELIGA 10 G | C117: Tube | F117: =D117*E117 -> 0 | I117: =G117*H117 -> 0 | J117: OK306
... A182: 146 | B182: RENADINAC 25 MG | C182: Botol | F182: =D182*E182 -> 0 | I182: =G182*H182 -> 0 | J182: OK204
D184: =SUM(D37:D183) -> 0 | E184: =SUM(E37:E183) -> 0 | F184: =SUM(F37:F183) -> 0 | G184: =SUM(G37:G182) -> 0 | H184: =SUM(H37:H182) -> 0 | I184: =SUM(I37:I183) -> 0
A185: 4 | B185: Informasi Teknologi / Information Technology | E185: 12351 | K185: =F184-F185 -> 0 | L185: =E184-E185 -> -12351
A186: 1 | B186: Adaptor | C186: Biji | F186: =D186*E186 -> 0 | I186: =G186*H186 -> 0
A187: 2 | B187: Batery UPS | C187: Biji | F187: =D187*E187 -> 0 | I187: =G187*H187 -> 0
A188: 3 | B188: Fan Cooler | C188: Biji | F188: =D188*E188 -> 0 | I188: =G188*H188 -> 0
A189: 4 | B189: Hardisk 500GB | C189: Biji | F189: =D189*E189 -> 0 | I189: =G189*H189 -> 0
A190: 5 | B190: Flash disk | C190: Biji | F190: =D190*E190 -> 0 | I190: =G190*H190 -> 0
A191: 6 | B191: Keyboard Usb | C191: Biji | F191: =D191*E191 -> 0 | I191: =G191*H191 -> 0
A192: 7 | B192: Kabel USB printer | C192: Biji | F192: =D192*E192 -> 0 | I192: =G192*H192 -> 0
A193: 8 | B193: LAN Card TF | C193: Biji | F193: =D193*E193 -> 0 | I193: =G193*H193 -> 0
A194: 9 | B194: LAN Card TG | C194: Biji | F194: =D194*E194 -> 0 | I194: =G194*H194 -> 0
A195: 10 | B195: Mouse Usb | C195: Biji | F195: =D195*E195 -> 0 | I195: =G195*H195 -> 0
A196: 11 | B196: Mikrotik Router Board | C196: Biji | F196: =D196*E196 -> 0 | I196: =G196*H196 -> 0
D197: =SUM(D186:D196) -> 0 | E197: =SUM(E186:E196) -> 0 | F197: =SUM(F186:F196) -> 0 | G197: =SUM(G186:G196) -> 0 | H197: =SUM(H186:H196) -> 0 | I197: =SUM(I186:I196) -> 0 | K197: 4
F198: 9213280
A199: 5 | B199: Persediaan Dapur / Kitchen | K199: =F197-F198 -> -9213280
A200: 1 | B200: Persediaan Beras | C200: Kg | F200: =D200*E200 -> 0 | I200: =G200*H200 -> 0 | L200: 9213
A201: 2 | B201: Persediaan Gas | C201: Tabung | F201: =D201*E201 -> 0 | I201: =G201*H201 -> 0 | L201: =F200-L200 -> -9213
A202: 3 | B202: Persediaan Bumbu (Kecap, saos, minyak goreng)
A203: 4 | B203: Persediaan Bahan Minuman (Teh , kopi, gula)
F204: =SUM(F200:F203) -> 0 | I204: =SUM(I200:I203) -> 0 | L204: =L200/E200 -> #DIV/0! | M204: d
A205: 6 | B205: Perlengkapan Kebersihan
A206: 1 | B206: Baygon | F206: =D206*E206 -> 0 | I206: =G206*H206 -> 0
A207: 2 | B207: Bio 2000 | F207: =D207*E207 -> 0 | I207: =G207*H207 -> 0
A208: 3 | B208: Bio L | F208: =D208*E208 -> 0 | I208: =G208*H208 -> 0
A209: 4 | B209: Botol Semprotan | F209: =D209*E209 -> 0 | I209: =G209*H209 -> 0
A210: 5 | B210: Canebo | F210: =D210*E210 -> 0 | I210: =G210*H210 -> 0
A211: 6 | B211: Cling | F211: =D211*E211 -> 0 | I211: =G211*H211 -> 0
A212: 7 | B212: Disinfektan | F212: =D212*E212 -> 0 | I212: =G212*H212 -> 0
...

Sheet 4
A2: PESANTREN ISLAM AL-IRSYAD, TENGARAN
A5: RINCIAN ASET TETAP
A6: 45138
A7: (Dengan perbandingan informasi keuangan 30 Juni 2023 )
A8: (Disajikan dalam rupiah)
A10: No./No. | C10: Uraian / | D10: Lokasi / | E10: Tanggal | F10: Referansi | G10: Qty | H10: UE | I10: Jumlah | J10: Tarif | K10: Harga satuan | L10: Harga perolehan / Acquisition cost | P10: Akumulasi penyusutan / Accumulated depreciation | T10: Nilai buku bersih
C11: Description | D11: Location | L11: =IN!C8 -> 31 May 2026 | M11: Penambahan & | N11: Pengurangan & | O11: =IN!C5 -> 30 June 2026 | P11: =L11 -> 31 May 2026 | Q11: Penambahan & | R11: Pengurangan & | S11: =O11 -> 30 June 2026 | T11: =S11 -> 30 June 2026
M12: reklasifikasi / | N12: reklasifikasi / | Q12: reklasifikasi / | R12: reklasifikasi /
M13: Additions & | N13: Deductions & | Q13: Additions & | R13: Deductions &
M14: reclassification | N14: reclassification | Q14: reclassification | R14: reclassification
A16: 1 | B16: Tanah / Land
B17: 1 | C17: TANAH | D17: PIAT 6 | E17: 44742 | G17: 1 | K17: 2820000000 | L17: 2820000000 | O17: =L17+M17-N17 -> 2820000000 | P17: 0 | S17: 0 | T17: =O17-S17 -> 2820000000 | U17: 1
B18: 2 | C18: TANAH | D18: PIAT 6 | E18: 44834 | G18: 1 | K18: 286270000 | L18: 286270000 | O18: =L18+M18-N18 -> 286270000 | P18: 0 | S18: 0 | T18: =O18-S18 -> 286270000 | U18: 1
B19: 3 | C19: TANAH (Angga Purnama Sari) | D19: PIAT 6 | E19: 44957 | G19: 1 | K19: 253700000 | L19: 253700000 | O19: =L19+M19-N19 -> 253700000 | S19: 0 | T19: =O19-S19 -> 253700000 | U19: 1
B20: 4 | C20: TANAH (DP1) Deny Haji Cung | D20: PIAT 6 | E20: 45293 | F20: CK030124 | G20: 1 | K20: 30000000 | L20: 30000000 | O20: =L20+M20-N20 -> 30000000 | S20: 0 | T20: =O20-S20 -> 30000000 | U20: 1
B21: 5 | C21: TANAH (DP2) Deny Haji Cung | D21: PIAT 6 | E21: 45293 | F21: K010124 | G21: 1 | K21: 20000000 | L21: 20000000 | O21: =L21+M21-N21 -> 20000000 | S21: 0 | T21: =O21-S21 -> 20000000 | U21: 1
B22: 6 | C22: TANAH (DP3) Deny Haji Cung | D22: PIAT 6 | E22: 45350 | F22: CK | G22: 1 | K22: 174000000 | L22: 174000000 | O22: =L22+M22-N22 -> 174000000 | S22: 0 | T22: =O22-S22 -> 174000000 | U22: 1
B23: 7 | C23: TANAH (Pelunasan) Deny Haji Cung | D23: PIAT 6 | E23: 45777 | F23: CK040425 | G23: 1 | K23: 300000000 | L23: 300000000 | O23: =L23+M23-N23 -> 300000000 | T23: =O23-S23 -> 300000000 | U23: 1
C25: TOTAL LAND | L25: =SUM(L17:L23) -> 3883970000 | M25: =SUM(M17:M23) -> 0 | N25: =SUM(N17:N23) -> 0 | O25: =SUM(O17:O23) -> 3883970000 | P25: 0 | Q25: =SUM(Q17:Q23) -> 0 | R25: =SUM(R17:R23) -> 0 | S25: =SUM(S17:S23) -> 0 | T25: =SUM(T17:T23) -> 3883970000
A26: 2 | B26: Gedung / Building
B27: 1 | C27: Building - Class & Office
B28: 1 | C28: Gedung Kelas | D28: PIAT 6 | E28: 43647 | G28: 1 | H28: 20 | I28: 240 | J28: 7083333.3 | K28: 1700000000 | L28: 1700000000 | O28: =L28+M28-N28 -> 1700000000 | P28: 5.8791667e+08 | Q28: =J28 -> 7083333.3 | S28: =P28+Q28-R28 -> 5.95e+08 | T28: =O28-S28 -> 1.105e+09 | U28: 3
B29: 2 | C29: GEDUNG KELAS | D29: PIAT 7 | E29: 44743 | G29: 1 | H29: 20 | I29: =12*H29 -> 240 | J29: =K29/I29 -> 8090218.8 | K29: 1941652520 | L29: 1941652520 | O29: =L29+M29-N29 -> 1941652520 | P29: 3.8024029e+08 | Q29: =J29 -> 8090218.8 | S29: =P29+Q29-R29 -> 3.883305e+08 | T29: =O29-S29 -> 1.553322e+09 | U29: 3
B30: 2 | C30: Kantor EXT | D30: PIAT 8 | E30: 45179 | G30: 1 | H30: 20 | I30: 240 | J30: =K30*G30/I30 -> 2229720 | K30: 535132800 | L30: =K30 -> 535132800 | O30: =L30+M30-N30 -> 535132800 | P30: 42364680 | Q30: =J30 -> 2229720 | S30: =P30+Q30-R30 -> 44594400 | T30: =O30-S30 -> 490538400 | U30: 3
B31: 3 | L31: 0 | O31: =L31+M31-N31 -> 0 | P31: 0 | Q31: =J31 -> 0 | S31: =P31+Q31-R31 -> 0 | T31: =O31-S31 -> 0 | U31: 3
B32: 3 | L32: 0 | O32: =L32+M32-N32 -> 0 | P32: 0 | Q32: =J32 -> 0 | S32: =P32+Q32-R32 -> 0 | T32: =O32-S32 -> 0 | U32: 3
J33: =SUM(J28:J32) -> 17403272 | K33: =SUM(K28:K32) -> 4176785320 | L33: =SUM(L28:L32) -> 4176785320 | M33: =SUM(M28:M32) -> 0 | N33: =SUM(N28:N32) -> 0 | O33: =SUM(O28:O32) -> 4176785320 | P33: =SUM(P28:P32) -> 1.0105216e+09 | Q33: =SUM(Q28:Q32) -> 17403272 | ... T33: =SUM(T28:T32) -> 3.1488604e+09
B34: 2 | C34: Building - Boarding
B35: 1 | C35: ASRAMA | D35: PIAT 6 | E35: 45260 | G35: 1 | H35: 20 | I35: 240 | J35: =K35*G35/I35 -> 13408750 | K35: 3218100000 | L35: =K35 -> 3218100000 | O35: =L35+M35-N35 -> 3218100000 | P35: 254766250 | Q35: =J35 -> 13408750 | S35: =P35+Q35-R35 -> 268175000 | T35: =O35-S35 -> 2949925000 | U35: 4
B36: 2 | U36: 4
B37: 3 | L37: 0 | O37: =L37+M37-N37 -> 0 | P37: 0 | Q37: =J37 -> 0 | S37: =P37+Q37-R37 -> 0 | T37: =O37-S37 -> 0 | U37: 4
J38: =SUM(J35:J37) -> 13408750 | K38: =SUM(K35:K37) -> 3218100000 | L38: =SUM(L35:L37) -> 3218100000 | M38: =SUM(M35:M37) -> 0 | N38: =SUM(N35:N37) -> 0 | O38: =SUM(O35:O37) -> 3218100000 | P38: =SUM(P35:P37) -> 254766250 | Q38: =SUM(Q35:Q37) -> 13408750 | ... T38: =SUM(T35:T37) -> 2949925000
B39: 3 | C39: Building - Housing
B40: 1 | C40: RUMAH GURU | E40: 43647 | G40: 2 | H40: 20 | I40: =12*H40 -> 240 | J40: =K40*G40/I40 -> 1083333.3 | K40: 130000000 | L40: =K40*G40 -> 260000000 | O40: =L40+M40-N40 -> 260000000 | P40: 89916667 | Q40: =J40 -> 1083333.3 | S40: =P40+Q40-R40 -> 91000000 | T40: =O40-S40 -> 1.69e+08 | U40: 5
B41: 2 | C41: RUMAH BUJANG & UKS | E41: 45350 | G41: 1 | H41: 20 | I41: 240 | J41: =K41*G41/I41 -> 3269275 | K41: 784626000 | L41: =K41*G41 -> 784626000 | O41: =L41+M41-N41 -> 784626000 | P41: 62116225 | Q41: =J41 -> 3269275 | S41: =P41+Q41-R41 -> 65385500 | T41: =O41-S41 -> 719240500 | U41: 5
B42: 3 | O42: =L42+M42-N42 -> 0 | P42: 0 | Q42: =J42 -> 0 | S42: =P42+Q42-R42 -> 0 | T42: =O42-S42 -> 0 | U42: 5
B43: 4 | U43: 5
J44: =SUM(J40:J43) -> 4352608.3 | K44: =SUM(K40:K43) -> 914626000 | L44: =SUM(L40:L43) -> 1044626000 | M44: =SUM(M40:M43) -> 0 | N44: =SUM(N40:N43) -> 0 | O44: =SUM(O40:O43) -> 1044626000 | P44: =SUM(P40:P43) -> 1.5203289e+08 | Q44: =SUM(Q40:Q43) -> 4352608.3 | ... T44: =SUM(T40:T43) -> 888240500
B45: 4 | C45: Building - Masjid
B46: 1 | C46: MASJID Ditambah Ke masjid no.3 Bulan Oktober 2025 | D46: PIAT 6 | E46: 43647 | G46: 1 UNIT | H46: 20 | I46: 240 | J46: 2725387.9 | K46: 654093087 | L46: 654093087 | O46: =L46+M46-N46 -> 654093087 | P46: 2.2620719e+08 | Q46: 2725387.9 | S46: =P46+Q46-R46 -> 2.2893258e+08 | T46: =O46-S46 -> 4.2516051e+08 | U46: 6
B47: 2 | C47: TEMPAT WUDHU + 9 KAMAR MANDI | D47: PIAT 6 | E47: 43647 | G47: 1 UNIT | H47: 20 | I47: 240 | J47: 612500 | K47: 147000000 | L47: 147000000 | O47: =L47+M47-N47 -> 147000000 | P47: 50837500 | Q47: 612500 | S47: =P47+Q47-R47 -> 51450000 | T47: =O47-S47 -> 95550000 | U47: 6
B48: 3 | C48: Masjid Baru | D48: PIAT 6 | E48: 45961 | F48: JM091025 | G48: 1 | H48: 20 | I48: 240 | J48: =K48*G48/I48 -> 10380579 | K48: 2491338850 | L48: =K48*G48 -> 2491338850 | O48: =L48+M48-N48 -> 2491338850 | P48: 83044628 | Q48: =J48 -> 10380579 | S48: =P48+Q48-R48 -> 93425207 | T48: =O48-S48 -> 2.3979136e+09 | U48: 6
B49: 4 | C49: Masjid Baru (Galvalum Sebelah Kiri) | D49: PIAT 6 | E49: 46016 | F49: K551225 | G49: 1 | H49: 20 | I49: 240 | J49: =K49*G49/I49 -> 73828.333 | K49: 17718800 | L49: =K49*G49 -> 17718800 | O49: =L49+M49-N49 -> 17718800 | P49: 442970 | Q49: =J49 -> 73828.333 | S49: =P49+Q49-R49 -> 516798.33 | T49: =O49-S49 -> 17202002 | U49: 6
B50: 5 | T50: =O50-S50 -> 0 | U50: 6
B51: 6 | U51: 6
J52: =SUM(J46:J51) -> 13792295 | K52: =SUM(K46:K51) -> 3310150737 | L52: =SUM(L46:L51) -> 3310150737 | M52: =SUM(M46:M51) -> 0 | N52: =SUM(N46:N51) -> 0 | O52: =SUM(O46:O51) -> 3310150737 | P52: =SUM(P46:P51) -> 3.6053229e+08 | Q52: =SUM(Q46:Q51) -> 13792295 | ... T52: =SUM(T46:T51) -> 2.9358262e+09
B53: 5 | C53: Building - Gedung Serba Guna
B54: 1 | U54: 8
B55: 2 | U55: 8
J56: =SUM(J54:J55) -> 0 | K56: =SUM(K54:K55) -> 0 | L56: 0 | M56: =SUM(M54:M55) -> 0 | N56: =SUM(N54:N55) -> 0 | O56: =SUM(O54:O55) -> 0 | P56: 0 | Q56: =SUM(Q54:Q55) -> 0 | R56: =SUM(R54:R55) -> 0 | S56: =SUM(S54:S55) -> 0 | T56: =SUM(T54:T55) -> 0
B57: 6 | C57: Building Kitchen & Laundry
B58: 1 | C58: MATH'AM | E58: 43647 | G58: 1 UNIT | H58: 20 | I58: 240 | J58: 1166666.7 | K58: 280000000 | L58: 280000000 | O58: =L58+M58-N58 -> 280000000 | P58: 96833333 | Q58: 1166666.7 | S58: =P58+Q58-R58 -> 98000000 | T58: =O58-S58 -> 1.82e+08 | U58: 9
B59: 2 | C59: MATH'AM EXT | E59: 45350 | G59: 1 | H59: 20 | I59: 240 | J59: =K59*G59/I59 -> 1126394.8 | K59: 270334750 | L59: =K59 -> 270334750 | O59: =L59+M59-N59 -> 270334750 | P59: 21925035 | Q59: =J59 -> 1126394.8 | S59: =P59+Q59-R59 -> 23051430 | T59: =O59-S59 -> 2.4728332e+08 | U59: 9
B60: 2 | C60: MATH'AM EXT (Penggantian Atap) | D60: CK041225 | E60: 46022 | G60: 1 | H60: 20 | I60: 240 | J60: =K60*G60/I60 -> 43197.917 | K60: 10367500 | L60: =K60*G60 -> 10367500 | O60: =L60+M60-N60 -> 10367500 | P60: 259187.5 | Q60: =J60 -> 43197.917 | S60: =P60+Q60-R60 -> 302385.42 | T60: =O60-S60 -> 10065115 | U60: 9
B61: 3 | O61: =L61+M61-N61 -> 0 | P61: 0 | Q61: =J61 -> 0 | S61: =P61+Q61-R61 -> 0 | T61: =O61-S61 -> 0 | U61: 9
B62: 3 | U62: 9
J63: =SUM(J58:J62) -> 2336259.4 | K63: =SUM(K58:K62) -> 560702250 | L63: =SUM(L58:L62) -> 560702250 | M63: =SUM(M58:M62) -> 0 | N63: =SUM(N58:N62) -> 0 | O63: =SUM(O58:O62) -> 560702250 | P63: =SUM(P58:P62) -> 1.1901756e+08 | Q63: =SUM(Q58:Q62) -> 2336259.4 | ... T63: =SUM(T58:T62) -> 4.3934843e+08
B64: 7 | C64: Building - Others
B65: 1 | C65: POS SATPAM | E65: 43647 | G65: 1 UNIT | H65: 20 | I65: 240 | J65: 50000 | K65: 12000000 | L65: 12000000 | O65: =L65+M65-N65 -> 12000000 | P65: 4150008 | Q65: 50000 | S65: =P65+Q65-R65 -> 4200008 | T65: =O65-S65 -> 7799992 | U65: 10
B66: 2 | C66: KAKI TANDON AIR BETON | E66: 43647 | G66: 1 UNIT | H66: 5 | I66: 60 | J66: 416666.67 | K66: 25000000 | L66: 25000000 | O66: =L66+M66-N66 -> 25000000 | P66: 24999999 | Q66: 0 | S66: =P66+Q66-R66 -> 24999999 | T66: =O66-S66 -> 1 | U66: 10
B67: 3 | U67: 10
B68: 4 | U68: 10
J69: =SUM(J65:J68) -> 466666.67 | K69: =SUM(K65:K68) -> 37000000 | L69: =SUM(L65:L68) -> 37000000 | M69: =SUM(M65:M68) -> 0 | N69: =SUM(N65:N68) -> 0 | O69: =SUM(O65:O68) -> 37000000 | P69: =SUM(P65:P68) -> 29150007 | Q69: =SUM(Q65:Q68) -> 50000 | ... T69: =SUM(T65:T68) -> 7799993
C71: TOTAL BUILDING | J71: =J33+J38+J44+J52+J56+J63+J69 -> 51759851 | K71: =K33+K38+K44+K52+K56+K63+K69 -> 12217364307 | L71: =L33+L38+L44+L52+L56+L63+L69 -> 12347364307 | M71: =M33+M38+M44+M52+M56+M63+M69 -> 0 | N71: =N33+N38+N44+N52+N56+N63+N69 -> 0 | O71: =O33+O38+O44+O52+O56+O63+O69 -> 12347364307 | P71: =P33+P38+P44+P52+P56+P63+P69 -> 1.9260206e+09 | Q71: =Q33+Q38+Q44+Q52+Q56+Q63+Q69 -> 51343185 | ... T71: =T33+T38+T44+T52+T56+T63+T69 -> 1.037e+10
I72: =12*H72 -> 0
B73: INFRASTRUKTUR/INFRASTRUCTURE
B74: 1 | C74: Infrastruktur Jalan / Infrastructure - Road
B75: 1 | C75: paving | E75: 44986 | H75: 5 | I75: 60 | J75: 19425 | K75: 1165500 | L75: 1165500 | O75: =L75+M75-N75 -> 1165500 | P75: 757575 | Q75: =J75 -> 19425 | S75: =P75+Q75-R75 -> 777000 | T75: =O75-S75 -> 388500 | U75: 51
B76: 2 | C76: Paving | E76: 45017 | H76: 5 | I76: 60 | J76: 19000 | K76: 1140000 | L76: 1140000 | O76: =L76+M76-N76 -> 1140000 | P76: 722002 | Q76: =J76 -> 19000 | S76: =P76+Q76-R76 -> 741002 | T76: =O76-S76 -> 398998 | U76: 51
B77: 3 | C77: PAVING JALAN MASUK | E77: 44593 | G77: 1 UNIT | H77: 5 | I77: 60 | J77: 510700 | K77: 30642000 | L77: 30642000 | O77: =L77+M77-N77 -> 30642000 | P77: 26556400 | Q77: =J77 -> 510700 | S77: =P77+Q77-R77 -> 27067100 | T77: =O77-S77 -> 3574900 | U77: 51
B78: 4 | C78: PAVING RUMAH DINAS | E78: 44805 | H78: 5 | I78: 60 | J78: 35533.333 | K78: 2132000 | L78: 2132000 | O78: =L78+M78-N78 -> 2132000 | P78: 1598995 | Q78: =J78 -> 35533.333 | S78: =P78+Q78-R78 -> 1634528.3 | T78: =O78-S78 -> 497471.67 | U78: 51
J80: =SUM(J75:J79) -> 584658.33 | K80: =SUM(K75:K79) -> 35079500 | L80: =SUM(L75:L79) -> 35079500 | M80: =SUM(M75:M79) -> 0 | N80: =SUM(N75:N79) -> 0 | O80: =SUM(O75:O79) -> 35079500 | P80: =SUM(P75:P79) -> 29634972 | Q80: =SUM(Q75:Q79) -> 584658.33 | ... T80: =SUM(T75:T79) -> 4859869.7
B81: 2 | C81: Infrastruktur Selokan/ Infrastructure - Sewerage
U82: 52
U83: 52
Q84: =SUM(Q82:Q83) -> 0
B85: 3 | C85: Infrastruktur Taman / Infrastructure - Garden
B86: 1 | C86: TAMAN MASUK | E86: 44713 | G86: 1 SET | H86: 2 | I86: 24 | J86: 220833.33 | K86: 5300000 | L86: 5300000 | O86: =L86+M86-N86 -> 5300000 | P86: 5299999 | Q86: 0 | S86: =P86+Q86-R86 -> 5299999 | T86: =O86-S86 -> 1 | U86: 53
B87: 2 | C87: TAMAN | E87: 45231 | H87: 2 | I87: 24 | J87: 208333.33 | K87: 5000000 | L87: 5000000 | O87: =L87+M87-N87 -> 5000000 | P87: 4999999 | Q87: 0 | S87: =P87+Q87-R87 -> 4999999 | T87: =O87-S87 -> 1.0033333 | U87: 53
B88: 3 | C88: TAMAN | E88: 45261 | H88: 2 | I88: 24 | J88: 208333.33 | K88: 5000000 | L88: 5000000 | O88: =L88+M88-N88 -> 5000000 | P88: 4999999 | Q88: 0 | S88: =P88+Q88-R88 -> 4999999 | T88: =O88-S88 -> 1 | U88: 53
B89: 4 | C89: TAMAN (Depan Masjid) | D89: Masjid | E89: 45907 | F89: K210925 | G89: 1 | H89: 5 | I89: 60 | J89: =K89*G89/I89 -> 58333.333 | K89: 3500000 | L89: =K89*G89 -> 3500000 | O89: =L89+M89-N89 -> 3500000 | P89: 525000 | Q89: =J89 -> 58333.333 | S89: =P89+Q89-R89 -> 583333.33 | T89: =O89-S89 -> 2916666.7
K91: =SUM(K86:K90) -> 18800000 | L91: =SUM(L86:L90) -> 18800000 | M91: =SUM(M86:M90) -> 0 | N91: =SUM(N86:N90) -> 0 | O91: =SUM(O86:O90) -> 18800000 | P91: =SUM(P86:P90) -> 15824997 | Q91: =SUM(Q86:Q90) -> 58333.333 | R91: =SUM(R86:R90) -> 0 | ... T91: =SUM(T86:T90) -> 2916669.7
B93: 4 | C93: Infrastruktur Lapangan / Infrastructure - Field
B94: 1 | C94: LAMPU GOR | E94: 44593 | G94: 1 SET | H94: 4 | I94: 48 | J94: 46979.167 | K94: 2255000 | L94: 2255000 | O94: =L94+M94-N94 -> 2255000 | P94: 2255000 | Q94: -1 | S94: =P94+Q94-R94 -> 2254999 | T94: =O94-S94 -> 1 | U94: 54
B95: 2 | C95: RING BASKET | E95: 44593 | G95: 2 SET | H95: 2 | I95: 24 | J95: 33512.5 | K95: 804300 | L95: 804300 | O95: =L95+M95-N95 -> 804300 | P95: 804299 | Q95: 0 | S95: =P95+Q95-R95 -> 804299 | T95: =O95-S95 -> 1 | U95: 54
B96: 3 | C96: GERBANG GOR | E96: 44652 | G96: 1 SET | H96: 2 | I96: 24 | J96: 212500 | K96: 5100000 | L96: 5100000 | O96: =L96+M96-N96 -> 5100000 | P96: 5099999 | Q96: 0 | S96: =P96+Q96-R96 -> 5099999 | T96: =O96-S96 -> 1 | U96: 54
B97: 4 | C97: CAT GARIS GOR | E97: 44713 | G97: 1 SET | H97: 2 | I97: 24 | J97: 83333.333 | K97: 2000000 | L97: 2000000 | O97: =L97+M97-N97 -> 2000000 | P97: 1999999 | Q97: 0 | S97: =P97+Q97-R97 -> 1999999 | T97: =O97-S97 -> 1 | U97: 54
B98: 5 | C98: GAWANG BESAR | E98: 44713 | G98: 1 SET | H98: 2 | I98: 24 | J98: 367083.33 | K98: 8810000 | L98: 8810000 | O98: =L98+M98-N98 -> 8810000 | P98: 8809999 | Q98: 0 | S98: =P98+Q98-R98 -> 8809999 | T98: =O98-S98 -> 1 | U98: 54
B99: 6 | C99: GAWANG FUTSAL | E99: 45108 | G99: 1 SET | H99: 2 | I99: 24 | J99: 245833.33 | K99: 5900000 | L99: 5900000 | O99: =L99+M99-N99 -> 5900000 | P99: 5899999 | Q99: 0 | S99: =P99+Q99-R99 -> 5899999 | T99: =O99-S99 -> 0.99666667 | U99: 54
B100: 7 | C100: PANAHAN SANTRI | E100: 45231 | G100: 1 | H100: 2 | I100: 24 | J100: 50000 | K100: 1200000 | L100: 1200000 | O100: =L100+M100-N100 -> 1200000 | P100: 1199999 | Q100: 0 | S100: =P100+Q100-R100 -> 1199999 | T100: =O100-S100 -> 1 | U100: 54 | V100: 900000
K103: =SUM(K94:K102) -> 26069300 | L103: =SUM(L94:L102) -> 26069300 | M103: =SUM(M94:M102) -> 0 | N103: =SUM(N94:N102) -> 0 | O103: =SUM(O94:O102) -> 26069300 | P103: =SUM(P94:P102) -> 26069294 | Q103: =SUM(Q94:Q102) -> -1 | R103: =SUM(R94:R102) -> 0 | ... T103: =SUM(T94:T102) -> 6.9966667
B104: 5 | C104: Infrastruktur Lapangan / Infrastructure - Fence
B105: 1 | C105: Pagar Utara (Kelas Baru) | E105: 45838 | G105: 1 | H105: 20 | I105: 240 | J105: =K105*G105/I105 -> 3299047.9 | K105: 791771500 | L105: =G105*K105 -> 791771500 | O105: =L105+M105-N105 -> 791771500 | P105: 39588575 | Q105: =J105 -> 3299047.9 | S105: =P105+Q105-R105 -> 42887623 | T105: =O105-S105 -> 7.4888388e+08
K109: =SUM(K105:K108) -> 791771500 | L109: =SUM(L105:L108) -> 791771500 | M109: =SUM(M105:M108) -> 0 | N109: =SUM(N105:N108) -> 0 | O109: =SUM(O105:O108) -> 791771500 | P109: =SUM(P105:P108) -> 39588575 | Q109: =SUM(Q105:Q108) -> 3299047.9 | R109: =SUM(R105:R108) -> 0 | ... T109: =SUM(T105:T108) -> 7.4888388e+08
B110: 7 | C110: Infrastruktur Intallation
B111: 1 | C111: Travo/Gardu 66000 VA | D111: PIAT6 | E111: 45716 | F111: CK040225 | G111: 1 | H111: 8 | I111: 96 | J111: =K111*G111/I111 -> 685156.25 | K111: 65775000 | L111: =K111*G111 -> 65775000 | O111: =L111+M111-N111 -> 65775000 | P111: 12195781 | Q111: =J111 -> 685156.25 | S111: =P111+Q111-R111 -> 12880938 | T111: =O111-S111 -> 52894062
B112: 2 | C112: Tambahan material Gardu 66000 VA | D112: PIAT6 | E112: 45747 | F112: CK040325 | G112: 1 | H112: 8 | I112: 96 | J112: =K112*G112/I112 -> 182093.75 | K112: 17481000 | L112: =K112*G112 -> 17481000 | O112: =L112+M112-N112 -> 17481000 | P112: 2949918.8 | Q112: =J112 -> 182093.75 | S112: =P112+Q112-R112 -> 3132012.5 | T112: =O112-S112 -> 14348988
B113: 3 | C113: Instalatir Listrik | D113: PIAT6 | E113: 45808 | F113: CK040525 | G113: 1 | H113: 8 | I113: 96 | J113: =K113*G113/I113 -> 387607.64 | K113: 37210333 | L113: =G113*K113 -> 37210333 | O113: =L113+M113-N113 -> 37210333 | P113: 5038899.3 | Q113: =J113 -> 387607.64 | S113: =P113+Q113-R113 -> 5426506.9 | T113: =O113-S113 -> 31783826
B114: 4 | C114: Instalasi Jaringan & Jasa | D114: PIAT6 | E114: 45824 | F114: K620625 | G114: 1 | H114: 8 | I114: 96 | J114: =K114*G114/I114 -> 105713.54 | K114: 10148500 | L114: =G114*K114 -> 10148500 | O114: =L114+M114-N114 -> 10148500 | P114: 1268562.5 | Q114: =J114 -> 105713.54 | S114: =P114+Q114-R114 -> 1374276 | T114: =O114-S114 -> 8774224
B115: 5 | C115: Tiang Listrik | D115: PIAT6 | E115: 45838 | F115: JM030625 | G115: 4 | H115: 8 | I115: 96 | J115: =K115*G115/I115 -> 139583.33 | K115: 3350000 | L115: =G115*K115 -> 13400000 | O115: =L115+M115-N115 -> 13400000 | P115: 1675000 | Q115: =J115 -> 139583.33 | S115: =P115+Q115-R115 -> 1814583.3 | T115: =O115-S115 -> 11585417
...

Sheet 5
C1: 2 | D1: 3 | E1: 4 | F1: 5 | G1: 6 | H1: 7 | I1: 8
A2: =NRC!B2 -> PESANTREN ISLAM AL-IRSYAD TENGARAN 6 BONDOWOSO
A4: LAMPIRAN 5 / APPENDIX 5
A5: RINCIAN TITIPAN UANG PENDIDIKAN | I5: DETAIL OF TUITION AND FEE DEPOSIT
A6: ='1'!A6 -> 30 June 2026 | I6: ='1'!L6 -> 46203
A7: ='1'!A7 -> (Dengan perbandingan informasi keuangan untuk bulan yang berakhir 31 May 2026 / | I7: ='1'!L7 -> With Comparative financial information for the month ended May 31, 2026 )
A8: (Disajikan dalam Rupiah) | I8: (Expressed in rupiah)
A9: (lanjutan) | I9: (continued)
A11: No./ | B11: Uraian / | D11: Kelas / | E11: =H11 -> 30 June 2026/ | H11: ='1'!L11 -> 30 June 2026/ | I11: Keterangan /
B12: Description | D12: Class | E12: SPP / | F12: Ektra k. / | G12: Jumlah / | H12: ='1'!L12 -> 46203 | I12: Remark
E13: Tuition | F13: Extra c. | G13: Total
A15: 1. | B15: TITIPAN SANTRI / STUDENT RECEIVABLE
C16: MTS / Islamic junior high school
C17: Kelas VII / Class VII
B18: 1 | C18: ALRASYID MAHARDIKA AFANDI | D18: MTW VII | E18: 1900000 | G18: =SUM(E18:F18) -> 1900000 | H18: =G18 -> 1900000
B19: 2 | C19: ALVARO ABDILLAH PRATAMA | D19: MTW VII | E19: 1900000 | G19: =SUM(E19:F19) -> 1900000 | H19: =G19 -> 1900000
B20: 3 | C20: MUHAMMAD ZAHIR | D20: MTW VII | E20: 1050000 | G20: =SUM(E20:F20) -> 1050000 | H20: =G20 -> 1050000
B21: 4 | G21: =SUM(E21:F21) -> 0 | H21: =G21 -> 0
B22: 5 | G22: =SUM(E22:F22) -> 0 | H22: =G22 -> 0
B23: 6 | G23: =SUM(E23:F23) -> 0 | H23: =G23 -> 0
B24: 7 | G24: =SUM(E24:F24) -> 0 | H24: =G24 -> 0
B25: 8 | G25: =SUM(E25:F25) -> 0 | H25: =G25 -> 0
B26: 9 | G26: =SUM(E26:F26) -> 0 | H26: =G26 -> 0
B27: 10 | G27: =SUM(E27:F27) -> 0 | H27: =G27 -> 0
B28: 11 | G28: =SUM(E28:F28) -> 0 | H28: =G28 -> 0
B29: 12 | G29: =SUM(E29:F29) -> 0 | H29: =G29 -> 0
B30: 13 | G30: =SUM(E30:F30) -> 0 | H30: =G30 -> 0
B31: 14 | G31: =SUM(E31:F31) -> 0 | H31: =G31 -> 0
B32: 15 | G32: =SUM(E32:F32) -> 0 | H32: =G32 -> 0
... B37: 20 | G37: =SUM(E37:F37) -> 0 | H37: =G37 -> 0
E38: =SUM(E18:E37) -> 4850000 | F38: =SUM(F18:F37) -> 0 | G38: =SUM(G18:G37) -> 4850000 | H38: =SUM(H18:H37) -> 4850000
C39: Kelas VIII / Class VIII
B40: 1 | C40: Arkaan Dewa Fauzaan | D40: MTW VIII | E40: 1900000 | G40: =SUM(E40:F40) -> 1900000 | H40: =G40 -> 1900000
B41: 2 | C41: Izzatul Ibad | D41: MTW VIII | E41: 22800000 | G41: =SUM(E41:F41) -> 22800000 | H41: =G41 -> 22800000
B42: 3 | C42: Muhammad Aidan Maheswara | D42: MTW VIII | E42: 1900000 | G42: =SUM(E42:F42) -> 1900000 | H42: =G42 -> 1900000
B43: 4 | C43: Muhammad As Silmi Sulaiman | D43: MTW VIII | E43: 1900000 | G43: =SUM(E43:F43) -> 1900000 | H43: =G43 -> 1900000
B44: 5 | C44: Muhammad Faisal Rasyid | D44: MTW VIII | E44: 1900000 | G44: =SUM(E44:F44) -> 1900000 | H44: =G44 -> 1900000
B45: 6 | C45: Muhammad Fauzan Fahriansha | D45: MTW VIII | E45: 1900000 | G45: =SUM(E45:F45) -> 1900000 | H45: =G45 -> 1900000
B46: 7 | G46: =SUM(E46:F46) -> 0 | H46: =G46 -> 0
B47: 9 | G47: =SUM(E47:F47) -> 0 | H47: =G47 -> 0
B48: 10 | G48: =SUM(E48:F48) -> 0 | H48: =G48 -> 0
B49: 11 | G49: =SUM(E49:F49) -> 0 | H49: =G49 -> 0
B50: 12 | G50: =SUM(E50:F50) -> 0 | H50: =G50 -> 0
B51: 13 | G51: =SUM(E51:F51) -> 0 | H51: =G51 -> 0
B52: 14 | G52: =SUM(E52:F52) -> 0 | H52: =G52 -> 0
B53: 15 | G53: =SUM(E53:F53) -> 0 | H53: =G53 -> 0
B54: 16 | G54: =SUM(E54:F54) -> 0 | H54: =G54 -> 0
B55: 17 | G55: =SUM(E55:F55) -> 0 | H55: =G55 -> 0
B56: 18 | G56: =SUM(E56:F56) -> 0 | H56: =G56 -> 0
B57: 19 | G57: =SUM(E57:F57) -> 0 | H57: =G57 -> 0
B58: 20 | G58: =SUM(E58:F58) -> 0 | H58: =G58 -> 0
E59: =SUM(E40:E58) -> 32300000 | F59: =SUM(F40:F58) -> 0 | G59: =SUM(G40:G58) -> 32300000 | H59: =SUM(H40:H58) -> 32300000
C60: Kelas IX / Class IX
B61: 1 | C61: Abdul Azhim Azfar Ats Tsaqib Ibrohim | D61: MTW IX | E61: 1900000 | G61: =SUM(E61:F61) -> 1900000 | H61: =G61 -> 1900000
B62: 2 | C62: Maghribi Abdul Aziim | D62: MTW IX | E62: 1900000 | G62: =SUM(E62:F62) -> 1900000 | H62: =G62 -> 1900000
B63: 3 | C63: Muhammad Rafkhi Al Ayyubi | D63: MTW IX | E63: 1900000 | G63: =SUM(E63:F63) -> 1900000 | H63: =G63 -> 1900000
B64: 4 | G64: =SUM(E64:F64) -> 0 | H64: =G64 -> 0
B65: 5 | G65: =SUM(E65:F65) -> 0 | H65: =G65 -> 0
B66: 6 | G66: =SUM(E66:F66) -> 0 | H66: =G66 -> 0
B67: 7 | G67: =SUM(E67:F67) -> 0 | H67: =G67 -> 0
B68: 8 | G68: =SUM(E68:F68) -> 0 | H68: =G68 -> 0
B69: 9 | G69: =SUM(E69:F69) -> 0 | H69: =G69 -> 0
B70: 10 | G70: =SUM(E70:F70) -> 0 | H70: =G70 -> 0
B71: 11 | G71: =SUM(E71:F71) -> 0 | H71: =G71 -> 0
B72: 12 | G72: =SUM(E72:F72) -> 0 | H72: =G72 -> 0
B73: 13 | G73: =SUM(E73:F73) -> 0 | H73: =G73 -> 0
B74: 14 | G74: =SUM(E74:F74) -> 0 | H74: =G74 -> 0
B75: 15 | G75: =SUM(E75:F75) -> 0 | H75: =G75 -> 0
... B80: 20 | G80: =SUM(E80:F80) -> 0 | H80: =G80 -> 0
E81: =SUM(E61:E80) -> 5700000 | F81: =SUM(F61:F80) -> 0 | G81: =SUM(G61:G80) -> 5700000 | H81: =SUM(H61:H80) -> 5700000
A82: Jumlah MTW / Total SHS | E82: =E38+E59+E81 -> 42850000 | F82: =F38+F59+F81 -> 0 | G82: =G38+G59+G81 -> 42850000 | H82: =H38+H59+H81 -> 42850000
A83: =IN!C4 -> Laporan Keuangan June 2026 | E83: 54 | I83: =IN!D4 -> Financial Statement Jun 2026
C84: MA / Islamic senior high school
C85: Kelas X / Class X
B86: 1 | C86: AHMAD RADHIF WILDAN FATHURRAHMAN | D86: IM X | E86: 400000 | G86: =SUM(E86:F86) -> 400000 | H86: =G86 -> 400000
B87: 2 | C87: FABYAN AL GHAZALY | D87: IM X | E87: 1900000 | G87: =SUM(E87:F87) -> 1900000 | H87: =G87 -> 1900000
B88: 3 | C88: MUHAMMAD DAFFA MAESNA | D88: IM X | E88: 1900000 | G88: =SUM(E88:F88) -> 1900000 | H88: =G88 -> 1900000
B89: 4 | C89: MUHAMMAD WAHBI FAYYADI | D89: IM X | E89: 1900000 | G89: =SUM(E89:F89) -> 1900000 | H89: =G89 -> 1900000
B90: 5 | C90: Abdul Karim | D90: IM X | E90: 1900000 | G90: =SUM(E90:F90) -> 1900000 | H90: =G90 -> 1900000
B91: 6 | C91: Abdurrahman Sudais | D91: IM X | E91: 200000 | G91: =SUM(E91:F91) -> 200000 | H91: =G91 -> 200000
B92: 7 | C92: Dhaifullah M. Marshus | D92: IM X | E92: 1000000 | G92: =SUM(E92:F92) -> 1000000 | H92: =G92 -> 1000000
B93: 8 | C93: Faiz Essyah Hanif | D93: IM X | E93: 1900000 | G93: =SUM(E93:F93) -> 1900000 | H93: =G93 -> 1900000
B94: 9 | C94: Muhamad Luqman Hakim | D94: IM X | E94: 1900000 | G94: =SUM(E94:F94) -> 1900000 | H94: =G94 -> 1900000
B95: 10 | C95: Muhammad Akbar Maulana | D95: IM X | E95: 3000000 | G95: =SUM(E95:F95) -> 3000000 | H95: =G95 -> 3000000
B96: 11 | C96: Radhif | D96: IM X | E96: 1900000 | G96: =SUM(E96:F96) -> 1900000 | H96: =G96 -> 1900000
B97: 12 | C97: Yasa Ageng Suryana | D97: IM X | E97: 1900000 | G97: =SUM(E97:F97) -> 1900000 | H97: =G97 -> 1900000
B98: 13 | G98: =SUM(E98:F98) -> 0 | H98: =G98 -> 0
B99: 14 | G99: =SUM(E99:F99) -> 0 | H99: =G99 -> 0
B100: 15 | G100: =SUM(E100:F100) -> 0 | H100: =G100 -> 0
B101: 16 | G101: =SUM(E101:F101) -> 0 | H101: =G101 -> 0
B102: 17 | G102: =SUM(E102:F102) -> 0 | H102: =G102 -> 0
B103: 18 | G103: =SUM(E103:F103) -> 0 | H103: =G103 -> 0
B104: 19 | G104: =SUM(E104:F104) -> 0 | H104: =G104 -> 0
B105: 20 | G105: =SUM(E105:F105) -> 0 | H105: =G105 -> 0
E106: =SUM(E86:E105) -> 19800000 | F106: =SUM(F86:F105) -> 0 | G106: =SUM(G86:G105) -> 19800000 | H106: =SUM(H86:H105) -> 19800000
C107: Kelas XI / Class XI
B108: 1 | C108: Ahmad Daniar Bi Arsy Diaz Sandjita | D108: IM XI | E108: 51000 | G108: =SUM(E108:F108) -> 51000 | H108: =G108 -> 51000
B109: 2 | C109: Azzam Abiyu Adis | D109: IM XI | E109: 501000 | G109: =SUM(E109:F109) -> 501000 | H109: =G109 -> 501000
B110: 3 | C110: Haikal Malik Ibrahim | D110: IM XI | E110: 900000 | G110: =SUM(E110:F110) -> 900000 | H110: =G110 -> 900000
B111: 4 | C111: Abdur Rohman | D111: IM XI | E111: 200000 | G111: =SUM(E111:F111) -> 200000 | H111: =G111 -> 200000
...

Sheet 6
A2: =NRC!B2 -> PESANTREN ISLAM AL-IRSYAD TENGARAN 6 BONDOWOSO
A4: LAMPIRAN 6 / APPENDIX 6
A5: RINCIAN TITIPAN LAIN LAIN | H5: DETAIL OF OTHER DEPOSITS
A6: =NRC!B5 -> 30 June 2026 | G6: =NRC!I5 -> 46203
A7: =NRC!C6 -> (Dengan perbandingan informasi keuangan untuk bulan yang berakhir 31 May 2026 / | H7: =NRC!K6 -> With Comparative financial information for the month ended May 31, 2026 )
A8: (Disajikan dalam Rupiah) | H8: (Expressed in rupiah)
A9: (lanjutan) | H9: (continued)
A11: No. / | B11: Uraian / | F11: ='2'!D11 -> 30 June 2026/ | G11: ='2'!E11 -> 31 May 2026/ | H11: Keterangan
A12: No. | B12: Description | F12: ='2'!D12 -> 46203 | G12: ='2'!E12 -> 46173 | H12: Remark | L12: No | M12: Nama Customer | N12: No Invoice | O12: Tgl Invoice | P12: Nama sales | Q12: Jumlah | R12: Pembayaran I | U12: Pembayaran II | X12: Pembayaran III | AC12: Jumlah
A13: 1. | B13: Kiriman bank / Bank transfer
B14: Kiriman BMI - pending / BMI transfer - pending
B15: 1 | C15: Transfer | F15: 1300000 | G15: 1300000
B16: 2
B17: 3
B18: 4
B19: 5
B20: 6
B21: 7
B22: 8
B23: 9
B24: 10
B25: 11
B26: 12
B27: 13
... B30: 16
F33: =SUM(F15:F32) -> 1300000 | G33: =SUM(G15:G32) -> 1300000
B34: Kiriman GIRO BMI - pending / BMI transfer - pending | I34: =F33-I33 -> 1300000
B35: 1 | C35: Tranfer BMI Pesantren | D35: 45597 | F35: 150000 | G35: 150000
B36: 2 | C36: Tranfer Giro BMI | D36: 45635 | F36: =500000-500000 -> 0 | G36: 0 | H36: Muhammad Yusuf (VII)
B37: 3 | C37: Tranfer Giro BMI Flips | D37: 45818 | F37: =4500000-4500000 -> 0 | G37: 0 | H37: Muhammad Yusuf (VII)
B38: 4 | C38: Tranfer GIRO BMI (RIZKY FARIZA ) | D38: 45840 | F38: =1000000-1000000 -> 0 | G38: 1000000 | H38: Donasi
B39: 5 | C39: Tranfer GIRO BMI | D39: 45857 | F39: 0 | G39: 0 | H39: Wildan Farid Hamadah
B40: 6 | C40: Tranfer GIRO BMI | D40: 45873 | F40: =5000000-5000000 -> 0 | G40: 0 | H40: Donasi Pengeboran Kelas Baru
B41: 7
B42: 8
B43: 9
B44: 10
F46: =SUM(F35:F45) -> 150000 | G46: =SUM(G35:G45) -> 1150000 | I46: ='[16]AGT-23'!$W$2804 -> 56711946 | J46: =F46-I46 -> -56561946
A47: Jumlah kiriman bank / Total bank transfer | F47: =+F46+F33 -> 1450000 | G47: =+G46+G33 -> 2450000
A48: 2. | B48: Kelebihan pembayaran / Excess payment | J48: l
B49: Kelebihan pembayaran santri / Student excess payment
B50: 1 | C50: Abdul Ghofar IM I
B51: 2 | C51: Miftah Surur IM I
B52: 3 | C52: Ibnu Maulana IM Iib
B53: 4 | C53: Ahmad Zaki
B54: 5 | C54: Nanda Afif A
B55: 6 | C55: Sisa Bea Muh Imam B
F56: =SUM(F50:F55) -> 0 | G56: =SUM(G50:G55) -> 0
B57: Kelebihan pembayaran kafil / Sponsor excess payment
B58: 3 | C58: Hanif Tholib
B59: 4 | C59: Sisa / titipan saku Bp. M. Harhara
B60: 6 | C60: Sisa Beasiswa santri Bp Cholid
B61: 7 | C61: Sisa Beasiswa santri Bp Cholid
F62: =SUM(F58:F61) -> 0 | G62: =SUM(G58:G61) -> 0
B63: Kelebihan pembayaran Santri keluar/ exit student payment
B64: 1 | C64: Muhammad Sahl Abdullah
B65: 2 | C65: Muhammad Hafizh Jafar
B66: 3 | C66: Sulthan Syakir Aryasatya
B67: 4 | C67: Rakha Firdaus Idris
F69: =SUM(F64:F68) -> 0 | G69: =SUM(G64:G68) -> 0
A71: Jumlah kelebihan pembayaran / Total excess payment | F71: =F69+F62+F56 -> 0 | G71: =G69+G62+G56 -> 0
A72: 3. | B72: Bunga bank / Bank interest
B73: 1 | C73: BSM
B74: 2 | C74: BNI - Rp.
B75: 3 | C75: Bank Mandiri
B76: 4 | C76: Pihak ke III | D76: JKM 031006 | E76: 39027
A77: Jumlah bunga bank / Total bank interest | F77: =SUM(F73:F76) -> 0 | G77: =SUM(G73:G76) -> 0
A78: 5. | B78: Lain lain / Others
B79: 1 | C79: Titipan Operasional Yayasan | F79: =61760328 -> 61760328 | G79: 61760328
A82: Jumlah lain lain / Total others | F82: =SUM(F79:F81) -> 61760328 | G82: =SUM(G79:G81) -> 61760328
A84: Jumlah titipan lain lain / Total others deposit | F84: =F82+F77+F71+F47 -> 63210328 | G84: =G82+G77+G71+G47 -> 64210328
F86: 0 | G86: 0
A87: =IN!C4 -> Laporan Keuangan June 2026 | H87: =IN!D4 -> Financial Statement Jun 2026

Sheet 7
A1: =NRC!B2 -> PESANTREN ISLAM AL-IRSYAD TENGARAN 6 BONDOWOSO
A2: RINCIAN BIAYA MASIH HARUS DIBAYAR | G2: DETAIL OF ACCRUED EXPENSES
A3: =NRC!B5 -> 30 June 2026 | G3: =NRC!I5 -> 46203
A4: ='5'!A7 -> (Dengan perbandingan informasi keuangan untuk bulan yang berakhir 31 May 2026 / | G4: =NRC!K6 -> With Comparative financial information for the month ended May 31, 2026 )
A5: =NRC!B7 -> (Disajikan dalam rupiah) | G5: =NRC!K7 -> (Expressed in rupiah)
A6: (lanjutan) | G6: (continued)
A8: No./ | B8: Uraian / | E8: =NRC!E9 -> 30 June 2026/ | F8: =NRC!G9 -> 31 May 2026/ | G8: Keterangan /
A9: No. | B9: Description | E9: =NRC!E10 -> 46203 | F9: =NRC!G10 -> 46173 | G9: Remark
A10: 1. | B10: Gaji dan lembur / Salary and overtime
B11: 1 | C11: Gaji
B12: 1 | C12: Gaji Karyawan bulan April 2025 | D12: GT | E12: 2.4668843e+08 | F12: 2.3665195e+08
E27: =SUM(E12:E26) -> 2.4668843e+08 | F27: =SUM(F12:F26) -> 2.3665195e+08
A28: 2. | B28: Listrik / Electricity
B29: 1 | C29: Biaya Listrik | E29: 0 | F29: 0
A30: 3. | B30: Telekomunikasi/ Telekomunication
B31: 1 | C31: Telpon | E31: 0 | F31: 0
B32: 2 | C32: IT inventory
E33: =SUM(E31:E32) -> 0 | F33: =SUM(F31:F32) -> 0
A34: 4. | B34: Obat / Medicine
B35: 1 | C35: Apotek Husada | E35: =7461145-7521400+3394700-3394700+3253784-8780200+5918400+6938008-7330000+60263 -> 0 | F35: 0
A37: 5. | B37: Lain - lain / Others
B38: 1 | C38: Beras Pak Thoriq | E38: 0 | F38: 0
B39: 2 | C39: Gas Elpiji Ahmad Darsono | E39: 0 | F39: 0
B40: 3 | C40: Gas Elpiji | E40: 0 | F40: 0
E41: =SUM(E38:E40) -> 0 | F41: =SUM(F38:F40) -> 0
A42: 6. | B42: Usaha pelengkap / Auxiliary enterprises
B43: 1 | C43: Wartel | E43: 0 | F43: 0
B44: 2 | C44: Kantin 1 | E44: 0 | F44: 0
B45: 3 | C45: Kantin 2 | E45: 0 | F45: 0
B46: 4 | C46: Kantin 3 | E46: 0 | F46: 0
B47: 5 | C47: Kantin 4 | E47: 0 | F47: 0
B48: 6 | C48: Toko | E48: 0 | F48: 0
E49: =SUM(E43:E48) -> 0 | F49: =SUM(F43:F48) -> 0
A51: Jumlah biaya masih harus dibayar / Total accrued expenses | E51: =E41+E33+E35+E29+E49 -> 0 | F51: =F41+F33+F35+F29+F49 -> 0
A54: =IN!C4 -> Laporan Keuangan June 2026 | G54: =IN!D4 -> Financial Statement Jun 2026

Sheet 8
A1: =NRC!B2 -> PESANTREN ISLAM AL-IRSYAD TENGARAN 6 BONDOWOSO
A3: LAMPIRAN 8 / APPENDIX 8
A4: RINCIAN ASET BERSIH TERIKAT | Q4: DETAIL OF RESTRICTED NET ASSETS
A5: =NRC!B5 -> 30 June 2026 | P5: =NRC!I5 -> 46203
A6: ='7'!A4 -> (Dengan perbandingan informasi keuangan untuk bulan yang berakhir 31 May 2026 / | Q6: =NRC!K6 -> With Comparative financial information for the month ended May 31, 2026 )
A7: =NRC!B7 -> (Disajikan dalam rupiah) | Q7: =+[17]NRC!J7 -> (Expressed in rupiah)
A9: No./ | B9: Uraian / Description | N9: Saldo / | O9: Penambahan / | P9: Pembebasan dari | Q9: Saldo / | S9: ="Sd " & Q11 -> Sd 30 June 2026/
A10: No. | N10: Balance | O10: Additions | P10: pembatasan / | Q10: Balance | S10: =Q12 -> 46203
N11: =NRC!G9 -> 31 May 2026/ | P11: Release from | Q11: =NRC!E9 -> 30 June 2026/ | S11: Penambahan / | T11: Pembebasan / | U11: Saldo / Balance | W11: =N11 -> 31 May 2026/
N12: =NRC!G10 -> 46173 | P12: restriction | Q12: =NRC!E10 -> 46203 | S12: Additions | T12: Release
A13: 1 | B13: TERIKAT TEMPORER / TEMPORARELY RESTRICTED
A14: 1 | B14: Terikat program / program restrictions
B15: Akademik / Academic
B16: 1 | C16: BOS SDITQ - Diknas | N16: 0 | Q16: =N16+O16-P16 -> 0
B17: 2 | C17: BOS MTS - Depag | N17: 183016600 | P17: 7361800 | Q17: =N17+O17-P17 -> 175654800 | S17: =W17+O17 -> 232080000 | T17: =X17+P17 -> 105406800 | U17: =S17-T17 -> 126673200 | W17: 232080000 | X17: 98045000
B18: 3 | C18: BOOM MA - Depag | N18: 168206100 | P18: 6216400 | Q18: =N18+O18-P18 -> 161989700 | S18: =W18+O18 -> 296996100 | T18: =X18+P18 -> 158174100 | U18: =S18-T18 -> 138822000 | W18: 296996100 | X18: 151957700
N19: =SUM(N16:N18) -> 351222700 | O19: =SUM(O16:O18) -> 0 | P19: =SUM(P16:P18) -> 13578200 | Q19: =SUM(Q16:Q18) -> 337644500 | S19: =SUM(S17:S18) -> 529076100 | T19: =SUM(T17:T18) -> 263580900 | U19: =SUM(U17:U18) -> 265495200 | W19: =SUM(W17:W18) -> 529076100 | X19: =SUM(X17:X18) -> 250002700
B20: Dakwah dan sosial / Propaganda and social
B21: 1 | C21: Kurban Idul Adha / Sacrifice fund - Idul Adha
C22: אּ | D22: Qurban | N22: 0 | O22: 500000 | P22: 500000 | Q22: =N22+O22-P22 -> 0 | S22: =W22+O22 -> 70000000 | T22: =SUM(T20:T21) -> 0 | U22: =SUM(U20:U21) -> 0 | W22: 69500000 | X22: 0
C23: אּ | D23: Penjualan Kulit | I23: m241208 | N23: 0 | Q23: =N23+O23-P23 -> 0 | S23: =W23+O23 -> 0 | T23: =SUM(T21:T22) -> 0 | U23: =SUM(U21:U22) -> 0
N24: =SUM(N22:N23) -> 0 | O24: =SUM(O22:O23) -> 500000 | P24: =SUM(P22:P23) -> 500000 | Q24: =SUM(Q22:Q23) -> 0 | S24: =SUM(S22:S23) -> 70000000 | T24: =SUM(T22:T23) -> 0 | U24: =SUM(U22:U23) -> 0 | W24: =SUM(W22:W23) -> 69500000 | X24: =SUM(X22:X23) -> 0
C25: Zakat maal / Zakat maal
C26: אּ | D26: Zakat maal | N26: 0 | O26: 0 | P26: 0 | Q26: =N26+O26-P26 -> 0 | S26: =W26+O26 -> 5000000 | T26: =X26+P26 -> 5000000 | U26: =S26-T26 -> 0 | W26: 5000000 | X26: 5000000
C27: Ifthor ramadhan / Breaking fasting ramadan | S27: =W27+O27 -> 0 | T27: =X27+P27 -> 0 | U27: =S27-T27 -> 0 | W27: 0 | X27: 0
C28: אּ | D28: Dana Ifthor | N28: 0 | O28: 0 | P28: 0 | Q28: =N28+O28-P28 -> 0 | S28: =W28+O28 -> 22200000 | T28: =X28+P28 -> 22200000 | U28: =S28-T28 -> 0 | W28: 22200000 | X28: 22200000
B29: 2 | C29: Sosial / Social | S29: =W29+O29 -> 0 | T29: =X29+P29 -> 0 | U29: =S29-T29 -> 0 | W29: 0 | X29: 0
C30: אּ | D30: Donasi Bencana Sumatera & Aceh | N30: 0 | O30: 0 | P30: 0 | Q30: =N30+O30-P30 -> 0 | S30: =W30+O30 -> 11963300 | T30: =X30+P30 -> 11963300 | U30: =S30-T30 -> 0 | W30: 11963300 | X30: 11963300
C31: אּ | D31: Kotak Infak Masjid | N31: 0 | Q31: =N31+O31-P31 -> 0 | S31: =W31+O31 -> 0 | T31: =X31+P31 -> 0 | U31: =S31-T31 -> 0 | W31: 0 | X31: 0
N32: =SUM(N30:N31) -> 0 | O32: =SUM(O30:O31) -> 0 | P32: =SUM(P30:P31) -> 0 | Q32: =SUM(Q30:Q31) -> 0 | S32: =SUM(S30:S31) -> 11963300 | T32: =SUM(T30:T31) -> 11963300 | U32: =S32-T32 -> 0 | W32: =SUM(W30:W31) -> 11963300 | X32: =SUM(X30:X31) -> 11963300
N34: =N32+N28+N26+N24 -> 0 | O34: =O32+O28+O26+O24 -> 500000 | P34: =P32+P28+P26+P24 -> 500000 | Q34: =Q32+Q28+Q26+Q24 -> 0 | S34: =S32+S28+S26+S24 -> 109163300 | T34: =T32+T28+T26+T24 -> 39163300 | U34: =U32+U28+U26+U24 -> 0 | W34: =W32+W28+W26+W24 -> 108663300 | X34: =X32+X28+X26+X24 -> 39163300
B35: Bantuan keuangan santri / Student financial aid
B36: 1 | C36: Beasiswa / Scholarship
C37: אּ | D37: Beasiswa dari MTS | N37: 0 | Q37: =N37+O37-P37 -> 0 | S37: =W37+O37 -> 0 | T37: =X37+P37 -> 0 | U37: =S37-T37 -> 0
C38: אּ | D38: Pemerintah & Donatur | N38: 0 | Q38: =N38+O38-P38 -> 0 | S38: =W38+O38 -> 0 | T38: =X38+P38 -> 0 | U38: =S38-T38 -> 0
C39: אּ | D39: Beasiswa dari Mushinin | N39: 0 | Q39: =N39+O39-P39 -> 0 | S39: =W39+O39 -> 0 | T39: =X39+P39 -> 0 | U39: =S39-T39 -> 0
N40: =SUM(N37:N39) -> 0 | O40: =SUM(O37:O39) -> 0 | P40: =SUM(P37:P39) -> 0 | Q40: =SUM(Q37:Q39) -> 0 | S40: =SUM(S37:S39) -> 0 | T40: =SUM(T37:T39) -> 0 | U40: =SUM(U37:U39) -> 0 | W40: =SUM(W37:W39) -> 0 | X40: =SUM(X37:X39) -> 0
B41: 2 | C41: Santri yatim / Fatherless student
C42: אּ | D42: Muslim World League | M42: 39164 | N42: 0 | Q42: =N42+O42-P42 -> 0 | S42: =W42+O42 -> 0 | T42: =X42+P42 -> 0 | U42: =S42-T42 -> 0
C43: אּ | D43: Lain - lain | I43: M2300409 | M43: 39919 | N43: 0 | O43: 0 | P43: 0 | Q43: =N43+O43-P43 -> 0 | S43: =W43+O43 -> 0 | T43: =X43+P43 -> 0 | U43: =S43-T43 -> 0
N44: =SUM(N42:N43) -> 0 | O44: =SUM(O42:O43) -> 0 | P44: =SUM(P42:P43) -> 0 | Q44: =SUM(Q42:Q43) -> 0 | S44: =SUM(S42:S43) -> 0 | T44: =SUM(T42:T43) -> 0 | U44: =SUM(U42:U43) -> 0 | W44: =SUM(W42:W43) -> 0 | X44: =SUM(X42:X43) -> 0
B46: Jumlah terikat program / Total program retrictions | N46: =N44+N40+N34+N19 -> 351222700 | O46: =O44+O40+O34+O19 -> 500000 | P46: =P44+P40+P34+P19 -> 14078200 | Q46: =Q44+Q40+Q34+Q19 -> 337644500 | S46: =S44+S40+S34+S19 -> 638239400 | T46: =T44+T40+T34+T19 -> 302744200 | U46: =U44+U40+U34+U19 -> 265495200 | W46: =W44+W40+W34+W19+W24 -> 707239400 | X46: =X44+X40+X34+X19+X24 -> 289166000
A47: 2 | B47: Terikat perolehan Aset tetap / Fixed assets acquisition restriction
B48: 1 | C48: Peralatan / Equipment
C49: אּ | D49: Yayasan Pendidikan | N49: 0 | Q49: =N49+O49-P49 -> 0 | S49: =W49+O49 -> 0 | T49: =X49+P49 -> 0 | U49: =S49-T49 -> 0
N50: 0 | O50: =SUM(O49) -> 0 | P50: =SUM(P49) -> 0 | Q50: =SUM(Q49) -> 0
B51: 1 | C51: Gedung / Building
C52: אּ | D52: Bnagun Masjid & Kelas Baru | N52: 0 | O52: 0 | P52: 0 | Q52: =N52+O52-P52 -> 0 | S52: =W52+O52 -> 1872200000 | T52: =X52+P52 -> 1872200000 | U52: =S52-T52 -> 0 | W52: 1872200000 | X52: 1872200000
C53: אּ | D53: Sumur | N53: 0 | Q53: =N53+O53-P53 -> 0 | S53: =W53+O53 -> 0 | T53: =X53+P53 -> 0 | U53: =S53-T53 -> 0 | W53: 0 | X53: 0
C54: אּ | D54: Saluran Air | N54: 0 | Q54: =N54+O54-P54 -> 0 | S54: =W54+O54 -> 0 | T54: =X54+P54 -> 0 | U54: =S54-T54 -> 0 | W54: 0 | X54: 0
C55: אּ | D55: Infrastruktur | N55: 0 | Q55: =N55+O55-P55 -> 0 | S55: =W55+O55 -> 0 | T55: =X55+P55 -> 0 | U55: =S55-T55 -> 0 | W55: 0 | X55: 0
C56: אּ | D56: Kendaraan | N56: 0 | O56: 0 | P56: 0 | Q56: =N56+O56-P56 -> 0 | S56: =W56+O56 -> 215150000 | T56: =X56+P56 -> 215150000 | U56: =S56-T56 -> 0 | W56: 215150000 | X56: 215150000
C57: אּ | D57: Tanah | N57: 0 | O57: 0 | P57: 0 | Q57: =N57+O57-P57 -> 0 | S57: =W57+O57 -> 524000000 | T57: =X57+P57 -> 524000000 | U57: =S57-T57 -> 0 | W57: 524000000 | X57: 524000000
C58: אּ | D58: Lain-lain | E58: Sumbangan wastafel dari unilever | N58: 0 | O58: 0 | P58: 0 | Q58: =N58+O58-P58 -> 0 | S58: =W58+O58 -> 28736544 | T58: =X58+P58 -> 28736544 | U58: =S58-T58 -> 0 | W58: 28736544 | X58: 28736544
N59: =SUM(N52:N58) -> 0 | O59: =SUM(O52:O58) -> 0 | P59: =SUM(P52:P58) -> 0 | Q59: =SUM(Q52:Q58) -> 0 | S59: =SUM(S52:S58) -> 2640086544 | T59: =SUM(T52:T58) -> 2640086544 | U59: =SUM(U52:U58) -> 0 | W59: =SUM(W52:W58) -> 2640086544 | X59: =SUM(X52:X58) -> 2640086544
B61: Jumlah terikat Perolehan Aset tetap / Fixed assets acquisition restriction | N61: 0 | O61: =O59+O50 -> 0 | P61: =P59+P50 -> 0 | Q61: =Q59+Q50 -> 0 | S61: =S59+S50 -> 2640086544 | T61: =T59+T50 -> 2640086544 | U61: =U59+U50 -> 0 | W61: =W59+W50 -> 2640086544 | X61: =X59+X50 -> 2640086544
A63: Jumlah terikat temporer / Total temporarily restriction | N63: =N61+N46 -> 351222700 | O63: =O61+O46 -> 500000 | P63: =P61+P46 -> 14078200 | Q63: =Q61+Q46 -> 337644500 | S63: =S61+S46 -> 3278325944 | T63: =T61+T46 -> 2942830744 | U63: =U61+U46 -> 265495200 | W63: =W61+W46 -> 3347325944 | X63: =X61+X46 -> 2929252544
A64: 2 | B64: TERIKAT PERMANEN / PERMANENTLY RESTRICTED
C65: אּ | D65: Gedung | N65: 3078093087 | O65: 0 | P65: 0 | Q65: =N65+O65-P65 -> 3078093087
C66: אּ | D66: Tanah | N66: 3359970000 | Q66: =N66+O66-P66 -> 3359970000
A68: Jumlah terikat permanen / Total permanently retriction | N68: =SUM(N65:N67) -> 6438063087 | O68: =SUM(O65:O67) -> 0 | P68: =SUM(P65:P67) -> 0 | Q68: =SUM(Q65:Q67) -> 6438063087
A70: Jumlah Aset bersih terikat / Total restricted net assets | N70: =N68+N63 -> 6789285787 | O70: =O68+O63 -> 500000 | P70: =P68+P63 -> 14078200 | Q70: =Q68+Q63 -> 6775707587
N71: =N70-NRC!G72 -> 0 | Q71: =Q70-NRC!E72 -> 0
A73: =IN!C4 -> Laporan Keuangan June 2026 | N73: 68 | Q73: =IN!D4 -> Financial Statement Jun 2026

Sheet 9
A2: PESANTREN ISLAM AL-IRSYAD TENGARAN 6 BONDOWOSO
A4: LAMPIRAN 9 / APPENDIX 9
A5: RINCIAN PENDAPATAN DAN KEUNTUNGAN TIDAK TERIKAT | M5: DETAIL OF UNRESTRICTED REVENUE AND GAINS
A6: =LR!C6 -> Untuk Bulan yang Berakhir 30 June 2026 | L6: =LR!I6 -> For The Month Ended Jun 2026
A7: =LR!C7 -> (Dengan perbandingan informasi keuangan untuk bulan yang berakhir 31 May 2026 / | L7: =LR!O7 -> With Comparative financial information for the month ended May 31, 2026 ) | M7: ( With comparative financial information for the month
L8: =[18]RL!O8 -> #N/A | M8: ended July 31, 2009 )
A9: ='[9]LR '!B9 -> (Disajikan dalam rupiah) | L9: ='[9]LR '!N9 -> (Expressed in rupiah) | M9: (Expressed in rupiah ) | O9: CONTROL SALDO
B11: Pos - pos | D11: =LR!E11 -> 30 June 2026/ | E11: % | F11: Catatan / | G11: =LR!H11 -> 31 May 2026/ | H11: % | I11: ="sd "&(D11) -> sd 30 June 2026/ | J11: % | K11: Accounts | O11: ="sd "&G11 -> sd 31 May 2026/
D12: =LR!E12 -> 46203 | F12: Notes | G12: =LR!H12 -> 46173 | I12: =LR!K12 -> 46203 | O12: s/d bulan sebelumnya
B13: Pendapatan dan keuntungan tidak terikat | L13: Unrestricted revenues & gains
B14: Pendapatan pendidikan | L14: Tuition and fees
B15: אּ | C15: SPP | D15: =RL!C38+RL!C59 -> 547400000 | G15: 552500000 | I15: =D15+O15 -> 6692650000 | K15: Tuition | L15: אּ | O15: 6145250000
B16: אּ | C16: Ekstrakurikuler | D16: =RL!C39+RL!C60 -> 0 | G16: 0 | I16: =D16+O16 -> 0 | K16: Extra curriculer | L16: אּ | O16: 0
B17: אּ | C17: Ujian akhir semester | D17: =RL!C40+RL!C61 -> 0 | G17: 0 | I17: =D17+O17 -> 0 | K17: Examination fee | L17: אּ | O17: 0
B18: אּ | C18: Daftar ulang | D18: =RL!C42+RL!C63 -> 0 | G18: 0 | I18: =D18+O18 -> 578289000 | K18: Enrollment fee | L18: אּ | O18: 578289000
B19: אּ | C19: Dana pengembangan | D19: =RL!C47+RL!C68 -> 0 | G19: 0 | I19: =D19+O19 -> 1207500000 | K19: Development fund | L19: אּ | O19: 1207500000
B20: אּ | C20: Kegiatan santri | D20: =RL!C44+RL!C65+RL!C66 -> 0 | G20: 0 | I20: =D20+O20 -> 74100000 | K20: Student activity | L20: אּ | O20: 74100000
B21: אּ | C21: Pendaftaran santri baru | D21: =RL!C50 -> 0 | G21: 0 | I21: =D21+O21 -> 22500000 | K21: Admission fee | L21: אּ | O21: 22500000
D22: =SUM(D15:D21) -> 547400000 | E22: =SUM(E15:E21) -> 0 | F22: =SUM(F15:F21) -> 0 | G22: 552500000 | H22: =SUM(H15:H21) -> 0 | I22: =SUM(I15:I21) -> 8575039000 | O22: 8027639000
B24: אּ | C24: Dikurangi : Potongan Pendidikan | D24: =-RL!C221 -> 3950000 | G24: 4200000 | I24: =D24+O24 -> 70768000 | K24: Less : scholarship | L24: אּ | O24: 66818000
D25: =D22-D24 -> 543450000 | E25: =E22-E24 -> 0 | F25: =F22-F24 -> 0 | G25: 548300000 | H25: =H22-H24 -> 0 | I25: =I22-I24 -> 8504271000 | O25: 7960821000
B26: Sumbangan | L26: Contributions
B27: אּ | C27: Pemerintah | D27: =RL!C81 -> 0 | G27: 0 | I27: =D27+O27 -> 0 | K27: Government | L27: אּ | O27: 0
B28: אּ | C28: Pemerintah daerah | D28: =RL!C82 -> 0 | G28: 0 | I28: =D28+O28 -> 0 | K28: Local government | L28: אּ | O28: 0
B29: אּ | C29: Lembaga bisnis | D29: =RL!C83 -> 0 | G29: 0 | I29: =D29+O29 -> 0 | K29: Bussines institution | L29: אּ | O29: 0
B30: אּ | C30: Lembaga sosial (Yayasan) | D30: =RL!C84 -> 0 | G30: 0 | I30: =D30+O30 -> 0 | K30: Social institution | L30: אּ | O30: 0
B31: אּ | C31: Masyarakat | D31: =RL!C85 -> 0 | G31: 0 | I31: =D31+O31 -> 0 | K31: Sociaty | L31: אּ | O31: 0
B32: אּ | C32: Wali santri | D32: =RL!C86 -> 0 | G32: 0 | I32: =D32+O32 -> 0 | K32: Student parents | L32: אּ | O32: 0
B33: אּ | C33: Donatur | D33: =RL!C87 -> 0 | G33: 0 | I33: =D33+O33 -> 0 | K33: Donors | L33: אּ | O33: 0
B34: אּ | C34: Pribadi | D34: =RL!C88 -> 1000000 | G34: 0 | I34: =D34+O34 -> 1000000 | K34: Private | L34: אּ | O34: 0
B35: אּ | C35: Lain lain | D35: =RL!C89+RL!C134+RL!C123 -> 100 | G35: 168 | I35: =D35+O35 -> 31304.33 | K35: Others | L35: אּ | O35: 31204.33
D36: =SUM(D27:D35) -> 1000100 | E36: =SUM(E27:E35) -> 0 | F36: =SUM(F27:F35) -> 0 | G36: 168 | H36: =SUM(H27:H35) -> 0 | I36: =SUM(I27:I35) -> 1031304.3 | O36: 31204.33
B37: Hibah & kontrak | D37: =RL!C101+RL!C112 -> 0 | G37: 0 | L37: Grants & contracs
B38: Penjualan & layanan | L38: Sales & services
B39: אּ | C39: Buku | D39: =RL!C139 -> 0 | G39: 40000 | I39: =D39+O39 -> 1374500 | K39: Books | L39: אּ | O39: 1374500
B40: אּ | C40: Seragam | D40: =RL!C140 -> 0 | G40: 0 | I40: =D40+O40 -> 7500000 | K40: Uniform | L40: אּ | O40: 7500000
B41: אּ | C41: Layanan | D41: =RL!C153 -> 0 | G41: 0 | I41: =D41+O41 -> 0 | K41: Car charges | L41: אּ | O41: 0
B42: אּ | C42: Barang bekas | D42: =SUM(RL!C141:C147) -> 50000 | G42: 374950 | I42: =D42+O42 -> 2039950 | K42: Scraps | L42: אּ | O42: 1989950
D44: =SUM(D39:D43) -> 50000 | E44: =SUM(E39:E43) -> 0 | G44: 414950 | H44: =SUM(H39:H43) -> 0 | I44: =SUM(I39:I43) -> 10914450 | O44: 10864450
B45: Penghasilan investasi | I45: =D45+O45 -> 0 | L45: Investment income | O45: 0
B46: Usaha pelengkap | L46: Auxiliary enterprises
B47: אּ | C47: Kantin 6 Mart | D47: ='13'!E13 -> 82572250 | G47: 129992100 | I47: =D47+O47 -> 1332016556 | K47: Financing 1 | L47: אּ | O47: 1249444306
B48: אּ | C48: Pembiayaan 2 | I48: =D48+O48 -> 0 | K48: Financing 2 | L48: אּ | O48: 0
B49: אּ | C49: Wartel | I49: =D49+O49 -> 0 | K49: Telephone cabin | L49: אּ | O49: 0
B50: אּ | C50: Kantin 1 | I50: =D50+O50 -> 0 | K50: Canteen 1 | L50: אּ | O50: 0
B51: אּ | C51: Kantin 2 | I51: =D51+O51 -> 0 | K51: Canteen 2 | L51: אּ | O51: 0
B52: אּ | C52: Kantin 3 | I52: =D52+O52 -> 0 | K52: Canteen 3 | L52: אּ | O52: 0
B53: אּ | C53: Kantin 4 | I53: =D53+O53 -> 0 | K53: Canteen4 | L53: אּ | O53: 0
D54: =SUM(D47:D53) -> 82572250 | E54: =SUM(E47:E53) -> 0 | F54: =SUM(F47:F53) -> 0 | G54: 129992100 | H54: =SUM(H47:H53) -> 0 | I54: =SUM(I47:I53) -> 1332016556 | O54: 1249444306
B56: Penghasilan lain lain & keuntungan | L56: Others income & gains
B57: אּ | C57: Keuntungan pelepasan Aset tetap | D57: =RL!C183 -> 0 | G57: 0 | I57: =D57+O57 -> 0 | K57: Gains on disposal of fixed assets | L57: אּ | O57: 0
B58: אּ | C58: Keuntungan penjualan investasi | D58: =RL!C169 -> 0 | G58: 0 | I58: =D58+O58 -> 0 | K58: Loss on sale invesment | L58: אּ | O58: 0
B59: אּ | C59: Keuntungan selisih kurs | D59: =RL!C174 -> 0 | G59: 0 | I59: =D59+O59 -> 0 | K59: Gains on foreign exchange | L59: אּ | O59: 0
B60: אּ | C60: Panen Beras Sawah | D60: =RL!C188 -> 0 | G60: 0 | I60: =D60+O60 -> 0 | O60: 0
B61: אּ | C61: Penerimaan dan pembulatan lebih | D61: =RL!C187+RL!C189 -> 0 | G61: 0 | I61: =D61+O61 -> 0 | K61: Excess payment and rounded | L61: אּ | O61: 0
B62: אּ | C62: Penerimaan piutang yang dihapus | D62: =RL!C178+RL!C179 -> 0 | G62: 0 | I62: =D62+O62 -> 0 | K62: Recovery of write off of receivable | L62: אּ | O62: 0
B63: אּ | C63: Bagi hasil dari UP | D63: =RL!C191 -> 0 | G63: 0 | I63: =D63+O63 -> 0 | K63: Profit sharing from AE | O63: 0
B64: אּ | C64: Lain - lain | D64: =RL!C227 -> 0 | G64: 0 | I64: =D64+O64 -> 0 | K64: Others | L64: אּ | O64: 0
D65: =SUM(D57:D64) -> 0 | E65: =SUM(E57:E64) -> 0 | F65: =SUM(F57:F64) -> 0 | G65: 0 | H65: =SUM(H57:H64) -> 0 | I65: =SUM(I57:I64) -> 0 | O65: 0
B67: Jumlah pendapatan dan | L67: Total unrestricted revenues and
B68: keuntungan tidak terikat | D68: =D65+D54+D44+D37+D36+D25 -> 627072350 | E68: =E65+E54+E44+E36+E25 -> 0 | F68: =F65+F54+F44+F36+F25 -> 0 | G68: =G65+G54+G44+G37+G36+G25 -> 678707218 | I68: =I65+I54+I44+I36+I25 -> 9.8482333e+09 | L68: gains | O68: 9.221161e+09
D69: =D68-LR!E48 -> 0 | G69: =G68-'[6]9'!$D$68 -> 0 | I69: =I68-LR!K48 -> 0
O70: =O68-'[6]9'!$I$68 -> 0
A73: =CLK!B681 -> Catatan atas laporan keuangan merupakan bagian yang tidak terpisahkan dari laporan keuangan
A75: =IN!C4 -> Laporan Keuangan June 2026 | G75: 18 | L75: =IN!D4 -> Financial Statement Jun 2026
C77: Total Pendapatan Pesantren | D77: =D68-D54 -> 544500100
C78: Penjualan Enam Mart | D78: =D54 -> 82572250

Sheet 10
A2: PESANTREN ISLAM AL-IRSYAD TENGARAN 6 BONDOWOSO
A4: LAMPIRAN 10 / APPENDIX 10
A5: RINCIAN BEBAN DAN KERUGIAN | L5: DETAIL OF EXPENSES AND LOSS
A6: ='9'!A6 -> Untuk Bulan yang Berakhir 30 June 2026 | L6: ='9'!L6 -> For The Month Ended Jun 2026
A7: ='9'!A7 -> (Dengan perbandingan informasi keuangan untuk bulan yang berakhir 31 May 2026 / | L7: ='9'!L7 -> With Comparative financial information for the month ended May 31, 2026 )
A9: ( Disajikan dalam rupiah ) | L9: (Expressed in rupiah) | N9: Control saldo
A11: Pos pos | D11: ='9'!D11 -> 30 June 2026/ | E11: % | F11: ='9'!G11 -> 31 May 2026/ | G11: % | H11: ='9'!I11 -> sd 30 June 2026/ | I11: % | J11: Accounts | N11: ="sd "&(F11) -> sd 31 May 2026/
D12: ='9'!D12 -> 46203 | F12: ='9'!G12 -> 46173 | H12: ='9'!I12 -> 46203 | N12: =F12 -> 46173
A13: Pendidikan & umum | L13: Education and general
A14: Akademik | L14: Academic
A15: אּ | B15: Sekolah dasar / Daycare | D15: =IF(B15="","",SUM(SDITQ)) -> 0 | F15: 0 | H15: =D15+N15 -> 0 | K15: Elementary school | L15: אּ | N15: 0
A16: אּ | B16: Madrasah Tsanawiyah | D16: =IF(B16="","",SUM(MTS)) -> 7361800 | E16: =D16/D$110 -> 0.012431654 | F16: 13195900 | H16: =D16+N16 -> 93926600 | I16: =H16/H$106 -> 0.010543197 | K16: Islamic yunior high school & IL | L16: אּ | N16: 86564800
A17: אּ | B17: Madrasah Aliyah & IL | D17: =IF(B17="","",SUM(MA)) -> 6216400 | E17: =D17/D$110 -> 0.010497451 | F17: 40423900 | H17: =D17+N17 -> 192642500 | I17: =H17/H$106 -> 0.021623989 | K17: Islamic senior high school | L17: אּ | N17: 186426100
D18: =SUM(D15:D17) -> 13578200 | E18: =SUM(E15:E17) -> 0.022929105 | F18: 53619800 | H18: =SUM(H15:H17) -> 286569100 | I18: =SUM(I15:I17) -> 0.032167186 | N18: 272990900
A19: Dakwah & sosial | L19: Propaganda and social | P19: 52000 | Q19: PUBLIC SERVICE
A20: אּ | B20: Dakwah | D20: =IF(OR(B20="",A20=""),"",SUM(Dakwah)) -> 0 | F20: 76000 | H20: =D20+N20 -> 223000 | I20: =H20/H$106 -> 2.5031597e-05 | K20: Propaganda | L20: אּ | N20: 223000 | Q20: 52100 | R20: DAKWAH PROGRAMS
A21: אּ | B21: Sosial | D21: =IF(B21="","",SUM(Sosial)) -> 140000 | F21: 72197100 | H21: =D21+N21 -> 284629400 | I21: =H21/H$106 -> 0.031949456 | K21: Social | L21: אּ | N21: 284489400 | Q21: 52200 | R21: SOCIAL PROGRAM
A22: אּ | B22: Radio | D22: =IF(B22="","",SUM(Radio)) -> 0 | F22: 0 | H22: =D22+N22 -> 0 | I22: =H22/H$106 -> 0 | N22: 0 | Q22: 52300 | R22: RADIO PROGRAMS
A23: אּ | B23: Hubungan masyarakat | D23: =IF(B23="","",SUM(Humas)) -> 1250000 | F23: 15298000 | H23: =D23+N23 -> 163528500 | I23: =H23/H$106 -> 0.018355962 | K23: Radio | L23: אּ | M23: PWSB & Per. Pusat & wisuda | N23: 162278500 | Q23: 52400 | R23: PUBLIC RELATION PROGRAMS
D24: =SUM(D20:D23) -> 1390000 | F24: 87571100 | H24: =SUM(H20:H23) -> 448380900 | I24: =SUM(I20:I23) -> 0.050330449 | N24: 446990900
A25: Dukungan akademik | L25: Academic support | P25: 53000 | Q25: SUPPORT PROGRAM AND STUDENT SERVICE
A26: אּ | B26: Perpustakaan | D26: =IF(B26="","",SUM(Perpustakaan)) -> 0 | F26: 0 | H26: =D26+N26 -> 4165000 | I26: =H26/H$106 -> 0.0004675184 | K26: Library | L26: אּ | N26: 4165000 | Q26: 53100 | R26: LIBERARY
A27: אּ | B27: Audio visual | D27: =IF(B27="","",SUM(Audio)) -> 0 | F27: 0 | H27: =D27+N27 -> 0 | I27: =H27/H$106 -> 0 | K27: Audio visual | L27: אּ | N27: 0 | Q27: 53200 | R27: AUDIO VISUAL
D28: =SUM(D25:D27) -> 0 | F28: 0 | H28: =SUM(H26:H27) -> 4165000 | I28: =SUM(I26:I27) -> 0.0004675184 | N28: 4165000 | Q28: 53300 | R28: KEPENGASUHAN SDITQ
A29: Kegiatan dan layanan santri | L29: Student activity and service | Q29: 53400 | R29: KEPENGASUHAN MTW
A30: אּ | B30: Organisasi santri | D30: =IF(B30="","",SUM(Jummiyah)) -> 6265000 | F30: 2946400 | H30: =D30+N30 -> 32977000 | I30: =H30/H$106 -> 0.0037016457 | K30: Student organization | L30: אּ | N30: 26712000 | Q30: 53500 | R30: KEPENGASUHAN IM&IL
A31: אּ | B31: Dakwah | D31: =IF(B31="","",SUM(Daksan)) -> 0 | F31: 0 | H31: =D31+N31 -> 0 | I31: =H31/H$106 -> 0 | K31: Student sport | L31: אּ | N31: 0 | Q31: 53600 | R31: BIMBINGAN KONSELING
A32: אּ | B32: Olah raga santri | D32: =IF(B32="","",SUM(ORsan)) -> 0 | F32: 0 | H32: =D32+N32 -> 556900 | I32: =H32/H$106 -> 6.2511644e-05 | K32: Student propaganda | L32: אּ | N32: 556900 | Q32: 53700 | R32: KESEHATAN SANTRI
A33: אּ | B33: Kepengasuhan | H33: =D33+N33 -> 0 | I33: =H33/H$106 -> 0 | K33: Student administration | L33: אּ | N33: 0 | P33: 54000 | Q33: STUDENT ACTIVITIES
B34: ~ | C34: Kepengasuhan | D34: =IF(B34="","",SUM(KepengasuhanSDITQ)) -> 0 | F34: 0 | H34: =D34+N34 -> 0 | I34: =H34/H$106 -> 0 | N34: 0
B35: ~ | C35: Kepengasuhan | D35: =IF(B35="","",SUM(Kepengasuhanmts)) -> 0 | F35: 0 | H35: =D35+N35 -> 0 | I35: =H35/H$106 -> 0 | N35: 0
B36: ~ | C36: Kepengasuhan MTs & MA | D36: =IF(B36="","",SUM(KepengasuhanMA)) -> 2105200 | E36: =D36/D$110 -> 0.003554989 | F36: 2973500 | H36: =D36+N36 -> 168574300 | I36: =H36/H$106 -> 0.01892235 | N36: 166469100
A37: אּ | B37: Bimbingan dan konseling | D37: =IF(B37="","",SUM(Bimbangankonseling)) -> 0 | E37: =D37/D$110 -> 0 | F37: 0 | H37: =D37+N37 -> 3683100 | I37: =H37/H$106 -> 0.00041342546 | K37: Guidance and counseling | L37: אּ | N37: 3683100 | Q37: 54100 | R37: JUMIYYAH TOLABAH SDITQ
A38: אּ | B38: Kemusyrifan | E38: =D38/D$110 -> 0 | H38: =D38+N38 -> 0 | I38: =H38/H$106 -> 0 | K38: Boarding supervisory | L38: אּ | N38: 0 | Q38: 54300 | R38: JUMIYYAH TOLABAH IM/IL
A39: אּ | B39: Lomba santri | D39: =IF(B39="","",SUM(Lomba)) -> 0 | E39: =D39/D$110 -> 0 | F39: 0 | H39: =D39+N39 -> 0 | I39: =H39/H$106 -> 0 | K39: Student contest | L39: אּ | N39: 0 | Q39: 54400 | R39: DAKWAH / PROPAGANDA
A40: אּ | B40: Pendaftaran dan peneriman santri | D40: =IF(B40="","",SUM(PSB)) -> 0 | E40: =D40/D$110 -> 0 | F40: 0 | H40: =D40+N40 -> 16540500 | I40: =H40/H$106 -> 0.0018566598 | K40: Student admission and recruitment | L40: אּ | N40: 16540500 | Q40: 54600 | R40: STUDENT CONTEST
A41: אּ | B41: Kesehatan santri | D41: =IF(B41="","",SUM(Kesehatansantri)) -> 2438600 | E41: =D41/D$110 -> 0.0041179917 | F41: 1979900 | H41: =D41+N41 -> 42488447 | I41: =H41/H$106 -> 0.0047692991 | K41: Student healty | L41: אּ | N41: 40049847 | Q41: 54700 | R41: REGRISTRATION NEW STUDENT
D42: =SUM(D30:D41) -> 10808800 | E42: =SUM(E30:E41) -> 0.0076729808 | F42: 7899800 | H42: =SUM(H30:H41) -> 264820247 | I42: =SUM(I30:I41) -> 0.029725892 | N42: 254011447 | P42: 55000 | Q42: SUPPORT INSTITUTION
A43: Dukungan institusi | L43: Institutional support | Q43: 55100 | R43: EXECUTIVE MANAGEMENT
A44: אּ | B44: Manajemen eksekutif | D44: =IF(B44="","",SUM(Executive)) -> 0 | E44: =D44/D$110 -> 0 | F44: 5000000 | H44: =D44+N44 -> 18189500 | I44: =H44/H$106 -> 0.0020417589 | K44: Executive management | L44: אּ | N44: 18189500 | Q44: 55200 | R44: RESEACH AND DEVELOPMENT
A45: אּ | B45: Litbang PIA | D45: =IF(B45="","",SUM(Litbang)) -> 0 | E45: =D45/D$110 -> 0 | F45: 0 | H45: =D45+N45 -> 36811500 | I45: =H45/H$106 -> 0.0041320657 | N45: 36811500
A46: אּ | B46: Akuntansi dan keuangan | D46: =IF(B46="","",SUM(Aktkeu)) -> 3414380 | E46: =D46/D$110 -> 0.0057657626 | F46: 4713000 | H46: =D46+N46 -> 408860218 | I46: =H46/H$106 -> 0.04589428 | K46: Accounting and finance | L46: אּ | N46: 405445838 | Q46: 55300 | R46: ACCOUNTING AND FINANCE
A47: אּ | B47: Personalia | D47: =IF(B47="","",SUM(Personalia)) -> 2.847563e+08 | E47: =D47/D$110 -> 0.48085955 | F47: 2.7407414e+08 | H47: =D47+N47 -> 3.5575979e+09 | I47: =H47/H$106 -> 0.39933793 | K47: Personnel | L47: אּ | N47: 3.2728416e+09 | Q47: 55400 | R47: HUMAN RESOURCE
A48: אּ | B48: Umum & administrasi | D48: =IF(B48="","",SUM(Rumahtangga)) -> 9969350 | E48: =D48/D$110 -> 0.016834947 | F48: 10146350 | H48: =D48+N48 -> 115358570 | I48: =H48/H$106 -> 0.012948921 | K48: General and Administrartion | L48: אּ | N48: 105389220 | Q48: 55500 | R48: GENERAL AND ADMINISTRATION
A49: אּ | B49: Tehnologi informasi | D49: =IF(B49="","",SUM(InformasiTeknologi)) -> 177400 | E49: =D49/D$110 -> 0.00029957014 | F49: 0 | H49: =D49+N49 -> 8294370 | I49: =H49/H$106 -> 0.00093103736 | N49: 8116970 | Q49: 55600 | R49: INFORMATION TECHNOLOGY
D50: =SUM(D44:D49) -> 2.9831743e+08 | E50: =SUM(E44:E49) -> 0.50375983 | F50: 2.9393349e+08 | H50: =SUM(H44:H49) -> 4.1451121e+09 | I50: =SUM(I44:I49) -> 0.46528599 | N50: 3.8467946e+09 | P50: 56000 | Q50: MAINTENANCE AND OPERATIONAL PLANT
A51: Pemeliharan & operasional plant | L51: Maintenance and operational of plant | Q51: 56100 | R51: PHYSICAL TOOLS ADMINISTRATION
A52: אּ | B52: Administrasi sarana fisik | D52: =IF(B52="","",SUM(ASF)) -> 0 | F52: 0 | H52: =D52+N52 -> 0 | K52: Administration of phisical plant | L52: אּ | N52: 0 | Q52: 56200 | R52: HEALTH AND CLEANESS ENVIRONMENT
A53: אּ | B53: Kebersihan dan kesehatan | D53: =IF(B53="","",SUM(KK)) -> 5458000 | E53: =D53/D$110 -> 0.0092167633 | F53: 7659400 | H53: =D53+N53 -> 75031901 | I53: =H53/H$106 -> 0.0084222796 | K53: Cleaness and healty | L53: אּ | N53: 69573901 | Q53: 56300 | R53: BUILD MAINTENANCE
A54: אּ | B54: Pemeliharaan gedung | D54: =IF(B54="","",SUM(PemeliharaanGedung)) -> 55856500 | E54: =D54/D$110 -> 0.094323221 | F54: 40840000 | H54: =D54+N54 -> 171449537 | I54: =H54/H$106 -> 0.019245093 | K54: Building maintenance | L54: אּ | N54: 115593037 | Q54: 56400 | R54: INFRASTRUCTURE MAINTENANCE
A55: אּ | B55: Pemeliharaan infrastruktur | D55: =IF(B55="","",SUM(PemeliharaanInfrastruktur)) -> 541000 | E55: =D55/D$110 -> 0.00091357071 | F55: 6789000 | H55: =D55+N55 -> 50757357 | I55: =H55/H$106 -> 0.0056974786 | K55: Infrastructure maintenance | L55: אּ | N55: 50216357 | Q55: 56500 | R55: NON BUILDING MAINTENANCE
A56: אּ | B56: Pemeliharaan non gedung | D56: =IF(B56="","",SUM(PemeliharaanNonge)) -> 702000 | E56: =D56/D$110 -> 0.0011854467 | F56: 4228300 | H56: =D56+N56 -> 71897398 | I56: =H56/H$106 -> 0.0080704338 | K56: Non Building maintenance | L56: אּ | N56: 71195398 | Q56: 56600 | R56: UTILITIES
A57: אּ | B57: Utilitas | D57: =IF(B57="","",SUM(Utilitas)) -> 8074100 | E57: =D57/D$110 -> 0.013634494 | F57: 6989900 | H57: =D57+N57 -> 78259800 | I57: =H57/H$106 -> 0.008784609 | K57: Ulitilities | L57: אּ | N57: 70185700 | Q57: 56700 | R57: SAFETY AND SECURITIES
A58: אּ | B58: Keamanan dan keselamatan | D58: =IF(B58="","",SUM(Keamanan)) -> 0 | E58: =D58/D$110 -> 0 | F58: 200100 | H58: =D58+N58 -> 2890100 | I58: =H58/H$106 -> 0.00032441175 | K58: Security and safety | L58: אּ | N58: 2890100 | Q58: 56800 | R58: LOGISTIC
A59: אּ | B59: Logistik | D59: =IF(B59="","",SUM(Logistik)) -> 0 | F59: 0 | H59: =D59+N59 -> 0 | I59: =H59/H$106 -> 0 | K59: Logistic | L59: אּ | N59: 0 | Q59: 56900 | R59: DEPRECIATION FIXED ASSET
D60: =SUM(D52:D59) -> 70631600 | E60: =SUM(E52:E59) -> 0.1192735 | F60: 66706700 | H60: =SUM(H52:H59) -> 450286093 | I60: =SUM(I52:I59) -> 0.050544306 | N60: 379654493
A61: Bantuan keuangan santri | L61: Student financial aid | P61: 57000 | Q61: STUDENT FINANCE AID
A62: אּ | B62: Beasiswa | D62: =IF(B62="","",SUM(BeasiswaSa)) -> 0 | E62: =D62/D$110 -> 0 | F62: 0 | H62: =D62+N62 -> 0 | I62: =H62/H$106 -> 0 | K62: Scholarship | L62: אּ | N62: 0 | Q62: 57100 | R62: SCHOOLARSHIP
A63: אּ | B63: Praktek kerja lapangan | D63: =IF(B63="","",SUM(PKL)) -> 0 | E63: =D63/D$110 -> 0 | F63: 0 | H63: =D63+N63 -> 0 | I63: =H63/H$106 -> 0 | K63: Work study | L63: אּ | N63: 0 | Q63: 57200 | R63: OTHERS AID
A64: אּ | B64: Bantuan santri | D64: =IF(B64="","",SUM(AdministrasiS)) -> 61850 | E64: =D64/D$110 -> 0.00010444427 | F64: 53300 | H64: =D64+N64 -> 2996487 | I64: =H64/H$106 -> 0.00033635362 | K64: Student grants | L64: אּ | N64: 2934637 | P64: 58000 | Q64: SALES AND SERVICE
D65: =SUM(D62:D64) -> 61850 | E65: =SUM(E62:E64) -> 0.00010444427 | F65: 53300 | H65: =SUM(H62:H64) -> 2996487 | I65: =SUM(I62:I64) -> 0.00033635362 | N65: 2934637 | Q65: 58100 | R65: KARTU IDENTITAS
A66: Penjualan dan jasa | L66: Sales and services | Q66: 58200 | R66: BOOKS
A67: אּ | B67: Buku | D67: =IF(B67="","",SUM(Buku)) -> 0 | F67: 0 | H67: =D67+N67 -> 395124231 | I67: =H67/H$106 -> 0.044352425 | K67: Books | L67: אּ | N67: 395124231 | Q67: 58300 | R67: UNIFORM
A68: אּ | B68: Seragam | D68: =IF(B68="","",SUM(Seragam)) -> 0 | F68: 0 | H68: =D68+N68 -> 37726000 | I68: =H68/H$106 -> 0.0042347177 | K68: Uniform | L68: אּ | N68: 37726000 | P68: 59000 | Q68: BOARDING SERVICE
A69: אּ | B69: Lain-lain | D69: =IF(B69="","",SUM(SalesOth)) -> 0 | F69: 0 | I69: =H69/H$106 -> 0 | K69: Other sales | L69: אּ | Q69: 59100 | R69: FOODS SERVICE
D70: =SUM(D67:D69) -> 0 | E70: =SUM(E67:E68) -> 0 | F70: 0 | H70: =SUM(H67:H69) -> 432850231 | I70: =SUM(I67:I69) -> 0.048587142 | N70: 432850231 | Q70: 59200 | R70: LAUNDRY SERVICE
A71: Layanan asrama | L71: Boarding services | Q71: 59300 | R71: ROOM SERVICE
A72: אּ | B72: Makanan & minuman | D72: =IF(B72="","",SUM(Layananmakanan)) -> 100351243 | E72: =D72/D$110 -> 0.16946018 | F72: 222835178 | H72: =D72+N72 -> 1724236028 | I72: =H72/H$106 -> 0.19354432 | K72: Food and baverages | L72: אּ | N72: 1623884785 | O72: =D72-F72 -> -122483935
A73: אּ | B73: Cucian | D73: =IF(B73="","",SUM(layananlaundry)) -> 0 | E73: =D73/D$110 -> 0 | F73: 0 | H73: =D73+N73 -> 0 | I73: =H73/H$106 -> 0 | K73: Laundry | L73: אּ | N73: 0
A74: אּ | B74: Kamar (Layanan Tamu) | D74: =IF(B74="","",SUM(Layanankamar)) -> 5222000 | E74: =D74/D$110 -> 0.0088182371 | F74: 3822600 | H74: =D74+N74 -> 38130794 | I74: =H74/H$106 -> 0.0042801556 | K74: Room | L74: אּ | N74: 32908794
D75: =SUM(D72:D74) -> 105573243 | E75: =SUM(E72:E74) -> 0.17827842 | F75: 226657778 | H75: =SUM(H72:H74) -> 1762366822 | I75: =SUM(I72:I74) -> 0.19782447 | N75: 1656793579
D77: =D75+D70+D65+D60+D50+D42+D28+D24+D18 -> 5.0036112e+08 | E77: =E75+E70+E65+E60+E50+E42+E28+E24+E18 -> 0.83201827 | F77: 7.3644197e+08 | H77: =H75+H70+H65+H60+H50+H42+H28+H24+H18 -> 7.7975469e+09 | I77: =I75+I70+I65+I60+I50+I42+I28+I24+I18 -> 0.87526931 | N77: 7.2971858e+09
A78: Penyusutan | L78: Depreciation
A79: אּ | B79: Gedung | D79: =IF(B79="","",SUM(DepB)) -> 51343185 | E79: =D79/D$110 -> 0.086701718 | F79: 51343185 | H79: =D79+N79 -> 5.8459271e+08 | I79: =H79/H$106 -> 0.065620132 | K79: Building | L79: אּ | N79: 5.3324952e+08
A80: אּ | B80: Infrastruktur | D80: =IF(B80="","",SUM(DepInf)) -> 6247598.4 | E80: =D80/D$110 -> 0.010550135 | F80: 6247589.9 | H80: =D80+N80 -> 74919275 | I80: =H80/H$106 -> 0.0084096374 | K80: Infrastructure | L80: אּ | N80: 68671677
A81: אּ | B81: Peralatan | D81: =IF(B81="","",SUM(DepEq)) -> 12982655 | E81: =D81/D$110 -> 0.021923427 | F81: 13006306 | H81: =D81+N81 -> 1.4958605e+08 | I81: =H81/H$106 -> 0.016790932 | K81: Equipment | L81: אּ | N81: 1.366034e+08
A82: אּ | B82: Mebelair | D82: =IF(B82="","",SUM(DepFu)) -> 18917086 | E82: =D82/D$110 -> 0.031944724 | F82: 20509900 | H82: =D82+N82 -> 2.7516401e+08 | I82: =H82/H$106 -> 0.030886972 | K82: Furniture | L82: אּ | N82: 2.5624693e+08
A83: אּ | B83: Kendaraan | D83: =IF(B83="","",SUM(Depv)) -> 2330208.3 | E83: =D83/D$110 -> 0.0039349539 | F83: 2330208.3 | H83: =D83+N83 -> 26931249 | I83: =H83/H$106 -> 0.0030230143 | K83: Vehicle | L83: אּ | N83: 24601041
A84: אּ | B84: Buku dan material perpustakaan | D84: =IF(B84="","",SUM(DepLi)) -> 0 | F84: 0 | H84: =D84+N84 -> 0 | K84: Library book and material | L84: אּ | N84: 0
A85: אּ | B85: Lain lain aset tetap | D85: =IF(B85="","",SUM(Depoth)) -> 0 | F85: 0 | H85: =D85+N85 -> 0 | K85: Other fixed assets | L85: אּ | N85: 0
D86: =SUM(D79:D85) -> 91820733 | E86: =SUM(E79:E85) -> 0.15505496 | F86: 93437189 | H86: =SUM(H79:H85) -> 1.1111933e+09 | I86: =SUM(I79:I85) -> 0.12473069 | N86: 1.0193726e+09
A87: Usaha pelengkap | L87: Auxiliary enterprises
A88: אּ | B88: Kantin 6 Mart | D88: ='13'!E22+'13'!E49 -> 77692362 | F88: 1.238335e+08 | H88: =D88+N88 -> 1.2151222e+09 | K88: Auxiliary enterprises office | L88: אּ | N88: 1.1374299e+09
A89: אּ | B89: Pembiayaan | H89: =D89+N89 -> 0 | K89: Financing | L89: אּ | N89: 0
A90: אּ | B90: Wartel | H90: =D90+N90 -> 0 | K90: Telpon cabin | L90: אּ | N90: 0
A91: אּ | B91: Kanten | H91: =D91+N91 -> 0 | K91: Canteen | L91: אּ | N91: 0
A92: אּ | B92: Toko | H92: =D92+N92 -> 0 | K92: Foto copy | L92: אּ | N92: 0
D93: =SUM(D88:D92) -> 77692362 | E93: =SUM(E88:E92) -> 0 | F93: 1.238335e+08 | H93: =SUM(H88:H92) -> 1.2151222e+09 | N93: 1.1374299e+09
A94: Beban lain lain & kerugian | L94: Other expenses and losses
A95: אּ | B95: Pelepasan Aset tetap | H95: =D95+N95 -> 0 | K95: Disposal fixed assets | L95: אּ | N95: 0
A96: אּ | B96: Kerugian investasi | H96: =D96+N96 -> 0 | K96: Invesment loss | L96: אּ | N96: 0
A97: אּ | B97: Selisih kurang | H97: =D97+N97 -> 0 | K97: Shortage | L97: אּ | N97: 0
A98: אּ | B98: Pajak bunga bank | H98: =D98+N98 -> 0 | K98: Bank interest tax | L98: אּ | N98: 0
A99: אּ | B99: Pembayaran dan pembulatan kurang | H99: =D99+N99 -> 0 | K99: Less payment and rounded | L99: אּ | N99: 0
A100: אּ | B100: Penghaspusan piutang & persediaan | H100: =D100+N100 -> 0 | K100: Write off of receivable | L100: אּ | N100: 0
D101: =SUM(D95:D100) -> 0 | E101: =SUM(E95:E100) -> 0 | F101: 0 | H101: =SUM(H95:H100) -> 0 | N101: 0
A103: Jumlah beban dan kerugian | D103: =D101+D93+D86+D77 -> 6.6987422e+08 | E103: =E101+E93+E86+E77 -> 0.98707323 | F103: =F101+F93+F86+F77 -> 9.5371266e+08 | G103: =G101+G93+G86+G77 -> 0 | H103: =H101+H93+H86+H77 -> 1.0123862e+10 | I103: =I101+I93+I86+I77 -> 1 | L103: Total expenses and loss | N103: 9.4539883e+09
D104: =D103-LR!E75 -> 0 | F104: =F103-'[6]10'!$D$103 -> 0 | H104: =H103-LR!K75 -> 0
D105: 1.2751435e+09 | N105: =N103-'[6]10'!$H$103 -> 0
H106: =H103-H88 -> 8.9087402e+09
...

Sheet 11
A2: =[19]NRC!B2 -> PESANTREN ISLAM AL-IRSYAD, TENGARAN
A4: LAMPIRAN 11 / APPENDIX 11
A5: RINCIAN BEBAN DAN KERUGIAN MENURUT KLASIFIKASI SIFAT DENGAN FUNGSIONAL | Z5: DETAIL OF EXPENSES AND LOSSES BY NATURAL CLASSIFICATION WITH FUNCTIONAL CLASSIFICATION
A6: =LR!C6 -> Untuk Bulan yang Berakhir 30 June 2026 | Z6: =LR!I6 -> For The Month Ended Jun 2026
A7: =LR!C7 -> (Dengan perbandingan informasi keuangan untuk bulan yang berakhir 31 May 2026 / | Z7: =LR!O7 -> With Comparative financial information for the month ended May 31, 2026 )
A8: =[18]RL!C8 -> yang berakhir 30 June 2023 )
A9: ( Disajikan dalam rupiah )
F11: 1 | G11: 2 | H11: 3 | I11: 4 | J11: 5 | K11: 6 | L11: 7 | M11: 8 | N11: 9 | O11: 10 | P11: 11 | Q11: 12 | AC11: Control saldo
A12: Pos pos | D12: =#REF! -> #REF! | E12: s/d bulan ini | F12: =[18]IN!H23 -> #N/A | T12: =[18]IN!$G$26 -> 30 June 2023 / | V12: =[18]IN!$C$37 -> s/d 31 July 2023 / | X12: Accounts
D13: =#REF! -> #REF! | E13: s/d bulan ini | F13: Akademik / | G13: Dakwah | H13: Dukungan | I13: Kegiatan dan | J13: Dukungan | K13: Pemeliharaan | L13: Bantuan | M13: Penjualan dan | N13: Layanan | O13: Penyusutan / | P13: Usaha | Q13: Beban lain - lain | R13: Jumlah / | V13: ='10'!H11 -> sd 30 June 2026/
F14: Academic | G14: dan sosial / | H14: akademik / | I14: layanan santri / | J14: institusi / | K14: dan operasional | L14: keuangan | M14: jasa / | N14: asrama / | O14: Depreciation | P14: pelengkap / | Q14: dan kerugian / | R14: Total
G15: Propaganda | H15: Academic | I15: Student activities | J15: Institutional | K15: plant / | L15: santri / | M15: Sales and | N15: Boarding | P15: Auxiliary | Q15: Other expenses | R15: =IN!C5 -> 30 June 2026 | T15: ='10'!F11 -> 31 May 2026/
G16: and social | H16: support | I16: and service | J16: support | K16: Maintenance and | L16: Student | M16: service | N16: service | P16: enterprises | Q16: and loss | T16: ='10'!F12 -> 46173 | V16: =R17 -> 46203
K17: operational | L17: financial aid | R17: =IN!D5 -> 46203 | AC17: ="sd "&(T15) -> sd 31 May 2026/
K18: of plant | AC18: =T16 -> 46173
A19: Gaji | D19: 77125591 | E19: 1.9317774e+08 | S19: 100 | U19: 100 | W19: 100 | Z19: Salaries | AA19: 1SL
A20: Karyawan tetap | F20: =IF($AA20="","",SUMIF(Bakademik1,AA20,Bakademik2)) -> 0 | G20: =IF($AA20="","",SUMIF(BDaksos1,AA20,BDaksos2)) -> 0 | H20: =IF($AA20="","",SUMIF(BDukunganAka1,AA20,BDukunganAka2)) -> 0 | I20: =IF($AA20="","",SUMIF(BKegiatanSantri1,AA20,BKegiatanSantri2)) -> 0 | J20: =IF($AA20="","",SUMIF(DukunganInstitusi1,AA20,DukunganInstitusi2)) -> 246488430 | K20: =IF($AA20="","",SUMIF(BPemeliharaan1,AA20,BPemeliharaan2)) -> 0 | L20: =IF($AA20="","",SUMIF(BBantuan1,AA20,BBantuan2)) -> 0 | M20: =IF($AA20="","",SUMIF(BPenjualan1,AA20,BPenjualan2)) -> 0 | N20: =IF($AA20="","",SUMIF(BLayananAsrama1,AA20,BlayananAsrama2)) -> 0 | R20: =SUM(F20:Q20) -> 246488430 | T20: 2.3665195e+08 | V20: =R20+AC20 -> 2.8697528e+09 | Z20: Permanent employee | AA20: SL1 | AC20: 2.6232644e+09
A21: Karyawan tidak tetap | F21: =IF($AA21="","",SUMIF(Bakademik1,AA21,Bakademik2)) -> 0 | G21: =IF($AA21="","",SUMIF(BDaksos1,AA21,BDaksos2)) -> 0 | H21: =IF($AA21="","",SUMIF(BDukunganAka1,AA21,BDukunganAka2)) -> 0 | I21: =IF($AA21="","",SUMIF(BKegiatanSantri1,AA21,BKegiatanSantri2)) -> 0 | J21: =IF($AA21="","",SUMIF(DukunganInstitusi1,AA21,DukunganInstitusi2)) -> 0 | K21: =IF($AA21="","",SUMIF(BPemeliharaan1,AA21,BPemeliharaan2)) -> 0 | L21: =IF($AA21="","",SUMIF(BBantuan1,AA21,BBantuan2)) -> 0 | M21: =IF($AA21="","",SUMIF(BPenjualan1,AA21,BPenjualan2)) -> 0 | N21: =IF($AA21="","",SUMIF(BLayananAsrama1,AA21,BlayananAsrama2)) -> 0 | R21: =SUM(F21:Q21) -> 0 | T21: 1460000 | V21: =R21+AC21 -> 7805000 | Z21: Non permanent employee | AA21: SL2 | AC21: 7805000
A22: Karyawan Percobaan | F22: =IF($AA22="","",SUMIF(Bakademik1,AA22,Bakademik2)) -> 0 | G22: =IF($AA22="","",SUMIF(BDaksos1,AA22,BDaksos2)) -> 0 | H22: =IF($AA22="","",SUMIF(BDukunganAka1,AA22,BDukunganAka2)) -> 0 | I22: =IF($AA22="","",SUMIF(BKegiatanSantri1,AA22,BKegiatanSantri2)) -> 0 | J22: =IF($AA22="","",SUMIF(DukunganInstitusi1,AA22,DukunganInstitusi2)) -> 0 | K22: =IF($AA22="","",SUMIF(BPemeliharaan1,AA22,BPemeliharaan2)) -> 0 | L22: =IF($AA22="","",SUMIF(BBantuan1,AA22,BBantuan2)) -> 0 | M22: =IF($AA22="","",SUMIF(BPenjualan1,AA22,BPenjualan2)) -> 0 | N22: =IF($AA22="","",SUMIF(BLayananAsrama1,AA22,BlayananAsrama2)) -> 0 | R22: =SUM(F22:Q22) -> 0 | T22: 0 | V22: =R22+AC22 -> 0 | Z22: Trainee employee | AA22: SL3 | AC22: 0
A23: Lembur | F23: =IF($AA23="","",SUMIF(Bakademik1,AA23,Bakademik2)) -> 0 | G23: =IF($AA23="","",SUMIF(BDaksos1,AA23,BDaksos2)) -> 0 | H23: =IF($AA23="","",SUMIF(BDukunganAka1,AA23,BDukunganAka2)) -> 0 | I23: =IF($AA23="","",SUMIF(BKegiatanSantri1,AA23,BKegiatanSantri2)) -> 0 | J23: =IF($AA23="","",SUMIF(DukunganInstitusi1,AA23,DukunganInstitusi2)) -> 0 | K23: =IF($AA23="","",SUMIF(BPemeliharaan1,AA23,BPemeliharaan2)) -> 0 | L23: =IF($AA23="","",SUMIF(BBantuan1,AA23,BBantuan2)) -> 0 | M23: =IF($AA23="","",SUMIF(BPenjualan1,AA23,BPenjualan2)) -> 0 | N23: =IF($AA23="","",SUMIF(BLayananAsrama1,AA23,BlayananAsrama2)) -> 0 | R23: =SUM(F23:Q23) -> 0 | T23: 1815000 | V23: =R23+AC23 -> 12259830 | Z23: Overtime | AA23: SL4 | AC23: 12259830
F24: =SUM(F20:F23) -> 0 | G24: =SUM(G20:G23) -> 0 | H24: =SUM(H20:H23) -> 0 | I24: =SUM(I20:I23) -> 0 | J24: =SUM(J20:J23) -> 246488430 | K24: =SUM(K20:K23) -> 0 | L24: =SUM(L20:L23) -> 0 | M24: =SUM(M20:M23) -> 0 | ... R24: =SUM(R20:R23) -> 246488430 | T24: 2.3992695e+08 | U24: =SUM(U20:U23) -> 0 | V24: =SUM(V20:V23) -> 2.8898176e+09 | AA24: SL | AC24: 2.6433292e+09
A25: Tunjangan | Z25: Allowance
A26: Beras (Makan Libur Santri Asatidz) | F26: =IF($AA26="","",SUMIF(Bakademik1,AA26,Bakademik2)) -> 0 | G26: =IF($AA26="","",SUMIF(BDaksos1,AA26,BDaksos2)) -> 0 | H26: =IF($AA26="","",SUMIF(BDukunganAka1,AA26,BDukunganAka2)) -> 0 | I26: =IF($AA26="","",SUMIF(BKegiatanSantri1,AA26,BKegiatanSantri2)) -> 0 | J26: =IF($AA26="","",SUMIF(DukunganInstitusi1,AA26,DukunganInstitusi2)) -> 1720000 | K26: =IF($AA26="","",SUMIF(BPemeliharaan1,AA26,BPemeliharaan2)) -> 0 | L26: =IF($AA26="","",SUMIF(BBantuan1,AA26,BBantuan2)) -> 0 | M26: =IF($AA26="","",SUMIF(BPenjualan1,AA26,BPenjualan2)) -> 0 | N26: =IF($AA26="","",SUMIF(BLayananAsrama1,AA26,BlayananAsrama2)) -> 0 | R26: =SUM(F26:Q26) -> 1720000 | T26: 0 | V26: =R26+AC26 -> 12170000 | Z26: Hulled rice | AA26: AL1 | AC26: 10450000
A27: Reward Pegawai | F27: =IF($AA27="","",SUMIF(Bakademik1,AA27,Bakademik2)) -> 0 | G27: =IF($AA27="","",SUMIF(BDaksos1,AA27,BDaksos2)) -> 0 | H27: =IF($AA27="","",SUMIF(BDukunganAka1,AA27,BDukunganAka2)) -> 0 | I27: =IF($AA27="","",SUMIF(BKegiatanSantri1,AA27,BKegiatanSantri2)) -> 0 | J27: =IF($AA27="","",SUMIF(DukunganInstitusi1,AA27,DukunganInstitusi2)) -> 0 | K27: =IF($AA27="","",SUMIF(BPemeliharaan1,AA27,BPemeliharaan2)) -> 0 | L27: =IF($AA27="","",SUMIF(BBantuan1,AA27,BBantuan2)) -> 0 | M27: =IF($AA27="","",SUMIF(BPenjualan1,AA27,BPenjualan2)) -> 0 | N27: =IF($AA27="","",SUMIF(BLayananAsrama1,AA27,BlayananAsrama2)) -> 0 | R27: =SUM(F27:Q27) -> 0 | T27: 0 | V27: =R27+AC27 -> 8633798 | Z27: Medicine dan eyes glass | AA27: AL2 | AC27: 8633798
A28: BPJS Ketenagakerjaan | F28: =IF($AA28="","",SUMIF(Bakademik1,AA28,Bakademik2)) -> 0 | G28: =IF($AA28="","",SUMIF(BDaksos1,AA28,BDaksos2)) -> 0 | H28: =IF($AA28="","",SUMIF(BDukunganAka1,AA28,BDukunganAka2)) -> 0 | I28: =IF($AA28="","",SUMIF(BKegiatanSantri1,AA28,BKegiatanSantri2)) -> 0 | J28: =IF($AA28="","",SUMIF(DukunganInstitusi1,AA28,DukunganInstitusi2)) -> 8203104 | K28: =IF($AA28="","",SUMIF(BPemeliharaan1,AA28,BPemeliharaan2)) -> 0 | L28: =IF($AA28="","",SUMIF(BBantuan1,AA28,BBantuan2)) -> 0 | M28: =IF($AA28="","",SUMIF(BPenjualan1,AA28,BPenjualan2)) -> 0 | N28: =IF($AA28="","",SUMIF(BLayananAsrama1,AA28,BlayananAsrama2)) -> 0 | R28: =SUM(F28:Q28) -> 8203104 | T28: 8935524 | V28: =R28+AC28 -> 90673593 | Z28: Doctor | AA28: AL3 | AC28: 82470489
A29: BPJS Kesehatan | F29: =IF($AA29="","",SUMIF(Bakademik1,AA29,Bakademik2)) -> 0 | G29: =IF($AA29="","",SUMIF(BDaksos1,AA29,BDaksos2)) -> 0 | H29: =IF($AA29="","",SUMIF(BDukunganAka1,AA29,BDukunganAka2)) -> 0 | I29: =IF($AA29="","",SUMIF(BKegiatanSantri1,AA29,BKegiatanSantri2)) -> 0 | J29: =IF($AA29="","",SUMIF(DukunganInstitusi1,AA29,DukunganInstitusi2)) -> 12318000 | K29: =IF($AA29="","",SUMIF(BPemeliharaan1,AA29,BPemeliharaan2)) -> 0 | L29: =IF($AA29="","",SUMIF(BBantuan1,AA29,BBantuan2)) -> 0 | M29: =IF($AA29="","",SUMIF(BPenjualan1,AA29,BPenjualan2)) -> 0 | N29: =IF($AA29="","",SUMIF(BLayananAsrama1,AA29,BlayananAsrama2)) -> 0 | R29: =SUM(F29:Q29) -> 12318000 | T29: 12318000 | V29: =R29+AC29 -> 149678766 | Z29: Operation and hospitalization | AA29: AL4 | AC29: 137360766
A30: Musibah & kematian | F30: =IF($AA30="","",SUMIF(Bakademik1,AA30,Bakademik2)) -> 0 | G30: =IF($AA30="","",SUMIF(BDaksos1,AA30,BDaksos2)) -> 0 | H30: =IF($AA30="","",SUMIF(BDukunganAka1,AA30,BDukunganAka2)) -> 0 | I30: =IF($AA30="","",SUMIF(BKegiatanSantri1,AA30,BKegiatanSantri2)) -> 0 | J30: =IF($AA30="","",SUMIF(DukunganInstitusi1,AA30,DukunganInstitusi2)) -> 0 | K30: =IF($AA30="","",SUMIF(BPemeliharaan1,AA30,BPemeliharaan2)) -> 0 | L30: =IF($AA30="","",SUMIF(BBantuan1,AA30,BBantuan2)) -> 0 | M30: =IF($AA30="","",SUMIF(BPenjualan1,AA30,BPenjualan2)) -> 0 | N30: =IF($AA30="","",SUMIF(BLayananAsrama1,AA30,BlayananAsrama2)) -> 0 | R30: =SUM(F30:Q30) -> 0 | T30: 0 | V30: =R30+AC30 -> 608800 | Z30: Disaster and die | AA30: AL5 | AC30: 608800
A31: Hari raya | F31: =IF($AA31="","",SUMIF(Bakademik1,AA31,Bakademik2)) -> 0 | G31: =IF($AA31="","",SUMIF(BDaksos1,AA31,BDaksos2)) -> 0 | H31: =IF($AA31="","",SUMIF(BDukunganAka1,AA31,BDukunganAka2)) -> 0 | I31: =IF($AA31="","",SUMIF(BKegiatanSantri1,AA31,BKegiatanSantri2)) -> 0 | J31: =IF($AA31="","",SUMIF(DukunganInstitusi1,AA31,DukunganInstitusi2)) -> 0 | K31: =IF($AA31="","",SUMIF(BPemeliharaan1,AA31,BPemeliharaan2)) -> 0 | L31: =IF($AA31="","",SUMIF(BBantuan1,AA31,BBantuan2)) -> 0 | M31: =IF($AA31="","",SUMIF(BPenjualan1,AA31,BPenjualan2)) -> 0 | N31: =IF($AA31="","",SUMIF(BLayananAsrama1,AA31,BlayananAsrama2)) -> 0 | R31: =SUM(F31:Q31) -> 0 | T31: 0 | V31: =R31+AC31 -> 221329918 | Z31: Feast | AA31: AL6 | AC31: 221329918
A32: Kelahiran | F32: =IF($AA32="","",SUMIF(Bakademik1,AA32,Bakademik2)) -> 0 | G32: =IF($AA32="","",SUMIF(BDaksos1,AA32,BDaksos2)) -> 0 | H32: =IF($AA32="","",SUMIF(BDukunganAka1,AA32,BDukunganAka2)) -> 0 | I32: =IF($AA32="","",SUMIF(BKegiatanSantri1,AA32,BKegiatanSantri2)) -> 0 | J32: =IF($AA32="","",SUMIF(DukunganInstitusi1,AA32,DukunganInstitusi2)) -> 0 | K32: =IF($AA32="","",SUMIF(BPemeliharaan1,AA32,BPemeliharaan2)) -> 0 | L32: =IF($AA32="","",SUMIF(BBantuan1,AA32,BBantuan2)) -> 0 | M32: =IF($AA32="","",SUMIF(BPenjualan1,AA32,BPenjualan2)) -> 0 | N32: =IF($AA32="","",SUMIF(BLayananAsrama1,AA32,BlayananAsrama2)) -> 0 | R32: =SUM(F32:Q32) -> 0 | T32: 0 | V32: =R32+AC32 -> 4500000 | Z32: Birth | AA32: AL7 | AC32: 4500000
A33: Pernikahan | F33: =IF($AA33="","",SUMIF(Bakademik1,AA33,Bakademik2)) -> 0 | G33: =IF($AA33="","",SUMIF(BDaksos1,AA33,BDaksos2)) -> 0 | H33: =IF($AA33="","",SUMIF(BDukunganAka1,AA33,BDukunganAka2)) -> 0 | I33: =IF($AA33="","",SUMIF(BKegiatanSantri1,AA33,BKegiatanSantri2)) -> 0 | J33: =IF($AA33="","",SUMIF(DukunganInstitusi1,AA33,DukunganInstitusi2)) -> 500000 | K33: =IF($AA33="","",SUMIF(BPemeliharaan1,AA33,BPemeliharaan2)) -> 0 | L33: =IF($AA33="","",SUMIF(BBantuan1,AA33,BBantuan2)) -> 0 | M33: =IF($AA33="","",SUMIF(BPenjualan1,AA33,BPenjualan2)) -> 0 | N33: =IF($AA33="","",SUMIF(BLayananAsrama1,AA33,BlayananAsrama2)) -> 0 | R33: =SUM(F33:Q33) -> 500000 | T33: 0 | V33: =R33+AC33 -> 6380800 | Z33: Married | AA33: AL8 | AC33: 5880800
A34: Sewa rumah & lain lain | F34: =IF($AA34="","",SUMIF(Bakademik1,AA34,Bakademik2)) -> 0 | G34: =IF($AA34="","",SUMIF(BDaksos1,AA34,BDaksos2)) -> 0 | H34: =IF($AA34="","",SUMIF(BDukunganAka1,AA34,BDukunganAka2)) -> 0 | I34: =IF($AA34="","",SUMIF(BKegiatanSantri1,AA34,BKegiatanSantri2)) -> 0 | J34: =IF($AA34="","",SUMIF(DukunganInstitusi1,AA34,DukunganInstitusi2)) -> 2493666.7 | K34: =IF($AA34="","",SUMIF(BPemeliharaan1,AA34,BPemeliharaan2)) -> 0 | L34: =IF($AA34="","",SUMIF(BBantuan1,AA34,BBantuan2)) -> 0 | M34: =IF($AA34="","",SUMIF(BPenjualan1,AA34,BPenjualan2)) -> 0 | N34: =IF($AA34="","",SUMIF(BLayananAsrama1,AA34,BlayananAsrama2)) -> 0 | R34: =SUM(F34:Q34) -> 2493666.7 | T34: 5973666.7 | V34: =R34+AC34 -> 32961001 | Z34: House rent and others | AA34: AL9 | AC34: 30467335
F35: =SUM(F26:F34) -> 0 | G35: =SUM(G26:G34) -> 0 | H35: =SUM(H26:H34) -> 0 | I35: =SUM(I26:I34) -> 0 | J35: =SUM(J26:J34) -> 25234771 | K35: =SUM(K26:K34) -> 0 | L35: =SUM(L26:L34) -> 0 | M35: =SUM(M26:M34) -> 0 | ... S35: =SUM(S26:S34) -> 0 | T35: 27227191 | U35: =SUM(U26:U34) -> 0 | V35: =SUM(V26:V34) -> 5.2693668e+08 | AA35: AL | AC35: 5.0170191e+08
A36: Keperluan kantor | Z36: Office supplies
A37: Alat tulis kantor | F37: =IF($AA37="","",SUMIF(Bakademik1,AA37,Bakademik2)) -> 37500 | G37: =IF($AA37="","",SUMIF(BDaksos1,AA37,BDaksos2)) -> 40000 | H37: =IF($AA37="","",SUMIF(BDukunganAka1,AA37,BDukunganAka2)) -> 0 | I37: =IF($AA37="","",SUMIF(BKegiatanSantri1,AA37,BKegiatanSantri2)) -> 181500 | J37: =IF($AA37="","",SUMIF(DukunganInstitusi1,AA37,DukunganInstitusi2)) -> 314500 | K37: =IF($AA37="","",SUMIF(BPemeliharaan1,AA37,BPemeliharaan2)) -> 0 | L37: =IF($AA37="","",SUMIF(BBantuan1,AA37,BBantuan2)) -> 0 | M37: =IF($AA37="","",SUMIF(BPenjualan1,AA37,BPenjualan2)) -> 0 | N37: =IF($AA37="","",SUMIF(BLayananAsrama1,AA37,BlayananAsrama2)) -> 0 | R37: =SUM(F37:Q37) -> 573500 | T37: 3868600 | V37: =R37+AC37 -> 98794010 | Z37: Stationaries | AA37: OS1 | AC37: 98220510
A38: Fotocopy & percetakan | F38: =IF($AA38="","",SUMIF(Bakademik1,AA38,Bakademik2)) -> 4585200 | G38: =IF($AA38="","",SUMIF(BDaksos1,AA38,BDaksos2)) -> 0 | H38: =IF($AA38="","",SUMIF(BDukunganAka1,AA38,BDukunganAka2)) -> 0 | I38: =IF($AA38="","",SUMIF(BKegiatanSantri1,AA38,BKegiatanSantri2)) -> 380200 | J38: =IF($AA38="","",SUMIF(DukunganInstitusi1,AA38,DukunganInstitusi2)) -> 1463500 | K38: =IF($AA38="","",SUMIF(BPemeliharaan1,AA38,BPemeliharaan2)) -> 0 | L38: =IF($AA38="","",SUMIF(BBantuan1,AA38,BBantuan2)) -> 0 | M38: =IF($AA38="","",SUMIF(BPenjualan1,AA38,BPenjualan2)) -> 0 | N38: =IF($AA38="","",SUMIF(BLayananAsrama1,AA38,BlayananAsrama2)) -> 0 | R38: =SUM(F38:Q38) -> 6428900 | T38: 7898800 | V38: =R38+AC38 -> 55274100 | Z38: Foto copy and printing | AA38: OS2 | AC38: 48845200
A39: Konsumsi | F39: =IF($AA39="","",SUMIF(Bakademik1,AA39,Bakademik2)) -> 829500 | G39: =IF($AA39="","",SUMIF(BDaksos1,AA39,BDaksos2)) -> 100000 | H39: =IF($AA39="","",SUMIF(BDukunganAka1,AA39,BDukunganAka2)) -> 0 | I39: =IF($AA39="","",SUMIF(BKegiatanSantri1,AA39,BKegiatanSantri2)) -> 2398500 | J39: =IF($AA39="","",SUMIF(DukunganInstitusi1,AA39,DukunganInstitusi2)) -> 5005000 | K39: =IF($AA39="","",SUMIF(BPemeliharaan1,AA39,BPemeliharaan2)) -> 0 | L39: =IF($AA39="","",SUMIF(BBantuan1,AA39,BBantuan2)) -> 0 | M39: =IF($AA39="","",SUMIF(BPenjualan1,AA39,BPenjualan2)) -> 0 | N39: =IF($AA39="","",SUMIF(BLayananAsrama1,AA39,BlayananAsrama2)) -> 3682000 | R39: =SUM(F39:Q39) -> 12015000 | T39: 16688800 | V39: =R39+AC39 -> 163360444 | Z39: Consumption | AA39: OS3 | AC39: 151345444
A40: Administrasi bank | F40: =IF($AA40="","",SUMIF(Bakademik1,AA40,Bakademik2)) -> 0 | G40: =IF($AA40="","",SUMIF(BDaksos1,AA40,BDaksos2)) -> 0 | H40: =IF($AA40="","",SUMIF(BDukunganAka1,AA40,BDukunganAka2)) -> 0 | I40: =IF($AA40="","",SUMIF(BKegiatanSantri1,AA40,BKegiatanSantri2)) -> 0 | J40: =IF($AA40="","",SUMIF(DukunganInstitusi1,AA40,DukunganInstitusi2)) -> 2319880 | K40: =IF($AA40="","",SUMIF(BPemeliharaan1,AA40,BPemeliharaan2)) -> 0 | L40: =IF($AA40="","",SUMIF(BBantuan1,AA40,BBantuan2)) -> 0 | M40: =IF($AA40="","",SUMIF(BPenjualan1,AA40,BPenjualan2)) -> 0 | N40: =IF($AA40="","",SUMIF(BLayananAsrama1,AA40,BlayananAsrama2)) -> 0 | R40: =SUM(F40:Q40) -> 2319880 | T40: 2262000 | V40: =R40+AC40 -> 20147331 | Z40: Bank administration | AA40: OS4 | AC40: 17827451
A41: Lain - lain | F41: =IF($AA41="","",SUMIF(Bakademik1,AA41,Bakademik2)) -> 0 | G41: =IF($AA41="","",SUMIF(BDaksos1,AA41,BDaksos2)) -> 0 | H41: =IF($AA41="","",SUMIF(BDukunganAka1,AA41,BDukunganAka2)) -> 0 | I41: =IF($AA41="","",SUMIF(BKegiatanSantri1,AA41,BKegiatanSantri2)) -> 460500 | J41: =IF($AA41="","",SUMIF(DukunganInstitusi1,AA41,DukunganInstitusi2)) -> 2129700 | K41: =IF($AA41="","",SUMIF(BPemeliharaan1,AA41,BPemeliharaan2)) -> 0 | L41: =IF($AA41="","",SUMIF(BBantuan1,AA41,BBantuan2)) -> 0 | M41: =IF($AA41="","",SUMIF(BPenjualan1,AA41,BPenjualan2)) -> 0 | N41: =IF($AA41="","",SUMIF(BLayananAsrama1,AA41,BlayananAsrama2)) -> 1540000 | R41: =SUM(F41:Q41) -> 4130200 | T41: 6471500 | V41: =R41+AC41 -> 99292760 | Z41: Others | AA41: OS5 | AC41: 95162560
F42: =SUM(F37:F41) -> 5452200 | G42: =SUM(G37:G41) -> 140000 | H42: =SUM(H37:H41) -> 0 | I42: =SUM(I37:I41) -> 3420700 | J42: =SUM(J37:J41) -> 11232580 | K42: =SUM(K37:K41) -> 0 | L42: =SUM(L37:L41) -> 0 | M42: =SUM(M37:M41) -> 0 | ... S42: =SUM(S37:S41) -> 0 | T42: 37189700 | U42: =SUM(U37:U41) -> 0 | V42: =SUM(V37:V41) -> 436868645 | AA42: OS | AC42: 411401165
A43: Media pembelajaran | Z43: Learning media
A44: Bahan praktikum | F44: =IF($AA44="","",SUMIF(Bakademik1,AA44,Bakademik2)) -> 0 | G44: =IF($AA44="","",SUMIF(BDaksos1,AA44,BDaksos2)) -> 0 | H44: =IF($AA44="","",SUMIF(BDukunganAka1,AA44,BDukunganAka2)) -> 0 | I44: =IF($AA44="","",SUMIF(BKegiatanSantri1,AA44,BKegiatanSantri2)) -> 0 | J44: =IF($AA44="","",SUMIF(DukunganInstitusi1,AA44,DukunganInstitusi2)) -> 0 | K44: =IF($AA44="","",SUMIF(BPemeliharaan1,AA44,BPemeliharaan2)) -> 0 | L44: =IF($AA44="","",SUMIF(BBantuan1,AA44,BBantuan2)) -> 0 | M44: =IF($AA44="","",SUMIF(BPenjualan1,AA44,BPenjualan2)) -> 0 | N44: =IF($AA44="","",SUMIF(BLayananAsrama1,AA44,BlayananAsrama2)) -> 0 | R44: =SUM(F44:Q44) -> 0 | T44: 0 | V44: =R44+AC44 -> 0 | Z44: Practical work material | AA44: LM1 | AC44: 0
A45: Alat peraga | F45: =IF($AA45="","",SUMIF(Bakademik1,AA45,Bakademik2)) -> 0 | G45: =IF($AA45="","",SUMIF(BDaksos1,AA45,BDaksos2)) -> 0 | H45: =IF($AA45="","",SUMIF(BDukunganAka1,AA45,BDukunganAka2)) -> 0 | I45: =IF($AA45="","",SUMIF(BKegiatanSantri1,AA45,BKegiatanSantri2)) -> 0 | J45: =IF($AA45="","",SUMIF(DukunganInstitusi1,AA45,DukunganInstitusi2)) -> 0 | K45: =IF($AA45="","",SUMIF(BPemeliharaan1,AA45,BPemeliharaan2)) -> 0 | L45: =IF($AA45="","",SUMIF(BBantuan1,AA45,BBantuan2)) -> 0 | M45: =IF($AA45="","",SUMIF(BPenjualan1,AA45,BPenjualan2)) -> 0 | N45: =IF($AA45="","",SUMIF(BLayananAsrama1,AA45,BlayananAsrama2)) -> 0 | R45: =SUM(F45:Q45) -> 0 | T45: 0 | V45: =R45+AC45 -> 0 | Z45: Visual aid | AA45: LM2 | AC45: 0
A46: Buku panduan | F46: =IF($AA46="","",SUMIF(Bakademik1,AA46,Bakademik2)) -> 0 | G46: =IF($AA46="","",SUMIF(BDaksos1,AA46,BDaksos2)) -> 0 | H46: =IF($AA46="","",SUMIF(BDukunganAka1,AA46,BDukunganAka2)) -> 0 | I46: =IF($AA46="","",SUMIF(BKegiatanSantri1,AA46,BKegiatanSantri2)) -> 0 | J46: =IF($AA46="","",SUMIF(DukunganInstitusi1,AA46,DukunganInstitusi2)) -> 0 | K46: =IF($AA46="","",SUMIF(BPemeliharaan1,AA46,BPemeliharaan2)) -> 0 | L46: =IF($AA46="","",SUMIF(BBantuan1,AA46,BBantuan2)) -> 0 | M46: =IF($AA46="","",SUMIF(BPenjualan1,AA46,BPenjualan2)) -> 0 | N46: =IF($AA46="","",SUMIF(BLayananAsrama1,AA46,BlayananAsrama2)) -> 0 | R46: =SUM(F46:Q46) -> 0 | T46: 0 | V46: =R46+AC46 -> 0 | Z46: Text book | AA46: LM3 | AC46: 0
A47: CD pembelajaran | F47: =IF($AA47="","",SUMIF(Bakademik1,AA47,Bakademik2)) -> 0 | G47: =IF($AA47="","",SUMIF(BDaksos1,AA47,BDaksos2)) -> 0 | H47: =IF($AA47="","",SUMIF(BDukunganAka1,AA47,BDukunganAka2)) -> 0 | I47: =IF($AA47="","",SUMIF(BKegiatanSantri1,AA47,BKegiatanSantri2)) -> 0 | J47: =IF($AA47="","",SUMIF(DukunganInstitusi1,AA47,DukunganInstitusi2)) -> 0 | K47: =IF($AA47="","",SUMIF(BPemeliharaan1,AA47,BPemeliharaan2)) -> 0 | L47: =IF($AA47="","",SUMIF(BBantuan1,AA47,BBantuan2)) -> 0 | M47: =IF($AA47="","",SUMIF(BPenjualan1,AA47,BPenjualan2)) -> 0 | N47: =IF($AA47="","",SUMIF(BLayananAsrama1,AA47,BlayananAsrama2)) -> 0 | R47: =SUM(F47:Q47) -> 0 | T47: 0 | V47: =R47+AC47 -> 0 | Z47: Leraning CD | AA47: LM4 | AC47: 0
A48: Keperluan olahraga | F48: =IF($AA48="","",SUMIF(Bakademik1,AA48,Bakademik2)) -> 0 | G48: =IF($AA48="","",SUMIF(BDaksos1,AA48,BDaksos2)) -> 0 | H48: =IF($AA48="","",SUMIF(BDukunganAka1,AA48,BDukunganAka2)) -> 0 | I48: =IF($AA48="","",SUMIF(BKegiatanSantri1,AA48,BKegiatanSantri2)) -> 0 | J48: =IF($AA48="","",SUMIF(DukunganInstitusi1,AA48,DukunganInstitusi2)) -> 0 | K48: =IF($AA48="","",SUMIF(BPemeliharaan1,AA48,BPemeliharaan2)) -> 0 | L48: =IF($AA48="","",SUMIF(BBantuan1,AA48,BBantuan2)) -> 0 | M48: =IF($AA48="","",SUMIF(BPenjualan1,AA48,BPenjualan2)) -> 0 | N48: =IF($AA48="","",SUMIF(BLayananAsrama1,AA48,BlayananAsrama2)) -> 0 | R48: =SUM(F48:Q48) -> 0 | T48: 0 | V48: =R48+AC48 -> 12527900 | Z48: Sport supplies | AA48: LM5 | AC48: 12527900
A49: Keperluan laboratorium | F49: =IF($AA49="","",SUMIF(Bakademik1,AA49,Bakademik2)) -> 0 | G49: =IF($AA49="","",SUMIF(BDaksos1,AA49,BDaksos2)) -> 0 | H49: =IF($AA49="","",SUMIF(BDukunganAka1,AA49,BDukunganAka2)) -> 0 | I49: =IF($AA49="","",SUMIF(BKegiatanSantri1,AA49,BKegiatanSantri2)) -> 0 | J49: =IF($AA49="","",SUMIF(DukunganInstitusi1,AA49,DukunganInstitusi2)) -> 0 | K49: =IF($AA49="","",SUMIF(BPemeliharaan1,AA49,BPemeliharaan2)) -> 0 | L49: =IF($AA49="","",SUMIF(BBantuan1,AA49,BBantuan2)) -> 0 | M49: =IF($AA49="","",SUMIF(BPenjualan1,AA49,BPenjualan2)) -> 0 | N49: =IF($AA49="","",SUMIF(BLayananAsrama1,AA49,BlayananAsrama2)) -> 0 | R49: =SUM(F49:Q49) -> 0 | T49: 0 | V49: =R49+AC49 -> 2721600 | Z49: Laboratorium suplies | AA49: LM6 | AC49: 2721600
A50: Keperluan kelas | F50: =IF($AA50="","",SUMIF(Bakademik1,AA50,Bakademik2)) -> 0 | G50: =IF($AA50="","",SUMIF(BDaksos1,AA50,BDaksos2)) -> 0 | H50: =IF($AA50="","",SUMIF(BDukunganAka1,AA50,BDukunganAka2)) -> 0 | I50: =IF($AA50="","",SUMIF(BKegiatanSantri1,AA50,BKegiatanSantri2)) -> 0 | J50: =IF($AA50="","",SUMIF(DukunganInstitusi1,AA50,DukunganInstitusi2)) -> 0 | K50: =IF($AA50="","",SUMIF(BPemeliharaan1,AA50,BPemeliharaan2)) -> 0 | L50: =IF($AA50="","",SUMIF(BBantuan1,AA50,BBantuan2)) -> 0 | M50: =IF($AA50="","",SUMIF(BPenjualan1,AA50,BPenjualan2)) -> 0 | N50: =IF($AA50="","",SUMIF(BLayananAsrama1,AA50,BlayananAsrama2)) -> 0 | R50: =SUM(F50:Q50) -> 0 | T50: 0 | V50: =R50+AC50 -> 9906900 | Z50: Class supplies | AA50: LM7 | AC50: 9906900
A51: Lain lain | F51: =IF($AA51="","",SUMIF(Bakademik1,AA51,Bakademik2)) -> 0 | G51: =IF($AA51="","",SUMIF(BDaksos1,AA51,BDaksos2)) -> 0 | H51: =IF($AA51="","",SUMIF(BDukunganAka1,AA51,BDukunganAka2)) -> 0 | I51: =IF($AA51="","",SUMIF(BKegiatanSantri1,AA51,BKegiatanSantri2)) -> 4761000 | J51: =IF($AA51="","",SUMIF(DukunganInstitusi1,AA51,DukunganInstitusi2)) -> 0 | K51: =IF($AA51="","",SUMIF(BPemeliharaan1,AA51,BPemeliharaan2)) -> 0 | L51: =IF($AA51="","",SUMIF(BBantuan1,AA51,BBantuan2)) -> 0 | M51: =IF($AA51="","",SUMIF(BPenjualan1,AA51,BPenjualan2)) -> 0 | N51: =IF($AA51="","",SUMIF(BLayananAsrama1,AA51,BlayananAsrama2)) -> 0 | R51: =SUM(F51:Q51) -> 4761000 | T51: 23755300 | V51: =R51+AC51 -> 252377500 | Z51: Others | AA51: LM8 | AC51: 247616500 | AD51: PSB & PWSB
F52: =SUM(F44:F51) -> 0 | G52: =SUM(G44:G51) -> 0 | H52: =SUM(H44:H51) -> 0 | I52: =SUM(I44:I51) -> 4761000 | J52: =SUM(J44:J51) -> 0 | K52: =SUM(K44:K51) -> 0 | L52: =SUM(L44:L51) -> 0 | M52: =SUM(M44:M51) -> 0 | ... S52: =SUM(S44:S51) -> 0 | T52: 23755300 | U52: =SUM(U44:U51) -> 0 | V52: =SUM(V44:V51) -> 277533900 | AA52: LM | AC52: 272772900
A53: Keperluan dapur | Z53: Kitchen supplies
A54: Beras | F54: =IF($AA54="","",SUMIF(Bakademik1,AA54,Bakademik2)) -> 0 | G54: =IF($AA54="","",SUMIF(BDaksos1,AA54,BDaksos2)) -> 0 | H54: =IF($AA54="","",SUMIF(BDukunganAka1,AA54,BDukunganAka2)) -> 0 | I54: =IF($AA54="","",SUMIF(BKegiatanSantri1,AA54,BKegiatanSantri2)) -> 0 | J54: =IF($AA54="","",SUMIF(DukunganInstitusi1,AA54,DukunganInstitusi2)) -> 0 | K54: =IF($AA54="","",SUMIF(BPemeliharaan1,AA54,BPemeliharaan2)) -> 0 | L54: =IF($AA54="","",SUMIF(BBantuan1,AA54,BBantuan2)) -> 0 | M54: =IF($AA54="","",SUMIF(BPenjualan1,AA54,BPenjualan2)) -> 0 | N54: =IF($AA54="","",SUMIF(BLayananAsrama1,AA54,BlayananAsrama2)) -> 1154500 | R54: =SUM(F54:Q54) -> 1154500 | T54: 48875000 | V54: =R54+AC54 -> 388777000 | Z54: Hulled rice | AA54: KS1 | AC54: 387622500
A55: Lauk pauk | F55: =IF($AA55="","",SUMIF(Bakademik1,AA55,Bakademik2)) -> 0 | G55: =IF($AA55="","",SUMIF(BDaksos1,AA55,BDaksos2)) -> 0 | H55: =IF($AA55="","",SUMIF(BDukunganAka1,AA55,BDukunganAka2)) -> 0 | I55: =IF($AA55="","",SUMIF(BKegiatanSantri1,AA55,BKegiatanSantri2)) -> 0 | J55: =IF($AA55="","",SUMIF(DukunganInstitusi1,AA55,DukunganInstitusi2)) -> 0 | K55: =IF($AA55="","",SUMIF(BPemeliharaan1,AA55,BPemeliharaan2)) -> 0 | L55: =IF($AA55="","",SUMIF(BBantuan1,AA55,BBantuan2)) -> 0 | M55: =IF($AA55="","",SUMIF(BPenjualan1,AA55,BPenjualan2)) -> 0 | N55: =IF($AA55="","",SUMIF(BLayananAsrama1,AA55,BlayananAsrama2)) -> 88281143 | R55: =SUM(F55:Q55) -> 88281143 | T55: 221620778 | V55: =R55+AC55 -> 1404006963 | Z55: Side dishes | AA55: KS2 | AC55: 1315725820
A56: Gula / teh / susu / kopi | F56: =IF($AA56="","",SUMIF(Bakademik1,AA56,Bakademik2)) -> 0 | G56: =IF($AA56="","",SUMIF(BDaksos1,AA56,BDaksos2)) -> 0 | H56: =IF($AA56="","",SUMIF(BDukunganAka1,AA56,BDukunganAka2)) -> 0 | I56: =IF($AA56="","",SUMIF(BKegiatanSantri1,AA56,BKegiatanSantri2)) -> 0 | J56: =IF($AA56="","",SUMIF(DukunganInstitusi1,AA56,DukunganInstitusi2)) -> 0 | K56: =IF($AA56="","",SUMIF(BPemeliharaan1,AA56,BPemeliharaan2)) -> 0 | L56: =IF($AA56="","",SUMIF(BBantuan1,AA56,BBantuan2)) -> 0 | M56: =IF($AA56="","",SUMIF(BPenjualan1,AA56,BPenjualan2)) -> 0 | N56: =IF($AA56="","",SUMIF(BLayananAsrama1,AA56,BlayananAsrama2)) -> 190000 | R56: =SUM(F56:Q56) -> 190000 | T56: 850000 | V56: =R56+AC56 -> 8530000 | Z56: Sugar / tee / milk / coffee | AA56: KS3 | AC56: 8340000
A57: Minyak tanah & gas elpiji | F57: =IF($AA57="","",SUMIF(Bakademik1,AA57,Bakademik2)) -> 0 | G57: =IF($AA57="","",SUMIF(BDaksos1,AA57,BDaksos2)) -> 0 | H57: =IF($AA57="","",SUMIF(BDukunganAka1,AA57,BDukunganAka2)) -> 0 | I57: =IF($AA57="","",SUMIF(BKegiatanSantri1,AA57,BKegiatanSantri2)) -> 0 | J57: =IF($AA57="","",SUMIF(DukunganInstitusi1,AA57,DukunganInstitusi2)) -> 0 | K57: =IF($AA57="","",SUMIF(BPemeliharaan1,AA57,BPemeliharaan2)) -> 0 | L57: =IF($AA57="","",SUMIF(BBantuan1,AA57,BBantuan2)) -> 0 | M57: =IF($AA57="","",SUMIF(BPenjualan1,AA57,BPenjualan2)) -> 0 | N57: =IF($AA57="","",SUMIF(BLayananAsrama1,AA57,BlayananAsrama2)) -> 2458000 | R57: =SUM(F57:Q57) -> 2458000 | T57: 3800000 | V57: =R57+AC57 -> 38731700 | Z57: Gas oil and gas | AA57: KS4 | AC57: 36273700
A58: Minyak goreng | F58: =IF($AA58="","",SUMIF(Bakademik1,AA58,Bakademik2)) -> 0 | G58: =IF($AA58="","",SUMIF(BDaksos1,AA58,BDaksos2)) -> 0 | H58: =IF($AA58="","",SUMIF(BDukunganAka1,AA58,BDukunganAka2)) -> 0 | I58: =IF($AA58="","",SUMIF(BKegiatanSantri1,AA58,BKegiatanSantri2)) -> 0 | J58: =IF($AA58="","",SUMIF(DukunganInstitusi1,AA58,DukunganInstitusi2)) -> 0 | K58: =IF($AA58="","",SUMIF(BPemeliharaan1,AA58,BPemeliharaan2)) -> 0 | L58: =IF($AA58="","",SUMIF(BBantuan1,AA58,BBantuan2)) -> 0 | M58: =IF($AA58="","",SUMIF(BPenjualan1,AA58,BPenjualan2)) -> 0 | N58: =IF($AA58="","",SUMIF(BLayananAsrama1,AA58,BlayananAsrama2)) -> 3060000 | R58: =SUM(F58:Q58) -> 3060000 | T58: 4985000 | V58: =R58+AC58 -> 54689000 | Z58: Coconut oil | AA58: KS5 | AC58: 51629000
A59: Lauk-pauk santri sakit | F59: =IF($AA59="","",SUMIF(Bakademik1,AA59,Bakademik2)) -> 0 | G59: =IF($AA59="","",SUMIF(BDaksos1,AA59,BDaksos2)) -> 0 | H59: =IF($AA59="","",SUMIF(BDukunganAka1,AA59,BDukunganAka2)) -> 0 | I59: =IF($AA59="","",SUMIF(BKegiatanSantri1,AA59,BKegiatanSantri2)) -> 0 | J59: =IF($AA59="","",SUMIF(DukunganInstitusi1,AA59,DukunganInstitusi2)) -> 0 | K59: =IF($AA59="","",SUMIF(BPemeliharaan1,AA59,BPemeliharaan2)) -> 0 | L59: =IF($AA59="","",SUMIF(BBantuan1,AA59,BBantuan2)) -> 0 | M59: =IF($AA59="","",SUMIF(BPenjualan1,AA59,BPenjualan2)) -> 0 | N59: =IF($AA59="","",SUMIF(BLayananAsrama1,AA59,BlayananAsrama2)) -> 0 | R59: =SUM(F59:Q59) -> 0 | T59: 76000 | V59: =R59+AC59 -> 669600 | Z59: Side dishes for student sick | AA59: KS6 | AC59: 669600
A60: Buah-buahan | F60: =IF($AA60="","",SUMIF(Bakademik1,AA60,Bakademik2)) -> 0 | G60: =IF($AA60="","",SUMIF(BDaksos1,AA60,BDaksos2)) -> 0 | H60: =IF($AA60="","",SUMIF(BDukunganAka1,AA60,BDukunganAka2)) -> 0 | I60: =IF($AA60="","",SUMIF(BKegiatanSantri1,AA60,BKegiatanSantri2)) -> 0 | J60: =IF($AA60="","",SUMIF(DukunganInstitusi1,AA60,DukunganInstitusi2)) -> 0 | K60: =IF($AA60="","",SUMIF(BPemeliharaan1,AA60,BPemeliharaan2)) -> 0 | L60: =IF($AA60="","",SUMIF(BBantuan1,AA60,BBantuan2)) -> 0 | M60: =IF($AA60="","",SUMIF(BPenjualan1,AA60,BPenjualan2)) -> 0 | N60: =IF($AA60="","",SUMIF(BLayananAsrama1,AA60,BlayananAsrama2)) -> 4458000 | R60: =SUM(F60:Q60) -> 4458000 | T60: 7239000 | V60: =R60+AC60 -> 47622000 | Z60: Fruits | AA60: KS7 | AC60: 43164000
A61: Perlengkapan dapur | F61: =IF($AA61="","",SUMIF(Bakademik1,AA61,Bakademik2)) -> 0 | G61: =IF($AA61="","",SUMIF(BDaksos1,AA61,BDaksos2)) -> 0 | H61: =IF($AA61="","",SUMIF(BDukunganAka1,AA61,BDukunganAka2)) -> 0 | I61: =IF($AA61="","",SUMIF(BKegiatanSantri1,AA61,BKegiatanSantri2)) -> 0 | J61: =IF($AA61="","",SUMIF(DukunganInstitusi1,AA61,DukunganInstitusi2)) -> 0 | K61: =IF($AA61="","",SUMIF(BPemeliharaan1,AA61,BPemeliharaan2)) -> 0 | L61: =IF($AA61="","",SUMIF(BBantuan1,AA61,BBantuan2)) -> 0 | M61: =IF($AA61="","",SUMIF(BPenjualan1,AA61,BPenjualan2)) -> 0 | N61: =IF($AA61="","",SUMIF(BLayananAsrama1,AA61,BlayananAsrama2)) -> 749600 | R61: =SUM(F61:Q61) -> 749600 | T61: 1589400 | V61: =R61+AC61 -> 12841265 | Z61: Kicthen fixture | AA61: KS8 | AC61: 12091665
F62: =SUM(F54:F61) -> 0 | G62: =SUM(G54:G61) -> 0 | H62: =SUM(H54:H61) -> 0 | I62: =SUM(I54:I61) -> 0 | J62: =SUM(J54:J61) -> 0 | K62: =SUM(K54:K61) -> 0 | L62: =SUM(L54:L61) -> 0 | M62: =SUM(M54:M61) -> 0 | ... S62: =SUM(S54:S61) -> 0 | T62: 289035178 | U62: =SUM(U54:U61) -> 0 | V62: =SUM(V54:V61) -> 1955867528 | AA62: KS | AC62: 1855516285
A63: Keperluan laundry | Z63: Laundry supplies
A64: Sabun cuci | F64: =IF($AA64="","",SUMIF(Bakademik1,AA64,Bakademik2)) -> 0 | G64: =IF($AA64="","",SUMIF(BDaksos1,AA64,BDaksos2)) -> 0 | H64: =IF($AA64="","",SUMIF(BDukunganAka1,AA64,BDukunganAka2)) -> 0 | I64: =IF($AA64="","",SUMIF(BKegiatanSantri1,AA64,BKegiatanSantri2)) -> 0 | J64: =IF($AA64="","",SUMIF(DukunganInstitusi1,AA64,DukunganInstitusi2)) -> 0 | K64: =IF($AA64="","",SUMIF(BPemeliharaan1,AA64,BPemeliharaan2)) -> 0 | L64: =IF($AA64="","",SUMIF(BBantuan1,AA64,BBantuan2)) -> 0 | M64: =IF($AA64="","",SUMIF(BPenjualan1,AA64,BPenjualan2)) -> 0 | N64: =IF($AA64="","",SUMIF(BLayananAsrama1,AA64,BlayananAsrama2)) -> 0 | R64: =SUM(F64:Q64) -> 0 | T64: 0 | V64: =R64+AC64 -> 0 | Z64: Detergent | AA64: LS1 | AC64: 0
A65: Pemutih pakaian | F65: =IF($AA65="","",SUMIF(Bakademik1,AA65,Bakademik2)) -> 0 | G65: =IF($AA65="","",SUMIF(BDaksos1,AA65,BDaksos2)) -> 0 | H65: =IF($AA65="","",SUMIF(BDukunganAka1,AA65,BDukunganAka2)) -> 0 | I65: =IF($AA65="","",SUMIF(BKegiatanSantri1,AA65,BKegiatanSantri2)) -> 0 | J65: =IF($AA65="","",SUMIF(DukunganInstitusi1,AA65,DukunganInstitusi2)) -> 0 | K65: =IF($AA65="","",SUMIF(BPemeliharaan1,AA65,BPemeliharaan2)) -> 0 | L65: =IF($AA65="","",SUMIF(BBantuan1,AA65,BBantuan2)) -> 0 | M65: =IF($AA65="","",SUMIF(BPenjualan1,AA65,BPenjualan2)) -> 0 | N65: =IF($AA65="","",SUMIF(BLayananAsrama1,AA65,BlayananAsrama2)) -> 0 | R65: =SUM(F65:Q65) -> 0 | T65: 0 | V65: =R65+AC65 -> 0 | Z65: Whitener | AA65: LS2 | AC65: 0
A66: Pewangi & pelembut | F66: =IF($AA66="","",SUMIF(Bakademik1,AA66,Bakademik2)) -> 0 | G66: =IF($AA66="","",SUMIF(BDaksos1,AA66,BDaksos2)) -> 0 | H66: =IF($AA66="","",SUMIF(BDukunganAka1,AA66,BDukunganAka2)) -> 0 | I66: =IF($AA66="","",SUMIF(BKegiatanSantri1,AA66,BKegiatanSantri2)) -> 0 | J66: =IF($AA66="","",SUMIF(DukunganInstitusi1,AA66,DukunganInstitusi2)) -> 0 | K66: =IF($AA66="","",SUMIF(BPemeliharaan1,AA66,BPemeliharaan2)) -> 0 | L66: =IF($AA66="","",SUMIF(BBantuan1,AA66,BBantuan2)) -> 0 | M66: =IF($AA66="","",SUMIF(BPenjualan1,AA66,BPenjualan2)) -> 0 | N66: =IF($AA66="","",SUMIF(BLayananAsrama1,AA66,BlayananAsrama2)) -> 0 | R66: =SUM(F66:Q66) -> 0 | T66: 0 | V66: =R66+AC66 -> 0 | Z66: Whitener & softener | AA66: LS3 | AC66: 0
A67: Perlengkapan laundry | F67: =IF($AA67="","",SUMIF(Bakademik1,AA67,Bakademik2)) -> 0 | G67: =IF($AA67="","",SUMIF(BDaksos1,AA67,BDaksos2)) -> 0 | H67: =IF($AA67="","",SUMIF(BDukunganAka1,AA67,BDukunganAka2)) -> 0 | I67: =IF($AA67="","",SUMIF(BKegiatanSantri1,AA67,BKegiatanSantri2)) -> 0 | J67: =IF($AA67="","",SUMIF(DukunganInstitusi1,AA67,DukunganInstitusi2)) -> 0 | K67: =IF($AA67="","",SUMIF(BPemeliharaan1,AA67,BPemeliharaan2)) -> 0 | L67: =IF($AA67="","",SUMIF(BBantuan1,AA67,BBantuan2)) -> 0 | M67: =IF($AA67="","",SUMIF(BPenjualan1,AA67,BPenjualan2)) -> 0 | N67: =IF($AA67="","",SUMIF(BLayananAsrama1,AA67,BlayananAsrama2)) -> 0 | R67: =SUM(F67:Q67) -> 0 | T67: 0 | V67: =R67+AC67 -> 0 | Z67: Laundry fixture | AA67: LS4 | AC67: 0
F68: =SUM(F64:F67) -> 0 | G68: =SUM(G64:G67) -> 0 | H68: =SUM(H64:H67) -> 0 | I68: =SUM(I64:I67) -> 0 | J68: =SUM(J64:J67) -> 0 | K68: =SUM(K64:K67) -> 0 | L68: =SUM(L64:L67) -> 0 | M68: =SUM(M64:M67) -> 0 | ... S68: =SUM(S64:S67) -> 0 | T68: 0 | U68: =SUM(U64:U67) -> 0 | V68: =SUM(V64:V67) -> 0 | AA68: LS | AC68: 0
A69: Keperluan klinik | Z69: Clinic supplies
A70: Obat | F70: =IF($AA70="","",SUMIF(Bakademik1,AA70,Bakademik2)) -> 0 | G70: =IF($AA70="","",SUMIF(BDaksos1,AA70,BDaksos2)) -> 0 | H70: =IF($AA70="","",SUMIF(BDukunganAka1,AA70,BDukunganAka2)) -> 0 | I70: =IF($AA70="","",SUMIF(BKegiatanSantri1,AA70,BKegiatanSantri2)) -> 2252100 | J70: =IF($AA70="","",SUMIF(DukunganInstitusi1,AA70,DukunganInstitusi2)) -> 0 | K70: =IF($AA70="","",SUMIF(BPemeliharaan1,AA70,BPemeliharaan2)) -> 0 | L70: =IF($AA70="","",SUMIF(BBantuan1,AA70,BBantuan2)) -> 0 | M70: =IF($AA70="","",SUMIF(BPenjualan1,AA70,BPenjualan2)) -> 0 | N70: =IF($AA70="","",SUMIF(BLayananAsrama1,AA70,BlayananAsrama2)) -> 0 | R70: =SUM(F70:Q70) -> 2252100 | T70: 1509500 | V70: =R70+AC70 -> 32924700 | Z70: Medicine | AA70: CL1 | AC70: 30672600
A71: Bahan dan alat habis pakai | F71: =IF($AA71="","",SUMIF(Bakademik1,AA71,Bakademik2)) -> 0 | G71: =IF($AA71="","",SUMIF(BDaksos1,AA71,BDaksos2)) -> 0 | H71: =IF($AA71="","",SUMIF(BDukunganAka1,AA71,BDukunganAka2)) -> 0 | I71: =IF($AA71="","",SUMIF(BKegiatanSantri1,AA71,BKegiatanSantri2)) -> 186500 | J71: =IF($AA71="","",SUMIF(DukunganInstitusi1,AA71,DukunganInstitusi2)) -> 0 | K71: =IF($AA71="","",SUMIF(BPemeliharaan1,AA71,BPemeliharaan2)) -> 0 | L71: =IF($AA71="","",SUMIF(BBantuan1,AA71,BBantuan2)) -> 0 | M71: =IF($AA71="","",SUMIF(BPenjualan1,AA71,BPenjualan2)) -> 0 | N71: =IF($AA71="","",SUMIF(BLayananAsrama1,AA71,BlayananAsrama2)) -> 0 | R71: =SUM(F71:Q71) -> 186500 | T71: 0 | V71: =R71+AC71 -> 2062300 | Z71: Material and tool one use | AA71: CL2 | AC71: 1875800
F72: =SUM(F70:F71) -> 0 | G72: =SUM(G70:G71) -> 0 | H72: =SUM(H70:H71) -> 0 | I72: =SUM(I70:I71) -> 2438600 | J72: =SUM(J70:J71) -> 0 | K72: =SUM(K70:K71) -> 0 | L72: =SUM(L70:L71) -> 0 | M72: =SUM(M70:M71) -> 0 | ... S72: =SUM(S70:S71) -> 0 | T72: 1509500 | U72: =SUM(U70:U71) -> 0 | V72: =SUM(V70:V71) -> 34987000 | AA72: CL | AC72: 32548400
A73: Keperluan kebersihan | Z73: Cleaning supplies
A74: Sapu | F74: =IF($AA74="","",SUMIF(Bakademik1,AA74,Bakademik2)) -> 0 | G74: =IF($AA74="","",SUMIF(BDaksos1,AA74,BDaksos2)) -> 0 | H74: =IF($AA74="","",SUMIF(BDukunganAka1,AA74,BDukunganAka2)) -> 0 | I74: =IF($AA74="","",SUMIF(BKegiatanSantri1,AA74,BKegiatanSantri2)) -> 0 | J74: =IF($AA74="","",SUMIF(DukunganInstitusi1,AA74,DukunganInstitusi2)) -> 0 | K74: =IF($AA74="","",SUMIF(BPemeliharaan1,AA74,BPemeliharaan2)) -> 0 | L74: =IF($AA74="","",SUMIF(BBantuan1,AA74,BBantuan2)) -> 0 | M74: =IF($AA74="","",SUMIF(BPenjualan1,AA74,BPenjualan2)) -> 0 | N74: =IF($AA74="","",SUMIF(BLayananAsrama1,AA74,BlayananAsrama2)) -> 0 | R74: =SUM(F74:Q74) -> 0 | T74: 0 | V74: =R74+AC74 -> 38000 | Z74: Broom | AA74: CS1 | AC74: 38000
A75: Alat pel | F75: =IF($AA75="","",SUMIF(Bakademik1,AA75,Bakademik2)) -> 0 | G75: =IF($AA75="","",SUMIF(BDaksos1,AA75,BDaksos2)) -> 0 | H75: =IF($AA75="","",SUMIF(BDukunganAka1,AA75,BDukunganAka2)) -> 0 | I75: =IF($AA75="","",SUMIF(BKegiatanSantri1,AA75,BKegiatanSantri2)) -> 0 | J75: =IF($AA75="","",SUMIF(DukunganInstitusi1,AA75,DukunganInstitusi2)) -> 0 | K75: =IF($AA75="","",SUMIF(BPemeliharaan1,AA75,BPemeliharaan2)) -> 0 | L75: =IF($AA75="","",SUMIF(BBantuan1,AA75,BBantuan2)) -> 0 | M75: =IF($AA75="","",SUMIF(BPenjualan1,AA75,BPenjualan2)) -> 0 | N75: =IF($AA75="","",SUMIF(BLayananAsrama1,AA75,BlayananAsrama2)) -> 0 | R75: =SUM(F75:Q75) -> 0 | T75: 0 | V75: =R75+AC75 -> 6682528 | Z75: Mop | AA75: CS2 | AC75: 6682528
A76: Kain pel | F76: =IF($AA76="","",SUMIF(Bakademik1,AA76,Bakademik2)) -> 0 | G76: =IF($AA76="","",SUMIF(BDaksos1,AA76,BDaksos2)) -> 0 | H76: =IF($AA76="","",SUMIF(BDukunganAka1,AA76,BDukunganAka2)) -> 0 | I76: =IF($AA76="","",SUMIF(BKegiatanSantri1,AA76,BKegiatanSantri2)) -> 0 | J76: =IF($AA76="","",SUMIF(DukunganInstitusi1,AA76,DukunganInstitusi2)) -> 0 | K76: =IF($AA76="","",SUMIF(BPemeliharaan1,AA76,BPemeliharaan2)) -> 0 | L76: =IF($AA76="","",SUMIF(BBantuan1,AA76,BBantuan2)) -> 0 | M76: =IF($AA76="","",SUMIF(BPenjualan1,AA76,BPenjualan2)) -> 0 | N76: =IF($AA76="","",SUMIF(BLayananAsrama1,AA76,BlayananAsrama2)) -> 0 | R76: =SUM(F76:Q76) -> 0 | T76: 741950 | V76: =R76+AC76 -> 2557797 | Z76: Mop linen | AA76: CS3 | AC76: 2557797
A77: Tempat sampah | F77: =IF($AA77="","",SUMIF(Bakademik1,AA77,Bakademik2)) -> 0 | G77: =IF($AA77="","",SUMIF(BDaksos1,AA77,BDaksos2)) -> 0 | H77: =IF($AA77="","",SUMIF(BDukunganAka1,AA77,BDukunganAka2)) -> 0 | I77: =IF($AA77="","",SUMIF(BKegiatanSantri1,AA77,BKegiatanSantri2)) -> 0 | J77: =IF($AA77="","",SUMIF(DukunganInstitusi1,AA77,DukunganInstitusi2)) -> 0 | K77: =IF($AA77="","",SUMIF(BPemeliharaan1,AA77,BPemeliharaan2)) -> 369000 | L77: =IF($AA77="","",SUMIF(BBantuan1,AA77,BBantuan2)) -> 0 | M77: =IF($AA77="","",SUMIF(BPenjualan1,AA77,BPenjualan2)) -> 0 | N77: =IF($AA77="","",SUMIF(BLayananAsrama1,AA77,BlayananAsrama2)) -> 0 | R77: =SUM(F77:Q77) -> 369000 | T77: 732200 | V77: =R77+AC77 -> 3736700 | Z77: Trash can | AA77: CS4 | AC77: 3367700
A78: Pembersih | F78: =IF($AA78="","",SUMIF(Bakademik1,AA78,Bakademik2)) -> 0 | G78: =IF($AA78="","",SUMIF(BDaksos1,AA78,BDaksos2)) -> 0 | H78: =IF($AA78="","",SUMIF(BDukunganAka1,AA78,BDukunganAka2)) -> 0 | I78: =IF($AA78="","",SUMIF(BKegiatanSantri1,AA78,BKegiatanSantri2)) -> 0 | J78: =IF($AA78="","",SUMIF(DukunganInstitusi1,AA78,DukunganInstitusi2)) -> 0 | K78: =IF($AA78="","",SUMIF(BPemeliharaan1,AA78,BPemeliharaan2)) -> 4655000 | L78: =IF($AA78="","",SUMIF(BBantuan1,AA78,BBantuan2)) -> 0 | M78: =IF($AA78="","",SUMIF(BPenjualan1,AA78,BPenjualan2)) -> 0 | N78: =IF($AA78="","",SUMIF(BLayananAsrama1,AA78,BlayananAsrama2)) -> 0 | R78: =SUM(F78:Q78) -> 4655000 | T78: 4546100 | V78: =R78+AC78 -> 43600363 | Z78: Material cleaner | AA78: CS5 | AC78: 38945363
A79: Penyegar ruangan | F79: =IF($AA79="","",SUMIF(Bakademik1,AA79,Bakademik2)) -> 0 | G79: =IF($AA79="","",SUMIF(BDaksos1,AA79,BDaksos2)) -> 0 | H79: =IF($AA79="","",SUMIF(BDukunganAka1,AA79,BDukunganAka2)) -> 0 | I79: =IF($AA79="","",SUMIF(BKegiatanSantri1,AA79,BKegiatanSantri2)) -> 0 | J79: =IF($AA79="","",SUMIF(DukunganInstitusi1,AA79,DukunganInstitusi2)) -> 0 | K79: =IF($AA79="","",SUMIF(BPemeliharaan1,AA79,BPemeliharaan2)) -> 0 | L79: =IF($AA79="","",SUMIF(BBantuan1,AA79,BBantuan2)) -> 0 | M79: =IF($AA79="","",SUMIF(BPenjualan1,AA79,BPenjualan2)) -> 0 | N79: =IF($AA79="","",SUMIF(BLayananAsrama1,AA79,BlayananAsrama2)) -> 0 | R79: =SUM(F79:Q79) -> 0 | T79: 317000 | V79: =R79+AC79 -> 5106813 | Z79: Freshener | AA79: CS6 | AC79: 5106813
A80: Lain lain | F80: =IF($AA80="","",SUMIF(Bakademik1,AA80,Bakademik2)) -> 0 | G80: =IF($AA80="","",SUMIF(BDaksos1,AA80,BDaksos2)) -> 0 | H80: =IF($AA80="","",SUMIF(BDukunganAka1,AA80,BDukunganAka2)) -> 0 | I80: =IF($AA80="","",SUMIF(BKegiatanSantri1,AA80,BKegiatanSantri2)) -> 0 | J80: =IF($AA80="","",SUMIF(DukunganInstitusi1,AA80,DukunganInstitusi2)) -> 0 | K80: =IF($AA80="","",SUMIF(BPemeliharaan1,AA80,BPemeliharaan2)) -> 0 | L80: =IF($AA80="","",SUMIF(BBantuan1,AA80,BBantuan2)) -> 0 | M80: =IF($AA80="","",SUMIF(BPenjualan1,AA80,BPenjualan2)) -> 0 | N80: =IF($AA80="","",SUMIF(BLayananAsrama1,AA80,BlayananAsrama2)) -> 0 | R80: =SUM(F80:Q80) -> 0 | T80: 572150 | V80: =R80+AC80 -> 7955700 | Z80: Others | AA80: CS7 | AC80: 7955700
F81: =SUM(F74:F80) -> 0 | G81: =SUM(G74:G80) -> 0 | H81: =SUM(H74:H80) -> 0 | I81: =SUM(I74:I80) -> 0 | J81: =SUM(J74:J80) -> 0 | K81: =SUM(K74:K80) -> 5024000 | L81: =SUM(L74:L80) -> 0 | M81: =SUM(M74:M80) -> 0 | ... S81: =SUM(S74:S80) -> 0 | T81: 6909400 | U81: =SUM(U74:U80) -> 0 | V81: =SUM(V74:V80) -> 69677901 | AA81: CS | AC81: 64653901
A82: Keperluan asrama | Z82: Boarding supplies
A83: Sprei dan sarung bantal | F83: =IF($AA83="","",SUMIF(Bakademik1,AA83,Bakademik2)) -> 0 | G83: =IF($AA83="","",SUMIF(BDaksos1,AA83,BDaksos2)) -> 0 | H83: =IF($AA83="","",SUMIF(BDukunganAka1,AA83,BDukunganAka2)) -> 0 | I83: =IF($AA83="","",SUMIF(BKegiatanSantri1,AA83,BKegiatanSantri2)) -> 0 | J83: =IF($AA83="","",SUMIF(DukunganInstitusi1,AA83,DukunganInstitusi2)) -> 0 | K83: =IF($AA83="","",SUMIF(BPemeliharaan1,AA83,BPemeliharaan2)) -> 0 | L83: =IF($AA83="","",SUMIF(BBantuan1,AA83,BBantuan2)) -> 0 | M83: =IF($AA83="","",SUMIF(BPenjualan1,AA83,BPenjualan2)) -> 0 | N83: =IF($AA83="","",SUMIF(BLayananAsrama1,AA83,BlayananAsrama2)) -> 0 | R83: =SUM(F83:Q83) -> 0 | T83: 0 | V83: =R83+AC83 -> 105550 | Z83: Bedcovers | AA83: BS1 | AC83: 105550
A84: Selimut | F84: =IF($AA84="","",SUMIF(Bakademik1,AA84,Bakademik2)) -> 0 | G84: =IF($AA84="","",SUMIF(BDaksos1,AA84,BDaksos2)) -> 0 | H84: =IF($AA84="","",SUMIF(BDukunganAka1,AA84,BDukunganAka2)) -> 0 | I84: =IF($AA84="","",SUMIF(BKegiatanSantri1,AA84,BKegiatanSantri2)) -> 0 | J84: =IF($AA84="","",SUMIF(DukunganInstitusi1,AA84,DukunganInstitusi2)) -> 0 | K84: =IF($AA84="","",SUMIF(BPemeliharaan1,AA84,BPemeliharaan2)) -> 0 | L84: =IF($AA84="","",SUMIF(BBantuan1,AA84,BBantuan2)) -> 0 | M84: =IF($AA84="","",SUMIF(BPenjualan1,AA84,BPenjualan2)) -> 0 | N84: =IF($AA84="","",SUMIF(BLayananAsrama1,AA84,BlayananAsrama2)) -> 0 | R84: =SUM(F84:Q84) -> 0 | T84: 0 | V84: =R84+AC84 -> 0 | Z84: Blanket | AA84: BS2 | AC84: 0
A85: Korden | F85: =IF($AA85="","",SUMIF(Bakademik1,AA85,Bakademik2)) -> 0 | G85: =IF($AA85="","",SUMIF(BDaksos1,AA85,BDaksos2)) -> 0 | H85: =IF($AA85="","",SUMIF(BDukunganAka1,AA85,BDukunganAka2)) -> 0 | I85: =IF($AA85="","",SUMIF(BKegiatanSantri1,AA85,BKegiatanSantri2)) -> 0 | J85: =IF($AA85="","",SUMIF(DukunganInstitusi1,AA85,DukunganInstitusi2)) -> 0 | K85: =IF($AA85="","",SUMIF(BPemeliharaan1,AA85,BPemeliharaan2)) -> 0 | L85: =IF($AA85="","",SUMIF(BBantuan1,AA85,BBantuan2)) -> 0 | M85: =IF($AA85="","",SUMIF(BPenjualan1,AA85,BPenjualan2)) -> 0 | N85: =IF($AA85="","",SUMIF(BLayananAsrama1,AA85,BlayananAsrama2)) -> 0 | R85: =SUM(F85:Q85) -> 0 | T85: 0 | V85: =R85+AC85 -> 0 | Z85: Gorden | AA85: BS3 | AC85: 0
A86: Gayung dan timba | F86: =IF($AA86="","",SUMIF(Bakademik1,AA86,Bakademik2)) -> 0 | G86: =IF($AA86="","",SUMIF(BDaksos1,AA86,BDaksos2)) -> 0 | H86: =IF($AA86="","",SUMIF(BDukunganAka1,AA86,BDukunganAka2)) -> 0 | I86: =IF($AA86="","",SUMIF(BKegiatanSantri1,AA86,BKegiatanSantri2)) -> 0 | J86: =IF($AA86="","",SUMIF(DukunganInstitusi1,AA86,DukunganInstitusi2)) -> 0 | K86: =IF($AA86="","",SUMIF(BPemeliharaan1,AA86,BPemeliharaan2)) -> 0 | L86: =IF($AA86="","",SUMIF(BBantuan1,AA86,BBantuan2)) -> 0 | M86: =IF($AA86="","",SUMIF(BPenjualan1,AA86,BPenjualan2)) -> 0 | N86: =IF($AA86="","",SUMIF(BLayananAsrama1,AA86,BlayananAsrama2)) -> 0 | R86: =SUM(F86:Q86) -> 0 | T86: 0 | V86: =R86+AC86 -> 0 | Z86: Scoop and pail | AA86: BS4 | AC86: 0
A87: Perlengkapan kamar | F87: =IF($AA87="","",SUMIF(Bakademik1,AA87,Bakademik2)) -> 0 | G87: =IF($AA87="","",SUMIF(BDaksos1,AA87,BDaksos2)) -> 0 | H87: =IF($AA87="","",SUMIF(BDukunganAka1,AA87,BDukunganAka2)) -> 0 | I87: =IF($AA87="","",SUMIF(BKegiatanSantri1,AA87,BKegiatanSantri2)) -> 0 | J87: =IF($AA87="","",SUMIF(DukunganInstitusi1,AA87,DukunganInstitusi2)) -> 0 | K87: =IF($AA87="","",SUMIF(BPemeliharaan1,AA87,BPemeliharaan2)) -> 0 | L87: =IF($AA87="","",SUMIF(BBantuan1,AA87,BBantuan2)) -> 0 | M87: =IF($AA87="","",SUMIF(BPenjualan1,AA87,BPenjualan2)) -> 0 | N87: =IF($AA87="","",SUMIF(BLayananAsrama1,AA87,BlayananAsrama2)) -> 0 | R87: =SUM(F87:Q87) -> 0 | S87: =SUM(G87:R87) -> 0 | T87: 0 | V87: =R87+AC87 -> 0 | Z87: Room supplies | AA87: BS5 | AC87: 0
A88: Perlengkapan area asrama | F88: =IF($AA88="","",SUMIF(Bakademik1,AA88,Bakademik2)) -> 0 | G88: =IF($AA88="","",SUMIF(BDaksos1,AA88,BDaksos2)) -> 0 | H88: =IF($AA88="","",SUMIF(BDukunganAka1,AA88,BDukunganAka2)) -> 0 | I88: =IF($AA88="","",SUMIF(BKegiatanSantri1,AA88,BKegiatanSantri2)) -> 0 | J88: =IF($AA88="","",SUMIF(DukunganInstitusi1,AA88,DukunganInstitusi2)) -> 0 | K88: =IF($AA88="","",SUMIF(BPemeliharaan1,AA88,BPemeliharaan2)) -> 0 | L88: =IF($AA88="","",SUMIF(BBantuan1,AA88,BBantuan2)) -> 0 | M88: =IF($AA88="","",SUMIF(BPenjualan1,AA88,BPenjualan2)) -> 0 | N88: =IF($AA88="","",SUMIF(BLayananAsrama1,AA88,BlayananAsrama2)) -> 0 | R88: =SUM(F88:Q88) -> 0 | T88: 0 | V88: =R88+AC88 -> 40000 | Z88: Dormitory supplies | AA88: BS6 | AC88: 40000
F89: =SUM(F83:F88) -> 0 | G89: =SUM(G83:G88) -> 0 | H89: =SUM(H83:H88) -> 0 | I89: =SUM(I83:I88) -> 0 | J89: =SUM(J83:J88) -> 0 | K89: =SUM(K83:K88) -> 0 | L89: =SUM(L83:L88) -> 0 | M89: =SUM(M83:M88) -> 0 | ... S89: =SUM(S83:S88) -> 0 | T89: 0 | U89: =SUM(U83:U88) -> 0 | V89: =SUM(V83:V88) -> 145550 | AA89: BS | AC89: 145550
A90: Keperluan lain lain | V90: =R90+AC90 -> 0 | Z90: Other supplies | AC90: 0
A91: Perlengkapan satpam | F91: =IF($AA91="","",SUMIF(Bakademik1,AA91,Bakademik2)) -> 0 | G91: =IF($AA91="","",SUMIF(BDaksos1,AA91,BDaksos2)) -> 0 | H91: =IF($AA91="","",SUMIF(BDukunganAka1,AA91,BDukunganAka2)) -> 0 | I91: =IF($AA91="","",SUMIF(BKegiatanSantri1,AA91,BKegiatanSantri2)) -> 0 | J91: =IF($AA91="","",SUMIF(DukunganInstitusi1,AA91,DukunganInstitusi2)) -> 0 | K91: =IF($AA91="","",SUMIF(BPemeliharaan1,AA91,BPemeliharaan2)) -> 0 | L91: =IF($AA91="","",SUMIF(BBantuan1,AA91,BBantuan2)) -> 0 | M91: =IF($AA91="","",SUMIF(BPenjualan1,AA91,BPenjualan2)) -> 0 | N91: =IF($AA91="","",SUMIF(BLayananAsrama1,AA91,BlayananAsrama2)) -> 0 | R91: =SUM(F91:Q91) -> 0 | T91: 0 | V91: =R91+AC91 -> 1060000 | Z91: Security supplies | AA91: OT1 | AC91: 1060000
A92: Perlengkapan gudang | F92: =IF($AA92="","",SUMIF(Bakademik1,AA92,Bakademik2)) -> 0 | G92: =IF($AA92="","",SUMIF(BDaksos1,AA92,BDaksos2)) -> 0 | H92: =IF($AA92="","",SUMIF(BDukunganAka1,AA92,BDukunganAka2)) -> 0 | I92: =IF($AA92="","",SUMIF(BKegiatanSantri1,AA92,BKegiatanSantri2)) -> 0 | J92: =IF($AA92="","",SUMIF(DukunganInstitusi1,AA92,DukunganInstitusi2)) -> 0 | K92: =IF($AA92="","",SUMIF(BPemeliharaan1,AA92,BPemeliharaan2)) -> 0 | L92: =IF($AA92="","",SUMIF(BBantuan1,AA92,BBantuan2)) -> 0 | M92: =IF($AA92="","",SUMIF(BPenjualan1,AA92,BPenjualan2)) -> 0 | N92: =IF($AA92="","",SUMIF(BLayananAsrama1,AA92,BlayananAsrama2)) -> 0 | R92: =SUM(F92:Q92) -> 0 | T92: 0 | V92: =R92+AC92 -> 0 | Z92: Warehouse supplies | AA92: OT2 | AC92: 0
